Workbook
Name NewMatrix: #REF!
Name RiskAutoStopPercChange: 1.5
Name RiskCorrelationSheet: #REF!
Name RiskExcelReportsGoInNewWorkbook: TRUE
Name RiskExcelReportsToGenerate: 0
Name RiskGenerateExcelReportsAtEndOfSimulation: FALSE
Name RiskRealTimeResults: FALSE
Name RiskReportGraphFormat: 0
Name RiskResultsUpdateFreq: 100
Name RiskShowRiskWindowAtEndOfSimulation: FALSE
Name RiskStatFunctionsUpdateFreq: 1
Name RiskTemplateSheetName: "myTemplate"
Name RiskUpdateStatFunctions: TRUE
Name sss: #REF!

Sheet RiskRGStrategic Cnv 2R34C1
Z1: -7178233
J2: Bin | K2: Height | Z2: 49892664
J3: -7270758.4 | K3: 23.499545 | Z3: 14850692
J4: 1793246.8 | K4: 17.98322
J5: 10857252 | K5: 20.962036
J6: 19921257 | K6: 19.196812
J7: 28985262 | K7: 11.142977
J8: 38049268 | K8: 7.8331818
J9: 47113273 | K9: 4.9646927
J10: 56177278 | K10: 2.6478361
J11: 65241283 | K11: 1.2135915
J12: 74305288 | K12: 0.55163252
J13: 83369293 | K13: 0.33097951
A4001: -11802761 | B4001: 0
A4002: -11802761 | B4002: =$K$3 -> 23.499545
A4003: -2738755.8 | B4003: =$K$3 -> 23.499545
A4004: -2738755.8 | B4004: 0
A4005: -2738755.8 | B4005: =$K$4 -> 17.98322
A4006: 6325249.4 | B4006: =$K$4 -> 17.98322
A4007: 6325249.4 | B4007: 0
A4008: 6325249.4 | B4008: =$K$5 -> 20.962036
A4009: 15389255 | B4009: =$K$5 -> 20.962036
A4010: 15389255 | B4010: 0
A4011: 15389255 | B4011: =$K$6 -> 19.196812
A4012: 24453260 | B4012: =$K$6 -> 19.196812
A4013: 24453260 | B4013: 0
A4014: 24453260 | B4014: =$K$7 -> 11.142977
A4015: 33517265 | B4015: =$K$7 -> 11.142977
A4016: 33517265 | B4016: 0
A4017: 33517265 | B4017: =$K$8 -> 7.8331818
A4018: 42581270 | B4018: =$K$8 -> 7.8331818
A4019: 42581270 | B4019: 0
A4020: 42581270 | B4020: =$K$9 -> 4.9646927
A4021: 51645275 | B4021: =$K$9 -> 4.9646927
A4022: 51645275 | B4022: 0
A4023: 51645275 | B4023: =$K$10 -> 2.6478361
A4024: 60709280 | B4024: =$K$10 -> 2.6478361
A4025: 60709280 | B4025: 0
A4026: 60709280 | B4026: =$K$11 -> 1.2135915
A4027: 69773286 | B4027: =$K$11 -> 1.2135915
A4028: 69773286 | B4028: 0
A4029: 69773286 | B4029: =$K$12 -> 0.55163252
A4030: 78837291 | B4030: =$K$12 -> 0.55163252
A4031: 78837291 | B4031: 0
A4032: 78837291 | B4032: =$K$13 -> 0.33097951
A4033: 87901296 | B4033: =$K$13 -> 0.33097951
A4034: 87901296 | B4034: 0
A5001: -11802761 | B5001: 0
A5002: -11802761 | B5002: =$K$3 -> 23.499545
A5003: -11703057 | B5003: =$K$3 -> 23.499545
A5004: -11703057 | B5004: 0
A5005: -11603353 | B5005: 0
A5006: -11603353 | B5006: =$K$3 -> 23.499545
A5007: -11503649 | B5007: =$K$3 -> 23.499545
A5008: -11503649 | B5008: 0
A5009: -11403945 | B5009: 0
A5010: -11403945 | B5010: =$K$3 -> 23.499545
A5011: -11304241 | B5011: =$K$3 -> 23.499545
A5012: -11304241 | B5012: 0
A5013: -11204537 | B5013: 0
A5014: -11204537 | B5014: =$K$3 -> 23.499545
A5015: -11104833 | B5015: =$K$3 -> 23.499545
A5016: -11104833 | B5016: 0
A5017: -11005129 | B5017: 0
A5018: -11005129 | B5018: =$K$3 -> 23.499545
A5019: -10905424 | B5019: =$K$3 -> 23.499545
A5020: -10905424 | B5020: 0
A5021: -10805720 | B5021: 0
A5022: -10805720 | B5022: =$K$3 -> 23.499545
A5023: -10706016 | B5023: =$K$3 -> 23.499545
A5024: -10706016 | B5024: 0
A5025: -10606312 | B5025: 0
A5026: -10606312 | B5026: =$K$3 -> 23.499545
A5027: -10506608 | B5027: =$K$3 -> 23.499545
A5028: -10506608 | B5028: 0
A5029: -10406904 | B5029: 0
A5030: -10406904 | B5030: =$K$3 -> 23.499545
A5031: -10307200 | B5031: =$K$3 -> 23.499545
A5032: -10307200 | B5032: 0
A5033: -10207496 | B5033: 0
A5034: -10207496 | B5034: =$K$3 -> 23.499545
A5035: -10107792 | B5035: =$K$3 -> 23.499545
A5036: -10107792 | B5036: 0
A5037: -10008088 | B5037: 0
A5038: -10008088 | B5038: =$K$3 -> 23.499545
A5039: -9908383.9 | B5039: =$K$3 -> 23.499545
A5040: -9908383.9 | B5040: 0
A5041: -9808679.9 | B5041: 0
A5042: -9808679.9 | B5042: =$K$3 -> 23.499545
A5043: -9708975.8 | B5043: =$K$3 -> 23.499545
A5044: -9708975.8 | B5044: 0
A5045: -9609271.7 | B5045: 0
A5046: -9609271.7 | B5046: =$K$3 -> 23.499545
A5047: -9509567.7 | B5047: =$K$3 -> 23.499545
A5048: -9509567.7 | B5048: 0
A5049: -9409863.6 | B5049: 0
A5050: -9409863.6 | B5050: =$K$3 -> 23.499545
A5051: -9310159.6 | B5051: =$K$3 -> 23.499545
A5052: -9310159.6 | B5052: 0
A5053: -9210455.5 | B5053: 0
...

Sheet RiskRGStrategic Cnv 2R36C1
Z1: -8431302
J2: Bin | K2: Height | Z2: 16203147
J3: -9746729 | K3: 23.527151 | Z3: 1610989.8
J4: -5708841.1 | K4: 50.521462
J5: -1670953.2 | K5: 45.073069
J6: 2366934.7 | K6: 46.063686
J7: 6404822.6 | K7: 37.395788
J8: 10442710 | K8: 20.555301
J9: 14480598 | K9: 12.630365
J10: 18518486 | K10: 6.6866641
J11: 22556374 | K11: 3.4671591
J12: 26594262 | K12: 0.9906169
J13: 30632150 | K13: 0.74296267
A4001: -11765673 | B4001: 0
A4002: -11765673 | B4002: =$K$3 -> 23.527151
A4003: -7727785.1 | B4003: =$K$3 -> 23.527151
A4004: -7727785.1 | B4004: 0
A4005: -7727785.1 | B4005: =$K$4 -> 50.521462
A4006: -3689897.2 | B4006: =$K$4 -> 50.521462
A4007: -3689897.2 | B4007: 0
A4008: -3689897.2 | B4008: =$K$5 -> 45.073069
A4009: 347990.73 | B4009: =$K$5 -> 45.073069
A4010: 347990.73 | B4010: 0
A4011: 347990.73 | B4011: =$K$6 -> 46.063686
A4012: 4385878.6 | B4012: =$K$6 -> 46.063686
A4013: 4385878.6 | B4013: 0
A4014: 4385878.6 | B4014: =$K$7 -> 37.395788
A4015: 8423766.5 | B4015: =$K$7 -> 37.395788
A4016: 8423766.5 | B4016: 0
A4017: 8423766.5 | B4017: =$K$8 -> 20.555301
A4018: 12461654 | B4018: =$K$8 -> 20.555301
A4019: 12461654 | B4019: 0
A4020: 12461654 | B4020: =$K$9 -> 12.630365
A4021: 16499542 | B4021: =$K$9 -> 12.630365
A4022: 16499542 | B4022: 0
A4023: 16499542 | B4023: =$K$10 -> 6.6866641
A4024: 20537430 | B4024: =$K$10 -> 6.6866641
A4025: 20537430 | B4025: 0
A4026: 20537430 | B4026: =$K$11 -> 3.4671591
A4027: 24575318 | B4027: =$K$11 -> 3.4671591
A4028: 24575318 | B4028: 0
A4029: 24575318 | B4029: =$K$12 -> 0.9906169
A4030: 28613206 | B4030: =$K$12 -> 0.9906169
A4031: 28613206 | B4031: 0
A4032: 28613206 | B4032: =$K$13 -> 0.74296267
A4033: 32651094 | B4033: =$K$13 -> 0.74296267
A4034: 32651094 | B4034: 0
A5001: -11765673 | B5001: 0
A5002: -11765673 | B5002: =$K$3 -> 23.527151
A5003: -11721256 | B5003: =$K$3 -> 23.527151
A5004: -11721256 | B5004: 0
A5005: -11676839 | B5005: 0
A5006: -11676839 | B5006: =$K$3 -> 23.527151
A5007: -11632423 | B5007: =$K$3 -> 23.527151
A5008: -11632423 | B5008: 0
A5009: -11588006 | B5009: 0
A5010: -11588006 | B5010: =$K$3 -> 23.527151
A5011: -11543589 | B5011: =$K$3 -> 23.527151
A5012: -11543589 | B5012: 0
A5013: -11499172 | B5013: 0
A5014: -11499172 | B5014: =$K$3 -> 23.527151
A5015: -11454756 | B5015: =$K$3 -> 23.527151
A5016: -11454756 | B5016: 0
A5017: -11410339 | B5017: 0
A5018: -11410339 | B5018: =$K$3 -> 23.527151
A5019: -11365922 | B5019: =$K$3 -> 23.527151
A5020: -11365922 | B5020: 0
A5021: -11321505 | B5021: 0
A5022: -11321505 | B5022: =$K$3 -> 23.527151
A5023: -11277089 | B5023: =$K$3 -> 23.527151
A5024: -11277089 | B5024: 0
A5025: -11232672 | B5025: 0
A5026: -11232672 | B5026: =$K$3 -> 23.527151
A5027: -11188255 | B5027: =$K$3 -> 23.527151
A5028: -11188255 | B5028: 0
A5029: -11143838 | B5029: 0
A5030: -11143838 | B5030: =$K$3 -> 23.527151
A5031: -11099421 | B5031: =$K$3 -> 23.527151
A5032: -11099421 | B5032: 0
A5033: -11055005 | B5033: 0
A5034: -11055005 | B5034: =$K$3 -> 23.527151
A5035: -11010588 | B5035: =$K$3 -> 23.527151
A5036: -11010588 | B5036: 0
A5037: -10966171 | B5037: 0
A5038: -10966171 | B5038: =$K$3 -> 23.527151
A5039: -10921754 | B5039: =$K$3 -> 23.527151
A5040: -10921754 | B5040: 0
A5041: -10877338 | B5041: 0
A5042: -10877338 | B5042: =$K$3 -> 23.527151
A5043: -10832921 | B5043: =$K$3 -> 23.527151
A5044: -10832921 | B5044: 0
A5045: -10788504 | B5045: 0
A5046: -10788504 | B5046: =$K$3 -> 23.527151
A5047: -10744087 | B5047: =$K$3 -> 23.527151
A5048: -10744087 | B5048: 0
A5049: -10699671 | B5049: 0
A5050: -10699671 | B5050: =$K$3 -> 23.527151
A5051: -10655254 | B5051: =$K$3 -> 23.527151
A5052: -10655254 | B5052: 0
A5053: -10610837 | B5053: 0
...

Sheet RiskRGStrategic Cnv 2R35C1
Z1: -8436326
J2: Bin | K2: Height | Z2: 17082860
J3: -9348674.5 | K3: 34.17105 | Z3: 1783241.9
J4: -5046787.4 | K4: 43.236839
J5: -744900.27 | K5: 46.026313
J6: 3556986.8 | K6: 44.166664
J7: 7858873.9 | K7: 27.662279
J8: 12160761 | K8: 17.899122
J9: 16462648 | K9: 10.460526
J10: 20764535 | K10: 5.3464909
J11: 25066422 | K11: 2.0921051
J12: 29368309 | K12: 0.9298245
J13: 33670196 | K13: 0.46491225
A4001: -11499618 | B4001: 0
A4002: -11499618 | B4002: =$K$3 -> 34.17105
A4003: -7197730.9 | B4003: =$K$3 -> 34.17105
A4004: -7197730.9 | B4004: 0
A4005: -7197730.9 | B4005: =$K$4 -> 43.236839
A4006: -2895843.8 | B4006: =$K$4 -> 43.236839
A4007: -2895843.8 | B4007: 0
A4008: -2895843.8 | B4008: =$K$5 -> 46.026313
A4009: 1406043.3 | B4009: =$K$5 -> 46.026313
A4010: 1406043.3 | B4010: 0
A4011: 1406043.3 | B4011: =$K$6 -> 44.166664
A4012: 5707930.4 | B4012: =$K$6 -> 44.166664
A4013: 5707930.4 | B4013: 0
A4014: 5707930.4 | B4014: =$K$7 -> 27.662279
A4015: 10009817 | B4015: =$K$7 -> 27.662279
A4016: 10009817 | B4016: 0
A4017: 10009817 | B4017: =$K$8 -> 17.899122
A4018: 14311705 | B4018: =$K$8 -> 17.899122
A4019: 14311705 | B4019: 0
A4020: 14311705 | B4020: =$K$9 -> 10.460526
A4021: 18613592 | B4021: =$K$9 -> 10.460526
A4022: 18613592 | B4022: 0
A4023: 18613592 | B4023: =$K$10 -> 5.3464909
A4024: 22915479 | B4024: =$K$10 -> 5.3464909
A4025: 22915479 | B4025: 0
A4026: 22915479 | B4026: =$K$11 -> 2.0921051
A4027: 27217366 | B4027: =$K$11 -> 2.0921051
A4028: 27217366 | B4028: 0
A4029: 27217366 | B4029: =$K$12 -> 0.9298245
A4030: 31519253 | B4030: =$K$12 -> 0.9298245
A4031: 31519253 | B4031: 0
A4032: 31519253 | B4032: =$K$13 -> 0.46491225
A4033: 35821140 | B4033: =$K$13 -> 0.46491225
A4034: 35821140 | B4034: 0
A5001: -11499618 | B5001: 0
A5002: -11499618 | B5002: =$K$3 -> 34.17105
A5003: -11452297 | B5003: =$K$3 -> 34.17105
A5004: -11452297 | B5004: 0
A5005: -11404976 | B5005: 0
A5006: -11404976 | B5006: =$K$3 -> 34.17105
A5007: -11357656 | B5007: =$K$3 -> 34.17105
A5008: -11357656 | B5008: 0
A5009: -11310335 | B5009: 0
A5010: -11310335 | B5010: =$K$3 -> 34.17105
A5011: -11263014 | B5011: =$K$3 -> 34.17105
A5012: -11263014 | B5012: 0
A5013: -11215693 | B5013: 0
A5014: -11215693 | B5014: =$K$3 -> 34.17105
A5015: -11168373 | B5015: =$K$3 -> 34.17105
A5016: -11168373 | B5016: 0
A5017: -11121052 | B5017: 0
A5018: -11121052 | B5018: =$K$3 -> 34.17105
A5019: -11073731 | B5019: =$K$3 -> 34.17105
A5020: -11073731 | B5020: 0
A5021: -11026410 | B5021: 0
A5022: -11026410 | B5022: =$K$3 -> 34.17105
A5023: -10979090 | B5023: =$K$3 -> 34.17105
A5024: -10979090 | B5024: 0
A5025: -10931769 | B5025: 0
A5026: -10931769 | B5026: =$K$3 -> 34.17105
A5027: -10884448 | B5027: =$K$3 -> 34.17105
A5028: -10884448 | B5028: 0
A5029: -10837127 | B5029: 0
A5030: -10837127 | B5030: =$K$3 -> 34.17105
A5031: -10789807 | B5031: =$K$3 -> 34.17105
A5032: -10789807 | B5032: 0
A5033: -10742486 | B5033: 0
A5034: -10742486 | B5034: =$K$3 -> 34.17105
A5035: -10695165 | B5035: =$K$3 -> 34.17105
A5036: -10695165 | B5036: 0
A5037: -10647844 | B5037: 0
A5038: -10647844 | B5038: =$K$3 -> 34.17105
A5039: -10600524 | B5039: =$K$3 -> 34.17105
A5040: -10600524 | B5040: 0
A5041: -10553203 | B5041: 0
A5042: -10553203 | B5042: =$K$3 -> 34.17105
A5043: -10505882 | B5043: =$K$3 -> 34.17105
A5044: -10505882 | B5044: 0
A5045: -10458561 | B5045: 0
A5046: -10458561 | B5046: =$K$3 -> 34.17105
A5047: -10411241 | B5047: =$K$3 -> 34.17105
A5048: -10411241 | B5048: 0
A5049: -10363920 | B5049: 0
A5050: -10363920 | B5050: =$K$3 -> 34.17105
A5051: -10316599 | B5051: =$K$3 -> 34.17105
A5052: -10316599 | B5052: 0
A5053: -10269278 | B5053: 0
...

Sheet RiskRGSheet1R33C1
Z1: -9.8195572
J2: Bin | K2: Height | Z2: 33.753624
J3: -32.107706 | K3: 0.12095782 | Z3: 12.079498
J4: -23.840362 | K4: 0.84670474
J5: -15.573017 | K5: 3.6287346
J6: -7.3056722 | K6: 10.402373
J7: 0.96167252 | K7: 21.167619
J8: 9.2290173 | K8: 28.908919
J9: 17.496362 | K9: 27.336467
J10: 25.763707 | K10: 17.7808
J11: 34.031051 | K11: 7.8622583
J12: 42.298396 | K12: 2.2981986
J13: 50.565741 | K13: 0.6047891
A4001: -36.241379 | B4001: 0
A4002: -36.241379 | B4002: =$K$3 -> 0.12095782
A4003: -27.974034 | B4003: =$K$3 -> 0.12095782
A4004: -27.974034 | B4004: 0
A4005: -27.974034 | B4005: =$K$4 -> 0.84670474
A4006: -19.706689 | B4006: =$K$4 -> 0.84670474
A4007: -19.706689 | B4007: 0
A4008: -19.706689 | B4008: =$K$5 -> 3.6287346
A4009: -11.439345 | B4009: =$K$5 -> 3.6287346
A4010: -11.439345 | B4010: 0
A4011: -11.439345 | B4011: =$K$6 -> 10.402373
A4012: -3.1719998 | B4012: =$K$6 -> 10.402373
A4013: -3.1719998 | B4013: 0
A4014: -3.1719998 | B4014: =$K$7 -> 21.167619
A4015: 5.0953449 | B4015: =$K$7 -> 21.167619
A4016: 5.0953449 | B4016: 0
A4017: 5.0953449 | B4017: =$K$8 -> 28.908919
A4018: 13.36269 | B4018: =$K$8 -> 28.908919
A4019: 13.36269 | B4019: 0
A4020: 13.36269 | B4020: =$K$9 -> 27.336467
A4021: 21.630034 | B4021: =$K$9 -> 27.336467
A4022: 21.630034 | B4022: 0
A4023: 21.630034 | B4023: =$K$10 -> 17.7808
A4024: 29.897379 | B4024: =$K$10 -> 17.7808
A4025: 29.897379 | B4025: 0
A4026: 29.897379 | B4026: =$K$11 -> 7.8622583
A4027: 38.164724 | B4027: =$K$11 -> 7.8622583
A4028: 38.164724 | B4028: 0
A4029: 38.164724 | B4029: =$K$12 -> 2.2981986
A4030: 46.432069 | B4030: =$K$12 -> 2.2981986
A4031: 46.432069 | B4031: 0
A4032: 46.432069 | B4032: =$K$13 -> 0.6047891
A4033: 54.699413 | B4033: =$K$13 -> 0.6047891
A4034: 54.699413 | B4034: 0
A5001: -36.241379 | B5001: 0
A5002: -36.241379 | B5002: =$K$3 -> 0.12095782
A5003: -36.150438 | B5003: =$K$3 -> 0.12095782
A5004: -36.150438 | B5004: 0
A5005: -36.059497 | B5005: 0
A5006: -36.059497 | B5006: =$K$3 -> 0.12095782
A5007: -35.968556 | B5007: =$K$3 -> 0.12095782
A5008: -35.968556 | B5008: 0
A5009: -35.877616 | B5009: 0
A5010: -35.877616 | B5010: =$K$3 -> 0.12095782
A5011: -35.786675 | B5011: =$K$3 -> 0.12095782
A5012: -35.786675 | B5012: 0
A5013: -35.695734 | B5013: 0
A5014: -35.695734 | B5014: =$K$3 -> 0.12095782
A5015: -35.604793 | B5015: =$K$3 -> 0.12095782
A5016: -35.604793 | B5016: 0
A5017: -35.513852 | B5017: 0
A5018: -35.513852 | B5018: =$K$3 -> 0.12095782
A5019: -35.422912 | B5019: =$K$3 -> 0.12095782
A5020: -35.422912 | B5020: 0
A5021: -35.331971 | B5021: 0
A5022: -35.331971 | B5022: =$K$3 -> 0.12095782
A5023: -35.24103 | B5023: =$K$3 -> 0.12095782
A5024: -35.24103 | B5024: 0
A5025: -35.150089 | B5025: 0
A5026: -35.150089 | B5026: =$K$3 -> 0.12095782
A5027: -35.059148 | B5027: =$K$3 -> 0.12095782
A5028: -35.059148 | B5028: 0
A5029: -34.968208 | B5029: 0
A5030: -34.968208 | B5030: =$K$3 -> 0.12095782
A5031: -34.877267 | B5031: =$K$3 -> 0.12095782
A5032: -34.877267 | B5032: 0
A5033: -34.786326 | B5033: 0
A5034: -34.786326 | B5034: =$K$3 -> 0.12095782
A5035: -34.695385 | B5035: =$K$3 -> 0.12095782
A5036: -34.695385 | B5036: 0
A5037: -34.604445 | B5037: 0
A5038: -34.604445 | B5038: =$K$3 -> 0.12095782
A5039: -34.513504 | B5039: =$K$3 -> 0.12095782
A5040: -34.513504 | B5040: 0
A5041: -34.422563 | B5041: 0
A5042: -34.422563 | B5042: =$K$3 -> 0.12095782
A5043: -34.331622 | B5043: =$K$3 -> 0.12095782
A5044: -34.331622 | B5044: 0
A5045: -34.240681 | B5045: 0
A5046: -34.240681 | B5046: =$K$3 -> 0.12095782
A5047: -34.149741 | B5047: =$K$3 -> 0.12095782
A5048: -34.149741 | B5048: 0
A5049: -34.0588 | B5049: 0
A5050: -34.0588 | B5050: =$K$3 -> 0.12095782
A5051: -33.967859 | B5051: =$K$3 -> 0.12095782
A5052: -33.967859 | B5052: 0
A5053: -33.876918 | B5053: 0
...

Sheet RiskRGSheet1R33C6
Z1: 0.025266975
J2: Bin | K2: Height | Z2: 0.83968531
J3: -0.063320121 | K3: 0.29096488 | Z3: 0.41759672
J4: 0.063831773 | K4: 0.68462325
J5: 0.19098367 | K5: 1.1381861
J6: 0.31813556 | K6: 1.4890556
J7: 0.44528746 | K7: 1.5318445
J8: 0.57243935 | K8: 1.2494374
J9: 0.69959124 | K9: 0.80443231
J10: 0.82674314 | K10: 0.41077395
J11: 0.95389503 | K11: 0.1797136
J12: 1.0810469 | K12: 0.059904534
J13: 1.2081988 | K13: 0.025673372
A4001: -0.12689607 | B4001: 0
A4002: -0.12689607 | B4002: =$K$3 -> 0.29096488
A4003: 0.00025582584 | B4003: =$K$3 -> 0.29096488
A4004: 0.00025582584 | B4004: 0
A4005: 0.00025582584 | B4005: =$K$4 -> 0.68462325
A4006: 0.12740772 | B4006: =$K$4 -> 0.68462325
A4007: 0.12740772 | B4007: 0
A4008: 0.12740772 | B4008: =$K$5 -> 1.1381861
A4009: 0.25455961 | B4009: =$K$5 -> 1.1381861
A4010: 0.25455961 | B4010: 0
A4011: 0.25455961 | B4011: =$K$6 -> 1.4890556
A4012: 0.38171151 | B4012: =$K$6 -> 1.4890556
A4013: 0.38171151 | B4013: 0
A4014: 0.38171151 | B4014: =$K$7 -> 1.5318445
A4015: 0.5088634 | B4015: =$K$7 -> 1.5318445
A4016: 0.5088634 | B4016: 0
A4017: 0.5088634 | B4017: =$K$8 -> 1.2494374
A4018: 0.6360153 | B4018: =$K$8 -> 1.2494374
A4019: 0.6360153 | B4019: 0
A4020: 0.6360153 | B4020: =$K$9 -> 0.80443231
A4021: 0.76316719 | B4021: =$K$9 -> 0.80443231
A4022: 0.76316719 | B4022: 0
A4023: 0.76316719 | B4023: =$K$10 -> 0.41077395
A4024: 0.89031909 | B4024: =$K$10 -> 0.41077395
A4025: 0.89031909 | B4025: 0
A4026: 0.89031909 | B4026: =$K$11 -> 0.1797136
A4027: 1.017471 | B4027: =$K$11 -> 0.1797136
A4028: 1.017471 | B4028: 0
A4029: 1.017471 | B4029: =$K$12 -> 0.059904534
A4030: 1.1446229 | B4030: =$K$12 -> 0.059904534
A4031: 1.1446229 | B4031: 0
A4032: 1.1446229 | B4032: =$K$13 -> 0.025673372
A4033: 1.2717748 | B4033: =$K$13 -> 0.025673372
A4034: 1.2717748 | B4034: 0
A5001: -0.12689607 | B5001: 0
A5002: -0.12689607 | B5002: =$K$3 -> 0.29096488
A5003: -0.1254974 | B5003: =$K$3 -> 0.29096488
A5004: -0.1254974 | B5004: 0
A5005: -0.12409873 | B5005: 0
A5006: -0.12409873 | B5006: =$K$3 -> 0.29096488
A5007: -0.12270006 | B5007: =$K$3 -> 0.29096488
A5008: -0.12270006 | B5008: 0
A5009: -0.12130139 | B5009: 0
A5010: -0.12130139 | B5010: =$K$3 -> 0.29096488
A5011: -0.11990271 | B5011: =$K$3 -> 0.29096488
A5012: -0.11990271 | B5012: 0
A5013: -0.11850404 | B5013: 0
A5014: -0.11850404 | B5014: =$K$3 -> 0.29096488
A5015: -0.11710537 | B5015: =$K$3 -> 0.29096488
A5016: -0.11710537 | B5016: 0
A5017: -0.1157067 | B5017: 0
A5018: -0.1157067 | B5018: =$K$3 -> 0.29096488
A5019: -0.11430803 | B5019: =$K$3 -> 0.29096488
A5020: -0.11430803 | B5020: 0
A5021: -0.11290936 | B5021: 0
A5022: -0.11290936 | B5022: =$K$3 -> 0.29096488
A5023: -0.11151069 | B5023: =$K$3 -> 0.29096488
A5024: -0.11151069 | B5024: 0
A5025: -0.11011202 | B5025: 0
A5026: -0.11011202 | B5026: =$K$3 -> 0.29096488
A5027: -0.10871335 | B5027: =$K$3 -> 0.29096488
A5028: -0.10871335 | B5028: 0
A5029: -0.10731468 | B5029: 0
A5030: -0.10731468 | B5030: =$K$3 -> 0.29096488
A5031: -0.10591601 | B5031: =$K$3 -> 0.29096488
A5032: -0.10591601 | B5032: 0
A5033: -0.10451734 | B5033: 0
A5034: -0.10451734 | B5034: =$K$3 -> 0.29096488
A5035: -0.10311866 | B5035: =$K$3 -> 0.29096488
A5036: -0.10311866 | B5036: 0
A5037: -0.10171999 | B5037: 0
A5038: -0.10171999 | B5038: =$K$3 -> 0.29096488
A5039: -0.10032132 | B5039: =$K$3 -> 0.29096488
A5040: -0.10032132 | B5040: 0
A5041: -0.098922652 | B5041: 0
A5042: -0.098922652 | B5042: =$K$3 -> 0.29096488
A5043: -0.097523981 | B5043: =$K$3 -> 0.29096488
A5044: -0.097523981 | B5044: 0
A5045: -0.09612531 | B5045: 0
A5046: -0.09612531 | B5046: =$K$3 -> 0.29096488
A5047: -0.094726639 | B5047: =$K$3 -> 0.29096488
A5048: -0.094726639 | B5048: 0
A5049: -0.093327968 | B5049: 0
A5050: -0.093327968 | B5050: =$K$3 -> 0.29096488
A5051: -0.091929298 | B5051: =$K$3 -> 0.29096488
A5052: -0.091929298 | B5052: 0
A5053: -0.090530627 | B5053: 0
...

Sheet RiskRGSheet1R34C1
Z1: -9.7257814
J2: Bin | K2: Height | Z2: 33.840965
J3: -35.157652 | K3: 0.044888354 | Z3: 12.08197
J4: -27.731821 | K4: 0.40399518
J5: -20.305989 | K5: 1.5710924
J6: -12.880158 | K6: 5.2968257
J7: -5.4543272 | K7: 12.658516
J8: 1.9715039 | K8: 22.3544
J9: 9.3973351 | K9: 29.132541
J10: 16.823166 | K10: 27.965444
J11: 24.248997 | K11: 19.750876
J12: 31.674828 | K12: 10.234545
J13: 39.10066 | K13: 3.9052868
J14: 46.526491 | K14: 1.0773205
J15: 53.952322 | K15: 0.26933012
A4001: -38.870567 | B4001: 0
A4002: -38.870567 | B4002: =$K$3 -> 0.044888354
A4003: -31.444736 | B4003: =$K$3 -> 0.044888354
A4004: -31.444736 | B4004: 0
A4005: -31.444736 | B4005: =$K$4 -> 0.40399518
A4006: -24.018905 | B4006: =$K$4 -> 0.40399518
A4007: -24.018905 | B4007: 0
A4008: -24.018905 | B4008: =$K$5 -> 1.5710924
A4009: -16.593074 | B4009: =$K$5 -> 1.5710924
A4010: -16.593074 | B4010: 0
A4011: -16.593074 | B4011: =$K$6 -> 5.2968257
A4012: -9.1672428 | B4012: =$K$6 -> 5.2968257
A4013: -9.1672428 | B4013: 0
A4014: -9.1672428 | B4014: =$K$7 -> 12.658516
A4015: -1.7414116 | B4015: =$K$7 -> 12.658516
A4016: -1.7414116 | B4016: 0
A4017: -1.7414116 | B4017: =$K$8 -> 22.3544
A4018: 5.6844195 | B4018: =$K$8 -> 22.3544
A4019: 5.6844195 | B4019: 0
A4020: 5.6844195 | B4020: =$K$9 -> 29.132541
A4021: 13.110251 | B4021: =$K$9 -> 29.132541
A4022: 13.110251 | B4022: 0
A4023: 13.110251 | B4023: =$K$10 -> 27.965444
A4024: 20.536082 | B4024: =$K$10 -> 27.965444
A4025: 20.536082 | B4025: 0
A4026: 20.536082 | B4026: =$K$11 -> 19.750876
A4027: 27.961913 | B4027: =$K$11 -> 19.750876
A4028: 27.961913 | B4028: 0
A4029: 27.961913 | B4029: =$K$12 -> 10.234545
A4030: 35.387744 | B4030: =$K$12 -> 10.234545
A4031: 35.387744 | B4031: 0
A4032: 35.387744 | B4032: =$K$13 -> 3.9052868
A4033: 42.813575 | B4033: =$K$13 -> 3.9052868
A4034: 42.813575 | B4034: 0
A4035: 42.813575 | B4035: =$K$14 -> 1.0773205
A4036: 50.239406 | B4036: =$K$14 -> 1.0773205
A4037: 50.239406 | B4037: 0
A4038: 50.239406 | B4038: =$K$15 -> 0.26933012
A4039: 57.665237 | B4039: =$K$15 -> 0.26933012
A4040: 57.665237 | B4040: 0
A5001: -38.870567 | B5001: 0
A5002: -38.870567 | B5002: =$K$3 -> 0.044888354
A5003: -38.774032 | B5003: =$K$3 -> 0.044888354
A5004: -38.774032 | B5004: 0
A5005: -38.677496 | B5005: 0
A5006: -38.677496 | B5006: =$K$3 -> 0.044888354
A5007: -38.58096 | B5007: =$K$3 -> 0.044888354
A5008: -38.58096 | B5008: 0
A5009: -38.484424 | B5009: 0
A5010: -38.484424 | B5010: =$K$3 -> 0.044888354
A5011: -38.387888 | B5011: =$K$3 -> 0.044888354
A5012: -38.387888 | B5012: 0
A5013: -38.291352 | B5013: 0
A5014: -38.291352 | B5014: =$K$3 -> 0.044888354
A5015: -38.194817 | B5015: =$K$3 -> 0.044888354
A5016: -38.194817 | B5016: 0
A5017: -38.098281 | B5017: 0
A5018: -38.098281 | B5018: =$K$3 -> 0.044888354
A5019: -38.001745 | B5019: =$K$3 -> 0.044888354
A5020: -38.001745 | B5020: 0
A5021: -37.905209 | B5021: 0
A5022: -37.905209 | B5022: =$K$3 -> 0.044888354
A5023: -37.808673 | B5023: =$K$3 -> 0.044888354
A5024: -37.808673 | B5024: 0
A5025: -37.712138 | B5025: 0
A5026: -37.712138 | B5026: =$K$3 -> 0.044888354
A5027: -37.615602 | B5027: =$K$3 -> 0.044888354
A5028: -37.615602 | B5028: 0
A5029: -37.519066 | B5029: 0
A5030: -37.519066 | B5030: =$K$3 -> 0.044888354
A5031: -37.42253 | B5031: =$K$3 -> 0.044888354
A5032: -37.42253 | B5032: 0
A5033: -37.325994 | B5033: 0
A5034: -37.325994 | B5034: =$K$3 -> 0.044888354
A5035: -37.229459 | B5035: =$K$3 -> 0.044888354
A5036: -37.229459 | B5036: 0
A5037: -37.132923 | B5037: 0
A5038: -37.132923 | B5038: =$K$3 -> 0.044888354
A5039: -37.036387 | B5039: =$K$3 -> 0.044888354
A5040: -37.036387 | B5040: 0
A5041: -36.939851 | B5041: 0
A5042: -36.939851 | B5042: =$K$3 -> 0.044888354
A5043: -36.843315 | B5043: =$K$3 -> 0.044888354
A5044: -36.843315 | B5044: 0
A5045: -36.74678 | B5045: 0
...

Sheet RiskRGSheet1R34C6
Z1: 0.025207884
J2: Bin | K2: Height | Z2: 0.83929157
J3: -0.071324881 | K3: 0.26085056 | Z3: 0.41741707
J4: 0.041264902 | K4: 0.61831244
J5: 0.15385469 | K5: 1.0079781
J6: 0.26644447 | K6: 1.3751011
J7: 0.37903425 | K7: 1.561883
J8: 0.49162404 | K8: 1.4620513
J9: 0.60421382 | K9: 1.1335728
J10: 0.7168036 | K10: 0.74390715
J11: 0.82939339 | K11: 0.40898792
J12: 0.94198317 | K12: 0.19000226
J13: 1.054573 | K13: 0.080509432
J14: 1.1671627 | K14: 0.025763018
J15: 1.2797525 | K15: 0.012881509
A4001: -0.12761977 | B4001: 0
A4002: -0.12761977 | B4002: =$K$3 -> 0.26085056
A4003: -0.01502999 | B4003: =$K$3 -> 0.26085056
A4004: -0.01502999 | B4004: 0
A4005: -0.01502999 | B4005: =$K$4 -> 0.61831244
A4006: 0.097559794 | B4006: =$K$4 -> 0.61831244
A4007: 0.097559794 | B4007: 0
A4008: 0.097559794 | B4008: =$K$5 -> 1.0079781
A4009: 0.21014958 | B4009: =$K$5 -> 1.0079781
A4010: 0.21014958 | B4010: 0
A4011: 0.21014958 | B4011: =$K$6 -> 1.3751011
A4012: 0.32273936 | B4012: =$K$6 -> 1.3751011
A4013: 0.32273936 | B4013: 0
A4014: 0.32273936 | B4014: =$K$7 -> 1.561883
A4015: 0.43532914 | B4015: =$K$7 -> 1.561883
A4016: 0.43532914 | B4016: 0
A4017: 0.43532914 | B4017: =$K$8 -> 1.4620513
A4018: 0.54791893 | B4018: =$K$8 -> 1.4620513
A4019: 0.54791893 | B4019: 0
A4020: 0.54791893 | B4020: =$K$9 -> 1.1335728
A4021: 0.66050871 | B4021: =$K$9 -> 1.1335728
A4022: 0.66050871 | B4022: 0
A4023: 0.66050871 | B4023: =$K$10 -> 0.74390715
A4024: 0.77309849 | B4024: =$K$10 -> 0.74390715
A4025: 0.77309849 | B4025: 0
A4026: 0.77309849 | B4026: =$K$11 -> 0.40898792
A4027: 0.88568828 | B4027: =$K$11 -> 0.40898792
A4028: 0.88568828 | B4028: 0
A4029: 0.88568828 | B4029: =$K$12 -> 0.19000226
A4030: 0.99827806 | B4030: =$K$12 -> 0.19000226
A4031: 0.99827806 | B4031: 0
A4032: 0.99827806 | B4032: =$K$13 -> 0.080509432
A4033: 1.1108678 | B4033: =$K$13 -> 0.080509432
A4034: 1.1108678 | B4034: 0
A4035: 1.1108678 | B4035: =$K$14 -> 0.025763018
A4036: 1.2234576 | B4036: =$K$14 -> 0.025763018
A4037: 1.2234576 | B4037: 0
A4038: 1.2234576 | B4038: =$K$15 -> 0.012881509
A4039: 1.3360474 | B4039: =$K$15 -> 0.012881509
A4040: 1.3360474 | B4040: 0
A5001: -0.12761977 | B5001: 0
A5002: -0.12761977 | B5002: =$K$3 -> 0.26085056
A5003: -0.12615611 | B5003: =$K$3 -> 0.26085056
A5004: -0.12615611 | B5004: 0
A5005: -0.12469244 | B5005: 0
A5006: -0.12469244 | B5006: =$K$3 -> 0.26085056
A5007: -0.12322877 | B5007: =$K$3 -> 0.26085056
A5008: -0.12322877 | B5008: 0
A5009: -0.1217651 | B5009: 0
A5010: -0.1217651 | B5010: =$K$3 -> 0.26085056
A5011: -0.12030144 | B5011: =$K$3 -> 0.26085056
A5012: -0.12030144 | B5012: 0
A5013: -0.11883777 | B5013: 0
A5014: -0.11883777 | B5014: =$K$3 -> 0.26085056
A5015: -0.1173741 | B5015: =$K$3 -> 0.26085056
A5016: -0.1173741 | B5016: 0
A5017: -0.11591044 | B5017: 0
A5018: -0.11591044 | B5018: =$K$3 -> 0.26085056
A5019: -0.11444677 | B5019: =$K$3 -> 0.26085056
A5020: -0.11444677 | B5020: 0
A5021: -0.1129831 | B5021: 0
A5022: -0.1129831 | B5022: =$K$3 -> 0.26085056
A5023: -0.11151943 | B5023: =$K$3 -> 0.26085056
A5024: -0.11151943 | B5024: 0
A5025: -0.11005577 | B5025: 0
A5026: -0.11005577 | B5026: =$K$3 -> 0.26085056
A5027: -0.1085921 | B5027: =$K$3 -> 0.26085056
A5028: -0.1085921 | B5028: 0
A5029: -0.10712843 | B5029: 0
A5030: -0.10712843 | B5030: =$K$3 -> 0.26085056
A5031: -0.10566477 | B5031: =$K$3 -> 0.26085056
A5032: -0.10566477 | B5032: 0
A5033: -0.1042011 | B5033: 0
A5034: -0.1042011 | B5034: =$K$3 -> 0.26085056
A5035: -0.10273743 | B5035: =$K$3 -> 0.26085056
A5036: -0.10273743 | B5036: 0
A5037: -0.10127376 | B5037: 0
A5038: -0.10127376 | B5038: =$K$3 -> 0.26085056
A5039: -0.099810097 | B5039: =$K$3 -> 0.26085056
A5040: -0.099810097 | B5040: 0
A5041: -0.098346429 | B5041: 0
A5042: -0.098346429 | B5042: =$K$3 -> 0.26085056
A5043: -0.096882762 | B5043: =$K$3 -> 0.26085056
A5044: -0.096882762 | B5044: 0
A5045: -0.095419095 | B5045: 0
...

Sheet RiskRGStatic ModetatsR34C1
Z1: -9.7421331
J2: Bin | K2: Height | Z2: 33.638954
J3: -26.789779 | K3: 0.49162835 | Z3: 12.079677
J4: -18.653552 | K4: 2.2123276
J5: -10.517325 | K5: 7.1286111
J6: -2.3810977 | K6: 16.715364
J7: 5.7551295 | K7: 26.547931
J8: 13.891357 | K8: 29.251887
J9: 22.027584 | K9: 22.860718
J10: 30.163811 | K10: 12.044895
J11: 38.300038 | K11: 4.4246552
J12: 46.436266 | K12: 1.2290709
A4001: -30.857893 | B4001: 0
A4002: -30.857893 | B4002: =$K$3 -> 0.49162835
A4003: -22.721666 | B4003: =$K$3 -> 0.49162835
A4004: -22.721666 | B4004: 0
A4005: -22.721666 | B4005: =$K$4 -> 2.2123276
A4006: -14.585439 | B4006: =$K$4 -> 2.2123276
A4007: -14.585439 | B4007: 0
A4008: -14.585439 | B4008: =$K$5 -> 7.1286111
A4009: -6.4492113 | B4009: =$K$5 -> 7.1286111
A4010: -6.4492113 | B4010: 0
A4011: -6.4492113 | B4011: =$K$6 -> 16.715364
A4012: 1.6870159 | B4012: =$K$6 -> 16.715364
A4013: 1.6870159 | B4013: 0
A4014: 1.6870159 | B4014: =$K$7 -> 26.547931
A4015: 9.8232431 | B4015: =$K$7 -> 26.547931
A4016: 9.8232431 | B4016: 0
A4017: 9.8232431 | B4017: =$K$8 -> 29.251887
A4018: 17.95947 | B4018: =$K$8 -> 29.251887
A4019: 17.95947 | B4019: 0
A4020: 17.95947 | B4020: =$K$9 -> 22.860718
A4021: 26.095698 | B4021: =$K$9 -> 22.860718
A4022: 26.095698 | B4022: 0
A4023: 26.095698 | B4023: =$K$10 -> 12.044895
A4024: 34.231925 | B4024: =$K$10 -> 12.044895
A4025: 34.231925 | B4025: 0
A4026: 34.231925 | B4026: =$K$11 -> 4.4246552
A4027: 42.368152 | B4027: =$K$11 -> 4.4246552
A4028: 42.368152 | B4028: 0
A4029: 42.368152 | B4029: =$K$12 -> 1.2290709
A4030: 50.504379 | B4030: =$K$12 -> 1.2290709
A4031: 50.504379 | B4031: 0
A5001: -30.857893 | B5001: 0
A5002: -30.857893 | B5002: =$K$3 -> 0.49162835
A5003: -30.776531 | B5003: =$K$3 -> 0.49162835
A5004: -30.776531 | B5004: 0
A5005: -30.695168 | B5005: 0
A5006: -30.695168 | B5006: =$K$3 -> 0.49162835
A5007: -30.613806 | B5007: =$K$3 -> 0.49162835
A5008: -30.613806 | B5008: 0
A5009: -30.532444 | B5009: 0
A5010: -30.532444 | B5010: =$K$3 -> 0.49162835
A5011: -30.451082 | B5011: =$K$3 -> 0.49162835
A5012: -30.451082 | B5012: 0
A5013: -30.369719 | B5013: 0
A5014: -30.369719 | B5014: =$K$3 -> 0.49162835
A5015: -30.288357 | B5015: =$K$3 -> 0.49162835
A5016: -30.288357 | B5016: 0
A5017: -30.206995 | B5017: 0
A5018: -30.206995 | B5018: =$K$3 -> 0.49162835
A5019: -30.125633 | B5019: =$K$3 -> 0.49162835
A5020: -30.125633 | B5020: 0
A5021: -30.04427 | B5021: 0
A5022: -30.04427 | B5022: =$K$3 -> 0.49162835
A5023: -29.962908 | B5023: =$K$3 -> 0.49162835
A5024: -29.962908 | B5024: 0
A5025: -29.881546 | B5025: 0
A5026: -29.881546 | B5026: =$K$3 -> 0.49162835
A5027: -29.800183 | B5027: =$K$3 -> 0.49162835
A5028: -29.800183 | B5028: 0
A5029: -29.718821 | B5029: 0
A5030: -29.718821 | B5030: =$K$3 -> 0.49162835
A5031: -29.637459 | B5031: =$K$3 -> 0.49162835
A5032: -29.637459 | B5032: 0
A5033: -29.556097 | B5033: 0
A5034: -29.556097 | B5034: =$K$3 -> 0.49162835
A5035: -29.474734 | B5035: =$K$3 -> 0.49162835
A5036: -29.474734 | B5036: 0
A5037: -29.393372 | B5037: 0
A5038: -29.393372 | B5038: =$K$3 -> 0.49162835
A5039: -29.31201 | B5039: =$K$3 -> 0.49162835
A5040: -29.31201 | B5040: 0
A5041: -29.230648 | B5041: 0
A5042: -29.230648 | B5042: =$K$3 -> 0.49162835
A5043: -29.149285 | B5043: =$K$3 -> 0.49162835
A5044: -29.149285 | B5044: 0
A5045: -29.067923 | B5045: 0
A5046: -29.067923 | B5046: =$K$3 -> 0.49162835
A5047: -28.986561 | B5047: =$K$3 -> 0.49162835
A5048: -28.986561 | B5048: 0
A5049: -28.905198 | B5049: 0
A5050: -28.905198 | B5050: =$K$3 -> 0.49162835
A5051: -28.823836 | B5051: =$K$3 -> 0.49162835
A5052: -28.823836 | B5052: 0
A5053: -28.742474 | B5053: 0
A5054: -28.742474 | B5054: =$K$3 -> 0.49162835
A5055: -28.661112 | B5055: =$K$3 -> 0.49162835
A5056: -28.661112 | B5056: 0
A5057: -28.579749 | B5057: 0
...

Sheet RiskRGStatic ModetatsR34C6
Z1: 0.02375216
J2: Bin | K2: Height | Z2: 0.83634168
J3: -0.028522137 | K3: 0.44382338 | Z3: 0.41703365
J4: 0.098829737 | K4: 0.81936624
J5: 0.22618161 | K5: 1.2461195
J6: 0.35353349 | K6: 1.5363117
J7: 0.48088536 | K7: 1.4680312
J8: 0.60823723 | K8: 1.1266286
J9: 0.73558911 | K9: 0.6828052
J10: 0.86294098 | K10: 0.3414026
J11: 0.99029286 | K11: 0.11949091
J12: 1.1176447 | K12: 0.06828052
A4001: -0.092198074 | B4001: 0
A4002: -0.092198074 | B4002: =$K$3 -> 0.44382338
A4003: 0.0351538 | B4003: =$K$3 -> 0.44382338
A4004: 0.0351538 | B4004: 0
A4005: 0.0351538 | B4005: =$K$4 -> 0.81936624
A4006: 0.16250567 | B4006: =$K$4 -> 0.81936624
A4007: 0.16250567 | B4007: 0
A4008: 0.16250567 | B4008: =$K$5 -> 1.2461195
A4009: 0.28985755 | B4009: =$K$5 -> 1.2461195
A4010: 0.28985755 | B4010: 0
A4011: 0.28985755 | B4011: =$K$6 -> 1.5363117
A4012: 0.41720942 | B4012: =$K$6 -> 1.5363117
A4013: 0.41720942 | B4013: 0
A4014: 0.41720942 | B4014: =$K$7 -> 1.4680312
A4015: 0.5445613 | B4015: =$K$7 -> 1.4680312
A4016: 0.5445613 | B4016: 0
A4017: 0.5445613 | B4017: =$K$8 -> 1.1266286
A4018: 0.67191317 | B4018: =$K$8 -> 1.1266286
A4019: 0.67191317 | B4019: 0
A4020: 0.67191317 | B4020: =$K$9 -> 0.6828052
A4021: 0.79926504 | B4021: =$K$9 -> 0.6828052
A4022: 0.79926504 | B4022: 0
A4023: 0.79926504 | B4023: =$K$10 -> 0.3414026
A4024: 0.92661692 | B4024: =$K$10 -> 0.3414026
A4025: 0.92661692 | B4025: 0
A4026: 0.92661692 | B4026: =$K$11 -> 0.11949091
A4027: 1.0539688 | B4027: =$K$11 -> 0.11949091
A4028: 1.0539688 | B4028: 0
A4029: 1.0539688 | B4029: =$K$12 -> 0.06828052
A4030: 1.1813207 | B4030: =$K$12 -> 0.06828052
A4031: 1.1813207 | B4031: 0
A5001: -0.092198074 | B5001: 0
A5002: -0.092198074 | B5002: =$K$3 -> 0.44382338
A5003: -0.090924555 | B5003: =$K$3 -> 0.44382338
A5004: -0.090924555 | B5004: 0
A5005: -0.089651036 | B5005: 0
A5006: -0.089651036 | B5006: =$K$3 -> 0.44382338
A5007: -0.088377518 | B5007: =$K$3 -> 0.44382338
A5008: -0.088377518 | B5008: 0
A5009: -0.087103999 | B5009: 0
A5010: -0.087103999 | B5010: =$K$3 -> 0.44382338
A5011: -0.08583048 | B5011: =$K$3 -> 0.44382338
A5012: -0.08583048 | B5012: 0
A5013: -0.084556961 | B5013: 0
A5014: -0.084556961 | B5014: =$K$3 -> 0.44382338
A5015: -0.083283443 | B5015: =$K$3 -> 0.44382338
A5016: -0.083283443 | B5016: 0
A5017: -0.082009924 | B5017: 0
A5018: -0.082009924 | B5018: =$K$3 -> 0.44382338
A5019: -0.080736405 | B5019: =$K$3 -> 0.44382338
A5020: -0.080736405 | B5020: 0
A5021: -0.079462886 | B5021: 0
A5022: -0.079462886 | B5022: =$K$3 -> 0.44382338
A5023: -0.078189368 | B5023: =$K$3 -> 0.44382338
A5024: -0.078189368 | B5024: 0
A5025: -0.076915849 | B5025: 0
A5026: -0.076915849 | B5026: =$K$3 -> 0.44382338
A5027: -0.07564233 | B5027: =$K$3 -> 0.44382338
A5028: -0.07564233 | B5028: 0
A5029: -0.074368811 | B5029: 0
A5030: -0.074368811 | B5030: =$K$3 -> 0.44382338
A5031: -0.073095293 | B5031: =$K$3 -> 0.44382338
A5032: -0.073095293 | B5032: 0
A5033: -0.071821774 | B5033: 0
A5034: -0.071821774 | B5034: =$K$3 -> 0.44382338
A5035: -0.070548255 | B5035: =$K$3 -> 0.44382338
A5036: -0.070548255 | B5036: 0
A5037: -0.069274737 | B5037: 0
A5038: -0.069274737 | B5038: =$K$3 -> 0.44382338
A5039: -0.068001218 | B5039: =$K$3 -> 0.44382338
A5040: -0.068001218 | B5040: 0
A5041: -0.066727699 | B5041: 0
A5042: -0.066727699 | B5042: =$K$3 -> 0.44382338
A5043: -0.06545418 | B5043: =$K$3 -> 0.44382338
A5044: -0.06545418 | B5044: 0
A5045: -0.064180662 | B5045: 0
A5046: -0.064180662 | B5046: =$K$3 -> 0.44382338
A5047: -0.062907143 | B5047: =$K$3 -> 0.44382338
A5048: -0.062907143 | B5048: 0
A5049: -0.061633624 | B5049: 0
A5050: -0.061633624 | B5050: =$K$3 -> 0.44382338
A5051: -0.060360105 | B5051: =$K$3 -> 0.44382338
A5052: -0.060360105 | B5052: 0
A5053: -0.059086587 | B5053: 0
A5054: -0.059086587 | B5054: =$K$3 -> 0.44382338
A5055: -0.057813068 | B5055: =$K$3 -> 0.44382338
A5056: -0.057813068 | B5056: 0
A5057: -0.056539549 | B5057: 0
...

Sheet RiskRGStrategic Cnv 2R32C1
Z1: -5226611
J2: Bin | K2: Height | Z2: 35739460
J3: -3521957.6 | K3: 26.760044 | Z3: 13035168
J4: 3055012.3 | K4: 23.71913
J5: 9631982.1 | K5: 29.496866
J6: 16208952 | K6: 27.368226
J7: 22785922 | K7: 20.070033
J8: 29362892 | K8: 13.07593
J9: 35939862 | K9: 6.9941023
J10: 42516831 | K10: 3.040914
J11: 49093801 | K11: 1.2163656
J12: 55670771 | K12: 0.3040914
A4001: -6810442.5 | B4001: 0
A4002: -6810442.5 | B4002: =$K$3 -> 26.760044
A4003: -233472.65 | B4003: =$K$3 -> 26.760044
A4004: -233472.65 | B4004: 0
A4005: -233472.65 | B4005: =$K$4 -> 23.71913
A4006: 6343497.2 | B4006: =$K$4 -> 23.71913
A4007: 6343497.2 | B4007: 0
A4008: 6343497.2 | B4008: =$K$5 -> 29.496866
A4009: 12920467 | B4009: =$K$5 -> 29.496866
A4010: 12920467 | B4010: 0
A4011: 12920467 | B4011: =$K$6 -> 27.368226
A4012: 19497437 | B4012: =$K$6 -> 27.368226
A4013: 19497437 | B4013: 0
A4014: 19497437 | B4014: =$K$7 -> 20.070033
A4015: 26074407 | B4015: =$K$7 -> 20.070033
A4016: 26074407 | B4016: 0
A4017: 26074407 | B4017: =$K$8 -> 13.07593
A4018: 32651377 | B4018: =$K$8 -> 13.07593
A4019: 32651377 | B4019: 0
A4020: 32651377 | B4020: =$K$9 -> 6.9941023
A4021: 39228346 | B4021: =$K$9 -> 6.9941023
A4022: 39228346 | B4022: 0
A4023: 39228346 | B4023: =$K$10 -> 3.040914
A4024: 45805316 | B4024: =$K$10 -> 3.040914
A4025: 45805316 | B4025: 0
A4026: 45805316 | B4026: =$K$11 -> 1.2163656
A4027: 52382286 | B4027: =$K$11 -> 1.2163656
A4028: 52382286 | B4028: 0
A4029: 52382286 | B4029: =$K$12 -> 0.3040914
A4030: 58959256 | B4030: =$K$12 -> 0.3040914
A4031: 58959256 | B4031: 0
A5001: -6810442.5 | B5001: 0
A5002: -6810442.5 | B5002: =$K$3 -> 26.760044
A5003: -6744672.8 | B5003: =$K$3 -> 26.760044
A5004: -6744672.8 | B5004: 0
A5005: -6678903.1 | B5005: 0
A5006: -6678903.1 | B5006: =$K$3 -> 26.760044
A5007: -6613133.4 | B5007: =$K$3 -> 26.760044
A5008: -6613133.4 | B5008: 0
A5009: -6547363.7 | B5009: 0
A5010: -6547363.7 | B5010: =$K$3 -> 26.760044
A5011: -6481594 | B5011: =$K$3 -> 26.760044
A5012: -6481594 | B5012: 0
A5013: -6415824.3 | B5013: 0
A5014: -6415824.3 | B5014: =$K$3 -> 26.760044
A5015: -6350054.6 | B5015: =$K$3 -> 26.760044
A5016: -6350054.6 | B5016: 0
A5017: -6284284.9 | B5017: 0
A5018: -6284284.9 | B5018: =$K$3 -> 26.760044
A5019: -6218515.2 | B5019: =$K$3 -> 26.760044
A5020: -6218515.2 | B5020: 0
A5021: -6152745.5 | B5021: 0
A5022: -6152745.5 | B5022: =$K$3 -> 26.760044
A5023: -6086975.8 | B5023: =$K$3 -> 26.760044
A5024: -6086975.8 | B5024: 0
A5025: -6021206.1 | B5025: 0
A5026: -6021206.1 | B5026: =$K$3 -> 26.760044
A5027: -5955436.4 | B5027: =$K$3 -> 26.760044
A5028: -5955436.4 | B5028: 0
A5029: -5889666.7 | B5029: 0
A5030: -5889666.7 | B5030: =$K$3 -> 26.760044
A5031: -5823897 | B5031: =$K$3 -> 26.760044
A5032: -5823897 | B5032: 0
A5033: -5758127.3 | B5033: 0
A5034: -5758127.3 | B5034: =$K$3 -> 26.760044
A5035: -5692357.6 | B5035: =$K$3 -> 26.760044
A5036: -5692357.6 | B5036: 0
A5037: -5626587.9 | B5037: 0
A5038: -5626587.9 | B5038: =$K$3 -> 26.760044
A5039: -5560818.2 | B5039: =$K$3 -> 26.760044
A5040: -5560818.2 | B5040: 0
A5041: -5495048.5 | B5041: 0
A5042: -5495048.5 | B5042: =$K$3 -> 26.760044
A5043: -5429278.8 | B5043: =$K$3 -> 26.760044
A5044: -5429278.8 | B5044: 0
A5045: -5363509.1 | B5045: 0
A5046: -5363509.1 | B5046: =$K$3 -> 26.760044
A5047: -5297739.4 | B5047: =$K$3 -> 26.760044
A5048: -5297739.4 | B5048: 0
A5049: -5231969.7 | B5049: 0
A5050: -5231969.7 | B5050: =$K$3 -> 26.760044
A5051: -5166200 | B5051: =$K$3 -> 26.760044
A5052: -5166200 | B5052: 0
A5053: -5100430.3 | B5053: 0
A5054: -5100430.3 | B5054: =$K$3 -> 26.760044
A5055: -5034660.6 | B5055: =$K$3 -> 26.760044
A5056: -5034660.6 | B5056: 0
A5057: -4968890.9 | B5057: 0
...

Sheet RiskRGStrategic Cnv 2R42C1
Z1: -5.2143726
J2: Bin | K2: Height | Z2: 35.776337
J3: -3.2817166 | K3: 26.355118 | Z3: 13.044224
J4: 3.7757361 | K4: 24.3714
J5: 10.833189 | K5: 30.039167
J6: 17.890641 | K6: 25.221565
J7: 24.948094 | K7: 17.853467
J8: 32.005547 | K8: 10.48537
J9: 39.062999 | K9: 4.8176023
J10: 46.120452 | K10: 1.9837186
J11: 53.177905 | K11: 0.28338837
J12: 60.235358 | K12: 0.28338837
A4001: -6.8104429 | B4001: 0
A4002: -6.8104429 | B4002: =$K$3 -> 26.355118
A4003: 0.24700975 | B4003: =$K$3 -> 26.355118
A4004: 0.24700975 | B4004: 0
A4005: 0.24700975 | B4005: =$K$4 -> 24.3714
A4006: 7.3044624 | B4006: =$K$4 -> 24.3714
A4007: 7.3044624 | B4007: 0
A4008: 7.3044624 | B4008: =$K$5 -> 30.039167
A4009: 14.361915 | B4009: =$K$5 -> 30.039167
A4010: 14.361915 | B4010: 0
A4011: 14.361915 | B4011: =$K$6 -> 25.221565
A4012: 21.419368 | B4012: =$K$6 -> 25.221565
A4013: 21.419368 | B4013: 0
A4014: 21.419368 | B4014: =$K$7 -> 17.853467
A4015: 28.47682 | B4015: =$K$7 -> 17.853467
A4016: 28.47682 | B4016: 0
A4017: 28.47682 | B4017: =$K$8 -> 10.48537
A4018: 35.534273 | B4018: =$K$8 -> 10.48537
A4019: 35.534273 | B4019: 0
A4020: 35.534273 | B4020: =$K$9 -> 4.8176023
A4021: 42.591726 | B4021: =$K$9 -> 4.8176023
A4022: 42.591726 | B4022: 0
A4023: 42.591726 | B4023: =$K$10 -> 1.9837186
A4024: 49.649179 | B4024: =$K$10 -> 1.9837186
A4025: 49.649179 | B4025: 0
A4026: 49.649179 | B4026: =$K$11 -> 0.28338837
A4027: 56.706631 | B4027: =$K$11 -> 0.28338837
A4028: 56.706631 | B4028: 0
A4029: 56.706631 | B4029: =$K$12 -> 0.28338837
A4030: 63.764084 | B4030: =$K$12 -> 0.28338837
A4031: 63.764084 | B4031: 0
A5001: -6.8104429 | B5001: 0
A5002: -6.8104429 | B5002: =$K$3 -> 26.355118
A5003: -6.7398684 | B5003: =$K$3 -> 26.355118
A5004: -6.7398684 | B5004: 0
A5005: -6.6692939 | B5005: 0
A5006: -6.6692939 | B5006: =$K$3 -> 26.355118
A5007: -6.5987193 | B5007: =$K$3 -> 26.355118
A5008: -6.5987193 | B5008: 0
A5009: -6.5281448 | B5009: 0
A5010: -6.5281448 | B5010: =$K$3 -> 26.355118
A5011: -6.4575703 | B5011: =$K$3 -> 26.355118
A5012: -6.4575703 | B5012: 0
A5013: -6.3869958 | B5013: 0
A5014: -6.3869958 | B5014: =$K$3 -> 26.355118
A5015: -6.3164212 | B5015: =$K$3 -> 26.355118
A5016: -6.3164212 | B5016: 0
A5017: -6.2458467 | B5017: 0
A5018: -6.2458467 | B5018: =$K$3 -> 26.355118
A5019: -6.1752722 | B5019: =$K$3 -> 26.355118
A5020: -6.1752722 | B5020: 0
A5021: -6.1046977 | B5021: 0
A5022: -6.1046977 | B5022: =$K$3 -> 26.355118
A5023: -6.0341231 | B5023: =$K$3 -> 26.355118
A5024: -6.0341231 | B5024: 0
A5025: -5.9635486 | B5025: 0
A5026: -5.9635486 | B5026: =$K$3 -> 26.355118
A5027: -5.8929741 | B5027: =$K$3 -> 26.355118
A5028: -5.8929741 | B5028: 0
A5029: -5.8223995 | B5029: 0
A5030: -5.8223995 | B5030: =$K$3 -> 26.355118
A5031: -5.751825 | B5031: =$K$3 -> 26.355118
A5032: -5.751825 | B5032: 0
A5033: -5.6812505 | B5033: 0
A5034: -5.6812505 | B5034: =$K$3 -> 26.355118
A5035: -5.610676 | B5035: =$K$3 -> 26.355118
A5036: -5.610676 | B5036: 0
A5037: -5.5401014 | B5037: 0
A5038: -5.5401014 | B5038: =$K$3 -> 26.355118
A5039: -5.4695269 | B5039: =$K$3 -> 26.355118
A5040: -5.4695269 | B5040: 0
A5041: -5.3989524 | B5041: 0
A5042: -5.3989524 | B5042: =$K$3 -> 26.355118
A5043: -5.3283779 | B5043: =$K$3 -> 26.355118
A5044: -5.3283779 | B5044: 0
A5045: -5.2578033 | B5045: 0
A5046: -5.2578033 | B5046: =$K$3 -> 26.355118
A5047: -5.1872288 | B5047: =$K$3 -> 26.355118
A5048: -5.1872288 | B5048: 0
A5049: -5.1166543 | B5049: 0
A5050: -5.1166543 | B5050: =$K$3 -> 26.355118
A5051: -5.0460798 | B5051: =$K$3 -> 26.355118
A5052: -5.0460798 | B5052: 0
A5053: -4.9755052 | B5053: 0
A5054: -4.9755052 | B5054: =$K$3 -> 26.355118
A5055: -4.9049307 | B5055: =$K$3 -> 26.355118
A5056: -4.9049307 | B5056: 0
A5057: -4.8343562 | B5057: 0
...

Sheet RiskRGStrategic Cnv 2R39C1
Z1: 0.089532284
J2: Bin | K2: Height | Z2: 0.79585623
J3: 0.062396155 | K3: 0.60037534 | Z3: 0.43823032
J4: 0.18136935 | K4: 0.99437165
J5: 0.30034254 | K5: 1.388368
J6: 0.41931574 | K6: 1.5572235
J7: 0.53828893 | K7: 2.2138841
J8: 0.65726212 | K8: 0.88180128
J9: 0.77623532 | K9: 0.4502815
J10: 0.89520851 | K10: 0.22514075
J11: 1.0141817 | K11: 0.056285188
J12: 1.1331549 | K12: 0.037523459
A4001: 0.0029095581 | B4001: 0
A4002: 0.0029095581 | B4002: =$K$3 -> 0.60037534
A4003: 0.12188275 | B4003: =$K$3 -> 0.60037534
A4004: 0.12188275 | B4004: 0
A4005: 0.12188275 | B4005: =$K$4 -> 0.99437165
A4006: 0.24085595 | B4006: =$K$4 -> 0.99437165
A4007: 0.24085595 | B4007: 0
A4008: 0.24085595 | B4008: =$K$5 -> 1.388368
A4009: 0.35982914 | B4009: =$K$5 -> 1.388368
A4010: 0.35982914 | B4010: 0
A4011: 0.35982914 | B4011: =$K$6 -> 1.5572235
A4012: 0.47880233 | B4012: =$K$6 -> 1.5572235
A4013: 0.47880233 | B4013: 0
A4014: 0.47880233 | B4014: =$K$7 -> 2.2138841
A4015: 0.59777553 | B4015: =$K$7 -> 2.2138841
A4016: 0.59777553 | B4016: 0
A4017: 0.59777553 | B4017: =$K$8 -> 0.88180128
A4018: 0.71674872 | B4018: =$K$8 -> 0.88180128
A4019: 0.71674872 | B4019: 0
A4020: 0.71674872 | B4020: =$K$9 -> 0.4502815
A4021: 0.83572192 | B4021: =$K$9 -> 0.4502815
A4022: 0.83572192 | B4022: 0
A4023: 0.83572192 | B4023: =$K$10 -> 0.22514075
A4024: 0.95469511 | B4024: =$K$10 -> 0.22514075
A4025: 0.95469511 | B4025: 0
A4026: 0.95469511 | B4026: =$K$11 -> 0.056285188
A4027: 1.0736683 | B4027: =$K$11 -> 0.056285188
A4028: 1.0736683 | B4028: 0
A4029: 1.0736683 | B4029: =$K$12 -> 0.037523459
A4030: 1.1926415 | B4030: =$K$12 -> 0.037523459
A4031: 1.1926415 | B4031: 0
A5001: 0.0029095581 | B5001: 0
A5002: 0.0029095581 | B5002: =$K$3 -> 0.60037534
A5003: 0.0040992901 | B5003: =$K$3 -> 0.60037534
A5004: 0.0040992901 | B5004: 0
A5005: 0.005289022 | B5005: 0
A5006: 0.005289022 | B5006: =$K$3 -> 0.60037534
A5007: 0.0064787539 | B5007: =$K$3 -> 0.60037534
A5008: 0.0064787539 | B5008: 0
A5009: 0.0076684859 | B5009: 0
A5010: 0.0076684859 | B5010: =$K$3 -> 0.60037534
A5011: 0.0088582178 | B5011: =$K$3 -> 0.60037534
A5012: 0.0088582178 | B5012: 0
A5013: 0.01004795 | B5013: 0
A5014: 0.01004795 | B5014: =$K$3 -> 0.60037534
A5015: 0.011237682 | B5015: =$K$3 -> 0.60037534
A5016: 0.011237682 | B5016: 0
A5017: 0.012427414 | B5017: 0
A5018: 0.012427414 | B5018: =$K$3 -> 0.60037534
A5019: 0.013617146 | B5019: =$K$3 -> 0.60037534
A5020: 0.013617146 | B5020: 0
A5021: 0.014806878 | B5021: 0
A5022: 0.014806878 | B5022: =$K$3 -> 0.60037534
A5023: 0.015996609 | B5023: =$K$3 -> 0.60037534
A5024: 0.015996609 | B5024: 0
A5025: 0.017186341 | B5025: 0
A5026: 0.017186341 | B5026: =$K$3 -> 0.60037534
A5027: 0.018376073 | B5027: =$K$3 -> 0.60037534
A5028: 0.018376073 | B5028: 0
A5029: 0.019565805 | B5029: 0
A5030: 0.019565805 | B5030: =$K$3 -> 0.60037534
A5031: 0.020755537 | B5031: =$K$3 -> 0.60037534
A5032: 0.020755537 | B5032: 0
A5033: 0.021945269 | B5033: 0
A5034: 0.021945269 | B5034: =$K$3 -> 0.60037534
A5035: 0.023135001 | B5035: =$K$3 -> 0.60037534
A5036: 0.023135001 | B5036: 0
A5037: 0.024324733 | B5037: 0
A5038: 0.024324733 | B5038: =$K$3 -> 0.60037534
A5039: 0.025514465 | B5039: =$K$3 -> 0.60037534
A5040: 0.025514465 | B5040: 0
A5041: 0.026704197 | B5041: 0
A5042: 0.026704197 | B5042: =$K$3 -> 0.60037534
A5043: 0.027893929 | B5043: =$K$3 -> 0.60037534
A5044: 0.027893929 | B5044: 0
A5045: 0.029083661 | B5045: 0
A5046: 0.029083661 | B5046: =$K$3 -> 0.60037534
A5047: 0.030273393 | B5047: =$K$3 -> 0.60037534
A5048: 0.030273393 | B5048: 0
A5049: 0.031463125 | B5049: 0
A5050: 0.031463125 | B5050: =$K$3 -> 0.60037534
A5051: 0.032652857 | B5051: =$K$3 -> 0.60037534
A5052: 0.032652857 | B5052: 0
A5053: 0.033842589 | B5053: 0
A5054: 0.033842589 | B5054: =$K$3 -> 0.60037534
A5055: 0.03503232 | B5055: =$K$3 -> 0.60037534
A5056: 0.03503232 | B5056: 0
A5057: 0.036222052 | B5057: 0
...

Sheet RiskRGStrategic Cnv 2R39C6
Z1: -5.2089324
J2: Bin | K2: Height | Z2: 35.545898
J3: -3.4842251 | K3: 27.464109 | Z3: 13.033911
J4: 2.9241385 | K4: 23.406911
J5: 9.3325021 | K5: 29.336662
J6: 15.740866 | K6: 27.776202
J7: 22.149229 | K7: 20.598082
J8: 28.557593 | K8: 14.356239
J9: 34.965957 | K9: 7.8023038
J10: 41.37432 | K10: 3.4330137
J11: 47.782684 | K11: 1.2483686
J12: 54.191048 | K12: 0.62418431
A4001: -6.6884069 | B4001: 0
A4002: -6.6884069 | B4002: =$K$3 -> 27.464109
A4003: -0.28004332 | B4003: =$K$3 -> 27.464109
A4004: -0.28004332 | B4004: 0
A4005: -0.28004332 | B4005: =$K$4 -> 23.406911
A4006: 6.1283203 | B4006: =$K$4 -> 23.406911
A4007: 6.1283203 | B4007: 0
A4008: 6.1283203 | B4008: =$K$5 -> 29.336662
A4009: 12.536684 | B4009: =$K$5 -> 29.336662
A4010: 12.536684 | B4010: 0
A4011: 12.536684 | B4011: =$K$6 -> 27.776202
A4012: 18.945048 | B4012: =$K$6 -> 27.776202
A4013: 18.945048 | B4013: 0
A4014: 18.945048 | B4014: =$K$7 -> 20.598082
A4015: 25.353411 | B4015: =$K$7 -> 20.598082
A4016: 25.353411 | B4016: 0
A4017: 25.353411 | B4017: =$K$8 -> 14.356239
A4018: 31.761775 | B4018: =$K$8 -> 14.356239
A4019: 31.761775 | B4019: 0
A4020: 31.761775 | B4020: =$K$9 -> 7.8023038
A4021: 38.170138 | B4021: =$K$9 -> 7.8023038
A4022: 38.170138 | B4022: 0
A4023: 38.170138 | B4023: =$K$10 -> 3.4330137
A4024: 44.578502 | B4024: =$K$10 -> 3.4330137
A4025: 44.578502 | B4025: 0
A4026: 44.578502 | B4026: =$K$11 -> 1.2483686
A4027: 50.986866 | B4027: =$K$11 -> 1.2483686
A4028: 50.986866 | B4028: 0
A4029: 50.986866 | B4029: =$K$12 -> 0.62418431
A4030: 57.395229 | B4030: =$K$12 -> 0.62418431
A4031: 57.395229 | B4031: 0
A5001: -6.6884069 | B5001: 0
A5002: -6.6884069 | B5002: =$K$3 -> 27.464109
A5003: -6.6243233 | B5003: =$K$3 -> 27.464109
A5004: -6.6243233 | B5004: 0
A5005: -6.5602397 | B5005: 0
A5006: -6.5602397 | B5006: =$K$3 -> 27.464109
A5007: -6.496156 | B5007: =$K$3 -> 27.464109
A5008: -6.496156 | B5008: 0
A5009: -6.4320724 | B5009: 0
A5010: -6.4320724 | B5010: =$K$3 -> 27.464109
A5011: -6.3679888 | B5011: =$K$3 -> 27.464109
A5012: -6.3679888 | B5012: 0
A5013: -6.3039051 | B5013: 0
A5014: -6.3039051 | B5014: =$K$3 -> 27.464109
A5015: -6.2398215 | B5015: =$K$3 -> 27.464109
A5016: -6.2398215 | B5016: 0
A5017: -6.1757379 | B5017: 0
A5018: -6.1757379 | B5018: =$K$3 -> 27.464109
A5019: -6.1116542 | B5019: =$K$3 -> 27.464109
A5020: -6.1116542 | B5020: 0
A5021: -6.0475706 | B5021: 0
A5022: -6.0475706 | B5022: =$K$3 -> 27.464109
A5023: -5.9834869 | B5023: =$K$3 -> 27.464109
A5024: -5.9834869 | B5024: 0
A5025: -5.9194033 | B5025: 0
A5026: -5.9194033 | B5026: =$K$3 -> 27.464109
A5027: -5.8553197 | B5027: =$K$3 -> 27.464109
A5028: -5.8553197 | B5028: 0
A5029: -5.791236 | B5029: 0
A5030: -5.791236 | B5030: =$K$3 -> 27.464109
A5031: -5.7271524 | B5031: =$K$3 -> 27.464109
A5032: -5.7271524 | B5032: 0
A5033: -5.6630688 | B5033: 0
A5034: -5.6630688 | B5034: =$K$3 -> 27.464109
A5035: -5.5989851 | B5035: =$K$3 -> 27.464109
A5036: -5.5989851 | B5036: 0
A5037: -5.5349015 | B5037: 0
A5038: -5.5349015 | B5038: =$K$3 -> 27.464109
A5039: -5.4708179 | B5039: =$K$3 -> 27.464109
A5040: -5.4708179 | B5040: 0
A5041: -5.4067342 | B5041: 0
A5042: -5.4067342 | B5042: =$K$3 -> 27.464109
A5043: -5.3426506 | B5043: =$K$3 -> 27.464109
A5044: -5.3426506 | B5044: 0
A5045: -5.2785669 | B5045: 0
A5046: -5.2785669 | B5046: =$K$3 -> 27.464109
A5047: -5.2144833 | B5047: =$K$3 -> 27.464109
A5048: -5.2144833 | B5048: 0
A5049: -5.1503997 | B5049: 0
A5050: -5.1503997 | B5050: =$K$3 -> 27.464109
A5051: -5.086316 | B5051: =$K$3 -> 27.464109
A5052: -5.086316 | B5052: 0
A5053: -5.0222324 | B5053: 0
A5054: -5.0222324 | B5054: =$K$3 -> 27.464109
A5055: -4.9581488 | B5055: =$K$3 -> 27.464109
A5056: -4.9581488 | B5056: 0
A5057: -4.8940651 | B5057: 0
...

Sheet RiskRGStatic ModetatsR51C1
Z1: -2481422.8
J2: Bin | K2: Height | Z2: 1932187.6
J3: -3760525.1 | K3: 14.127506 | Z3: -260379.22
J4: -2911118.3 | K4: 42.382519
J5: -2061711.5 | K5: 122.43839
J6: -1212304.7 | K6: 230.74927
J7: -362897.9 | K7: 291.96847
J8: 486508.9 | K8: 249.58595
J9: 1335915.7 | K9: 148.33882
J10: 2185322.5 | K10: 58.86461
J11: 3034729.3 | K11: 16.482091
J12: 3884136.1 | K12: 2.3545844
A4001: -4185228.5 | B4001: 0
A4002: -4185228.5 | B4002: =$K$3 -> 14.127506
A4003: -3335821.7 | B4003: =$K$3 -> 14.127506
A4004: -3335821.7 | B4004: 0
A4005: -3335821.7 | B4005: =$K$4 -> 42.382519
A4006: -2486414.9 | B4006: =$K$4 -> 42.382519
A4007: -2486414.9 | B4007: 0
A4008: -2486414.9 | B4008: =$K$5 -> 122.43839
A4009: -1637008.1 | B4009: =$K$5 -> 122.43839
A4010: -1637008.1 | B4010: 0
A4011: -1637008.1 | B4011: =$K$6 -> 230.74927
A4012: -787601.3 | B4012: =$K$6 -> 230.74927
A4013: -787601.3 | B4013: 0
A4014: -787601.3 | B4014: =$K$7 -> 291.96847
A4015: 61805.5 | B4015: =$K$7 -> 291.96847
A4016: 61805.5 | B4016: 0
A4017: 61805.5 | B4017: =$K$8 -> 249.58595
A4018: 911212.3 | B4018: =$K$8 -> 249.58595
A4019: 911212.3 | B4019: 0
A4020: 911212.3 | B4020: =$K$9 -> 148.33882
A4021: 1760619.1 | B4021: =$K$9 -> 148.33882
A4022: 1760619.1 | B4022: 0
A4023: 1760619.1 | B4023: =$K$10 -> 58.86461
A4024: 2610025.9 | B4024: =$K$10 -> 58.86461
A4025: 2610025.9 | B4025: 0
A4026: 2610025.9 | B4026: =$K$11 -> 16.482091
A4027: 3459432.7 | B4027: =$K$11 -> 16.482091
A4028: 3459432.7 | B4028: 0
A4029: 3459432.7 | B4029: =$K$12 -> 2.3545844
A4030: 4308839.5 | B4030: =$K$12 -> 2.3545844
A4031: 4308839.5 | B4031: 0
A5001: -4185228.5 | B5001: 0
A5002: -4185228.5 | B5002: =$K$3 -> 14.127506
A5003: -4176734.4 | B5003: =$K$3 -> 14.127506
A5004: -4176734.4 | B5004: 0
A5005: -4168240.4 | B5005: 0
A5006: -4168240.4 | B5006: =$K$3 -> 14.127506
A5007: -4159746.3 | B5007: =$K$3 -> 14.127506
A5008: -4159746.3 | B5008: 0
A5009: -4151252.2 | B5009: 0
A5010: -4151252.2 | B5010: =$K$3 -> 14.127506
A5011: -4142758.2 | B5011: =$K$3 -> 14.127506
A5012: -4142758.2 | B5012: 0
A5013: -4134264.1 | B5013: 0
A5014: -4134264.1 | B5014: =$K$3 -> 14.127506
A5015: -4125770 | B5015: =$K$3 -> 14.127506
A5016: -4125770 | B5016: 0
A5017: -4117276 | B5017: 0
A5018: -4117276 | B5018: =$K$3 -> 14.127506
A5019: -4108781.9 | B5019: =$K$3 -> 14.127506
A5020: -4108781.9 | B5020: 0
A5021: -4100287.8 | B5021: 0
A5022: -4100287.8 | B5022: =$K$3 -> 14.127506
A5023: -4091793.8 | B5023: =$K$3 -> 14.127506
A5024: -4091793.8 | B5024: 0
A5025: -4083299.7 | B5025: 0
A5026: -4083299.7 | B5026: =$K$3 -> 14.127506
A5027: -4074805.6 | B5027: =$K$3 -> 14.127506
A5028: -4074805.6 | B5028: 0
A5029: -4066311.5 | B5029: 0
A5030: -4066311.5 | B5030: =$K$3 -> 14.127506
A5031: -4057817.5 | B5031: =$K$3 -> 14.127506
A5032: -4057817.5 | B5032: 0
A5033: -4049323.4 | B5033: 0
A5034: -4049323.4 | B5034: =$K$3 -> 14.127506
A5035: -4040829.3 | B5035: =$K$3 -> 14.127506
A5036: -4040829.3 | B5036: 0
A5037: -4032335.3 | B5037: 0
A5038: -4032335.3 | B5038: =$K$3 -> 14.127506
A5039: -4023841.2 | B5039: =$K$3 -> 14.127506
A5040: -4023841.2 | B5040: 0
A5041: -4015347.1 | B5041: 0
A5042: -4015347.1 | B5042: =$K$3 -> 14.127506
A5043: -4006853.1 | B5043: =$K$3 -> 14.127506
A5044: -4006853.1 | B5044: 0
A5045: -3998359 | B5045: 0
A5046: -3998359 | B5046: =$K$3 -> 14.127506
A5047: -3989864.9 | B5047: =$K$3 -> 14.127506
A5048: -3989864.9 | B5048: 0
A5049: -3981370.9 | B5049: 0
A5050: -3981370.9 | B5050: =$K$3 -> 14.127506
A5051: -3972876.8 | B5051: =$K$3 -> 14.127506
A5052: -3972876.8 | B5052: 0
A5053: -3964382.7 | B5053: 0
A5054: -3964382.7 | B5054: =$K$3 -> 14.127506
A5055: -3955888.7 | B5055: =$K$3 -> 14.127506
A5056: -3955888.7 | B5056: 0
A5057: -3947394.6 | B5057: 0
...

Sheet RiskRGStatic ModetatsR51C6
Z1: -2111418.8
J2: Bin | K2: Height | Z2: 3469036.2
J3: -3728683 | K3: 11.173516 | Z3: 696811.37
J4: -2654714.9 | K4: 33.520549
J5: -1580746.8 | K5: 96.837141
J6: -506778.65 | K6: 182.50077
J7: 567189.45 | K7: 230.91934
J8: 1641157.6 | K8: 197.39879
J9: 2715125.6 | K9: 117.32192
J10: 3789093.8 | K10: 46.556318
J11: 4863061.8 | K11: 13.035769
J12: 5937030 | K12: 1.8622527
A4001: -4265667 | B4001: 0
A4002: -4265667 | B4002: =$K$3 -> 11.173516
A4003: -3191698.9 | B4003: =$K$3 -> 11.173516
A4004: -3191698.9 | B4004: 0
A4005: -3191698.9 | B4005: =$K$4 -> 33.520549
A4006: -2117730.8 | B4006: =$K$4 -> 33.520549
A4007: -2117730.8 | B4007: 0
A4008: -2117730.8 | B4008: =$K$5 -> 96.837141
A4009: -1043762.7 | B4009: =$K$5 -> 96.837141
A4010: -1043762.7 | B4010: 0
A4011: -1043762.7 | B4011: =$K$6 -> 182.50077
A4012: 30205.4 | B4012: =$K$6 -> 182.50077
A4013: 30205.4 | B4013: 0
A4014: 30205.4 | B4014: =$K$7 -> 230.91934
A4015: 1104173.5 | B4015: =$K$7 -> 230.91934
A4016: 1104173.5 | B4016: 0
A4017: 1104173.5 | B4017: =$K$8 -> 197.39879
A4018: 2178141.6 | B4018: =$K$8 -> 197.39879
A4019: 2178141.6 | B4019: 0
A4020: 2178141.6 | B4020: =$K$9 -> 117.32192
A4021: 3252109.7 | B4021: =$K$9 -> 117.32192
A4022: 3252109.7 | B4022: 0
A4023: 3252109.7 | B4023: =$K$10 -> 46.556318
A4024: 4326077.8 | B4024: =$K$10 -> 46.556318
A4025: 4326077.8 | B4025: 0
A4026: 4326077.8 | B4026: =$K$11 -> 13.035769
A4027: 5400045.9 | B4027: =$K$11 -> 13.035769
A4028: 5400045.9 | B4028: 0
A4029: 5400045.9 | B4029: =$K$12 -> 1.8622527
A4030: 6474014 | B4030: =$K$12 -> 1.8622527
A4031: 6474014 | B4031: 0
A5001: -4265667 | B5001: 0
A5002: -4265667 | B5002: =$K$3 -> 11.173516
A5003: -4254927.3 | B5003: =$K$3 -> 11.173516
A5004: -4254927.3 | B5004: 0
A5005: -4244187.6 | B5005: 0
A5006: -4244187.6 | B5006: =$K$3 -> 11.173516
A5007: -4233448 | B5007: =$K$3 -> 11.173516
A5008: -4233448 | B5008: 0
A5009: -4222708.3 | B5009: 0
A5010: -4222708.3 | B5010: =$K$3 -> 11.173516
A5011: -4211968.6 | B5011: =$K$3 -> 11.173516
A5012: -4211968.6 | B5012: 0
A5013: -4201228.9 | B5013: 0
A5014: -4201228.9 | B5014: =$K$3 -> 11.173516
A5015: -4190489.2 | B5015: =$K$3 -> 11.173516
A5016: -4190489.2 | B5016: 0
A5017: -4179749.6 | B5017: 0
A5018: -4179749.6 | B5018: =$K$3 -> 11.173516
A5019: -4169009.9 | B5019: =$K$3 -> 11.173516
A5020: -4169009.9 | B5020: 0
A5021: -4158270.2 | B5021: 0
A5022: -4158270.2 | B5022: =$K$3 -> 11.173516
A5023: -4147530.5 | B5023: =$K$3 -> 11.173516
A5024: -4147530.5 | B5024: 0
A5025: -4136790.8 | B5025: 0
A5026: -4136790.8 | B5026: =$K$3 -> 11.173516
A5027: -4126051.1 | B5027: =$K$3 -> 11.173516
A5028: -4126051.1 | B5028: 0
A5029: -4115311.5 | B5029: 0
A5030: -4115311.5 | B5030: =$K$3 -> 11.173516
A5031: -4104571.8 | B5031: =$K$3 -> 11.173516
A5032: -4104571.8 | B5032: 0
A5033: -4093832.1 | B5033: 0
A5034: -4093832.1 | B5034: =$K$3 -> 11.173516
A5035: -4083092.4 | B5035: =$K$3 -> 11.173516
A5036: -4083092.4 | B5036: 0
A5037: -4072352.7 | B5037: 0
A5038: -4072352.7 | B5038: =$K$3 -> 11.173516
A5039: -4061613.1 | B5039: =$K$3 -> 11.173516
A5040: -4061613.1 | B5040: 0
A5041: -4050873.4 | B5041: 0
A5042: -4050873.4 | B5042: =$K$3 -> 11.173516
A5043: -4040133.7 | B5043: =$K$3 -> 11.173516
A5044: -4040133.7 | B5044: 0
A5045: -4029394 | B5045: 0
A5046: -4029394 | B5046: =$K$3 -> 11.173516
A5047: -4018654.3 | B5047: =$K$3 -> 11.173516
A5048: -4018654.3 | B5048: 0
A5049: -4007914.7 | B5049: 0
A5050: -4007914.7 | B5050: =$K$3 -> 11.173516
A5051: -3997175 | B5051: =$K$3 -> 11.173516
A5052: -3997175 | B5052: 0
A5053: -3986435.3 | B5053: 0
A5054: -3986435.3 | B5054: =$K$3 -> 11.173516
A5055: -3975695.6 | B5055: =$K$3 -> 11.173516
A5056: -3975695.6 | B5056: 0
A5057: -3964955.9 | B5057: 0
...

Sheet RiskRGSCI DynamicodelR65C6
Z1: -1808508.9
J2: Bin | K2: Height | Z2: 1650000
J3: -1806303.2 | K3: 193.82329 | Z3: -19847.59
J4: -1311006.7 | K4: 246.31709
J5: -815710.19 | K5: 270.545
J6: -320413.66 | K6: 274.58299
J7: 174882.86 | K7: 266.50702
J8: 670179.39 | K8: 262.46903
J9: 1165475.9 | K9: 238.24112
J10: 1660772.4 | K10: 262.46903
J11: 2156069 | K11: 0
J12: 2651365.5 | K12: 4.0379851
A4001: -2053951.5 | B4001: 0
A4002: -2053951.5 | B4002: =$K$3 -> 193.82329
A4003: -1558655 | B4003: =$K$3 -> 193.82329
A4004: -1558655 | B4004: 0
A4005: -1558655 | B4005: =$K$4 -> 246.31709
A4006: -1063358.4 | B4006: =$K$4 -> 246.31709
A4007: -1063358.4 | B4007: 0
A4008: -1063358.4 | B4008: =$K$5 -> 270.545
A4009: -568061.93 | B4009: =$K$5 -> 270.545
A4010: -568061.93 | B4010: 0
A4011: -568061.93 | B4011: =$K$6 -> 274.58299
A4012: -72765.4 | B4012: =$K$6 -> 274.58299
A4013: -72765.4 | B4013: 0
A4014: -72765.4 | B4014: =$K$7 -> 266.50702
A4015: 422531.12 | B4015: =$K$7 -> 266.50702
A4016: 422531.12 | B4016: 0
A4017: 422531.12 | B4017: =$K$8 -> 262.46903
A4018: 917827.65 | B4018: =$K$8 -> 262.46903
A4019: 917827.65 | B4019: 0
A4020: 917827.65 | B4020: =$K$9 -> 238.24112
A4021: 1413124.2 | B4021: =$K$9 -> 238.24112
A4022: 1413124.2 | B4022: 0
A4023: 1413124.2 | B4023: =$K$10 -> 262.46903
A4024: 1908420.7 | B4024: =$K$10 -> 262.46903
A4025: 1908420.7 | B4025: 0
A4026: 1908420.7 | B4026: =$K$11 -> 0
A4027: 2403717.2 | B4027: =$K$11 -> 0
A4028: 2403717.2 | B4028: 0
A4029: 2403717.2 | B4029: =$K$12 -> 4.0379851
A4030: 2899013.8 | B4030: =$K$12 -> 4.0379851
A4031: 2899013.8 | B4031: 0
A5001: -2053951.5 | B5001: 0
A5002: -2053951.5 | B5002: =$K$3 -> 193.82329
A5003: -2048998.5 | B5003: =$K$3 -> 193.82329
A5004: -2048998.5 | B5004: 0
A5005: -2044045.6 | B5005: 0
A5006: -2044045.6 | B5006: =$K$3 -> 193.82329
A5007: -2039092.6 | B5007: =$K$3 -> 193.82329
A5008: -2039092.6 | B5008: 0
A5009: -2034139.6 | B5009: 0
A5010: -2034139.6 | B5010: =$K$3 -> 193.82329
A5011: -2029186.7 | B5011: =$K$3 -> 193.82329
A5012: -2029186.7 | B5012: 0
A5013: -2024233.7 | B5013: 0
A5014: -2024233.7 | B5014: =$K$3 -> 193.82329
A5015: -2019280.7 | B5015: =$K$3 -> 193.82329
A5016: -2019280.7 | B5016: 0
A5017: -2014327.8 | B5017: 0
A5018: -2014327.8 | B5018: =$K$3 -> 193.82329
A5019: -2009374.8 | B5019: =$K$3 -> 193.82329
A5020: -2009374.8 | B5020: 0
A5021: -2004421.8 | B5021: 0
A5022: -2004421.8 | B5022: =$K$3 -> 193.82329
A5023: -1999468.9 | B5023: =$K$3 -> 193.82329
A5024: -1999468.9 | B5024: 0
A5025: -1994515.9 | B5025: 0
A5026: -1994515.9 | B5026: =$K$3 -> 193.82329
A5027: -1989563 | B5027: =$K$3 -> 193.82329
A5028: -1989563 | B5028: 0
A5029: -1984610 | B5029: 0
A5030: -1984610 | B5030: =$K$3 -> 193.82329
A5031: -1979657 | B5031: =$K$3 -> 193.82329
A5032: -1979657 | B5032: 0
A5033: -1974704.1 | B5033: 0
A5034: -1974704.1 | B5034: =$K$3 -> 193.82329
A5035: -1969751.1 | B5035: =$K$3 -> 193.82329
A5036: -1969751.1 | B5036: 0
A5037: -1964798.1 | B5037: 0
A5038: -1964798.1 | B5038: =$K$3 -> 193.82329
A5039: -1959845.2 | B5039: =$K$3 -> 193.82329
A5040: -1959845.2 | B5040: 0
A5041: -1954892.2 | B5041: 0
A5042: -1954892.2 | B5042: =$K$3 -> 193.82329
A5043: -1949939.2 | B5043: =$K$3 -> 193.82329
A5044: -1949939.2 | B5044: 0
A5045: -1944986.3 | B5045: 0
A5046: -1944986.3 | B5046: =$K$3 -> 193.82329
A5047: -1940033.3 | B5047: =$K$3 -> 193.82329
A5048: -1940033.3 | B5048: 0
A5049: -1935080.3 | B5049: 0
A5050: -1935080.3 | B5050: =$K$3 -> 193.82329
A5051: -1930127.4 | B5051: =$K$3 -> 193.82329
A5052: -1930127.4 | B5052: 0
A5053: -1925174.4 | B5053: 0
A5054: -1925174.4 | B5054: =$K$3 -> 193.82329
A5055: -1920221.4 | B5055: =$K$3 -> 193.82329
A5056: -1920221.4 | B5056: 0
A5057: -1915268.5 | B5057: 0
...

Sheet RiskRGStatic ModetatsR33C1
Z1: -8.6462927
J2: Bin | K2: Height | Z2: 37.748196
J3: -27.397892 | K3: 0.48414215 | Z3: 14.631968
J4: -19.135855 | K4: 1.6944975
J5: -10.873819 | K5: 5.5676347
J6: -2.6117829 | K6: 13.55598
J7: 5.6502534 | K7: 22.875717
J8: 13.91229 | K8: 27.838174
J9: 22.174326 | K9: 24.328143
J10: 30.436362 | K10: 15.129442
J11: 38.698398 | K11: 6.7779901
J12: 46.960435 | K12: 2.2996752
J13: 55.222471 | K13: 0.48414215
A4001: -31.52891 | B4001: 0
A4002: -31.52891 | B4002: =$K$3 -> 0.48414215
A4003: -23.266873 | B4003: =$K$3 -> 0.48414215
A4004: -23.266873 | B4004: 0
A4005: -23.266873 | B4005: =$K$4 -> 1.6944975
A4006: -15.004837 | B4006: =$K$4 -> 1.6944975
A4007: -15.004837 | B4007: 0
A4008: -15.004837 | B4008: =$K$5 -> 5.5676347
A4009: -6.742801 | B4009: =$K$5 -> 5.5676347
A4010: -6.742801 | B4010: 0
A4011: -6.742801 | B4011: =$K$6 -> 13.55598
A4012: 1.5192353 | B4012: =$K$6 -> 13.55598
A4013: 1.5192353 | B4013: 0
A4014: 1.5192353 | B4014: =$K$7 -> 22.875717
A4015: 9.7812715 | B4015: =$K$7 -> 22.875717
A4016: 9.7812715 | B4016: 0
A4017: 9.7812715 | B4017: =$K$8 -> 27.838174
A4018: 18.043308 | B4018: =$K$8 -> 27.838174
A4019: 18.043308 | B4019: 0
A4020: 18.043308 | B4020: =$K$9 -> 24.328143
A4021: 26.305344 | B4021: =$K$9 -> 24.328143
A4022: 26.305344 | B4022: 0
A4023: 26.305344 | B4023: =$K$10 -> 15.129442
A4024: 34.56738 | B4024: =$K$10 -> 15.129442
A4025: 34.56738 | B4025: 0
A4026: 34.56738 | B4026: =$K$11 -> 6.7779901
A4027: 42.829416 | B4027: =$K$11 -> 6.7779901
A4028: 42.829416 | B4028: 0
A4029: 42.829416 | B4029: =$K$12 -> 2.2996752
A4030: 51.091453 | B4030: =$K$12 -> 2.2996752
A4031: 51.091453 | B4031: 0
A4032: 51.091453 | B4032: =$K$13 -> 0.48414215
A4033: 59.353489 | B4033: =$K$13 -> 0.48414215
A4034: 59.353489 | B4034: 0
A5001: -31.52891 | B5001: 0
A5002: -31.52891 | B5002: =$K$3 -> 0.48414215
A5003: -31.438027 | B5003: =$K$3 -> 0.48414215
A5004: -31.438027 | B5004: 0
A5005: -31.347145 | B5005: 0
A5006: -31.347145 | B5006: =$K$3 -> 0.48414215
A5007: -31.256262 | B5007: =$K$3 -> 0.48414215
A5008: -31.256262 | B5008: 0
A5009: -31.16538 | B5009: 0
A5010: -31.16538 | B5010: =$K$3 -> 0.48414215
A5011: -31.074498 | B5011: =$K$3 -> 0.48414215
A5012: -31.074498 | B5012: 0
A5013: -30.983615 | B5013: 0
A5014: -30.983615 | B5014: =$K$3 -> 0.48414215
A5015: -30.892733 | B5015: =$K$3 -> 0.48414215
A5016: -30.892733 | B5016: 0
A5017: -30.80185 | B5017: 0
A5018: -30.80185 | B5018: =$K$3 -> 0.48414215
A5019: -30.710968 | B5019: =$K$3 -> 0.48414215
A5020: -30.710968 | B5020: 0
A5021: -30.620086 | B5021: 0
A5022: -30.620086 | B5022: =$K$3 -> 0.48414215
A5023: -30.529203 | B5023: =$K$3 -> 0.48414215
A5024: -30.529203 | B5024: 0
A5025: -30.438321 | B5025: 0
A5026: -30.438321 | B5026: =$K$3 -> 0.48414215
A5027: -30.347439 | B5027: =$K$3 -> 0.48414215
A5028: -30.347439 | B5028: 0
A5029: -30.256556 | B5029: 0
A5030: -30.256556 | B5030: =$K$3 -> 0.48414215
A5031: -30.165674 | B5031: =$K$3 -> 0.48414215
A5032: -30.165674 | B5032: 0
A5033: -30.074791 | B5033: 0
A5034: -30.074791 | B5034: =$K$3 -> 0.48414215
A5035: -29.983909 | B5035: =$K$3 -> 0.48414215
A5036: -29.983909 | B5036: 0
A5037: -29.893027 | B5037: 0
A5038: -29.893027 | B5038: =$K$3 -> 0.48414215
A5039: -29.802144 | B5039: =$K$3 -> 0.48414215
A5040: -29.802144 | B5040: 0
A5041: -29.711262 | B5041: 0
A5042: -29.711262 | B5042: =$K$3 -> 0.48414215
A5043: -29.620379 | B5043: =$K$3 -> 0.48414215
A5044: -29.620379 | B5044: 0
A5045: -29.529497 | B5045: 0
A5046: -29.529497 | B5046: =$K$3 -> 0.48414215
A5047: -29.438615 | B5047: =$K$3 -> 0.48414215
A5048: -29.438615 | B5048: 0
A5049: -29.347732 | B5049: 0
A5050: -29.347732 | B5050: =$K$3 -> 0.48414215
A5051: -29.25685 | B5051: =$K$3 -> 0.48414215
A5052: -29.25685 | B5052: 0
A5053: -29.165967 | B5053: 0
...

Sheet RiskRGStatic ModetatsR33C6
Z1: 0.063053714
J2: Bin | K2: Height | Z2: 0.96671053
J3: -0.050290857 | K3: 0.22684741 | Z3: 0.50226041
J4: 0.090848404 | K4: 0.54443378
J5: 0.23198766 | K5: 0.9603207
J6: 0.37312693 | K6: 1.3081534
J7: 0.51426619 | K7: 1.4064539
J8: 0.65540545 | K8: 1.1796065
J9: 0.79654471 | K9: 0.77884277
J10: 0.93768397 | K10: 0.40832534
J11: 1.0788232 | K11: 0.18147793
J12: 1.2199625 | K12: 0.068054223
J13: 1.3611018 | K13: 0.022684741
A4001: -0.12086049 | B4001: 0
A4002: -0.12086049 | B4002: =$K$3 -> 0.22684741
A4003: 0.020278774 | B4003: =$K$3 -> 0.22684741
A4004: 0.020278774 | B4004: 0
A4005: 0.020278774 | B4005: =$K$4 -> 0.54443378
A4006: 0.16141803 | B4006: =$K$4 -> 0.54443378
A4007: 0.16141803 | B4007: 0
A4008: 0.16141803 | B4008: =$K$5 -> 0.9603207
A4009: 0.3025573 | B4009: =$K$5 -> 0.9603207
A4010: 0.3025573 | B4010: 0
A4011: 0.3025573 | B4011: =$K$6 -> 1.3081534
A4012: 0.44369656 | B4012: =$K$6 -> 1.3081534
A4013: 0.44369656 | B4013: 0
A4014: 0.44369656 | B4014: =$K$7 -> 1.4064539
A4015: 0.58483582 | B4015: =$K$7 -> 1.4064539
A4016: 0.58483582 | B4016: 0
A4017: 0.58483582 | B4017: =$K$8 -> 1.1796065
A4018: 0.72597508 | B4018: =$K$8 -> 1.1796065
A4019: 0.72597508 | B4019: 0
A4020: 0.72597508 | B4020: =$K$9 -> 0.77884277
A4021: 0.86711434 | B4021: =$K$9 -> 0.77884277
A4022: 0.86711434 | B4022: 0
A4023: 0.86711434 | B4023: =$K$10 -> 0.40832534
A4024: 1.0082536 | B4024: =$K$10 -> 0.40832534
A4025: 1.0082536 | B4025: 0
A4026: 1.0082536 | B4026: =$K$11 -> 0.18147793
A4027: 1.1493929 | B4027: =$K$11 -> 0.18147793
A4028: 1.1493929 | B4028: 0
A4029: 1.1493929 | B4029: =$K$12 -> 0.068054223
A4030: 1.2905321 | B4030: =$K$12 -> 0.068054223
A4031: 1.2905321 | B4031: 0
A4032: 1.2905321 | B4032: =$K$13 -> 0.022684741
A4033: 1.4316714 | B4033: =$K$13 -> 0.022684741
A4034: 1.4316714 | B4034: 0
A5001: -0.12086049 | B5001: 0
A5002: -0.12086049 | B5002: =$K$3 -> 0.22684741
A5003: -0.11930796 | B5003: =$K$3 -> 0.22684741
A5004: -0.11930796 | B5004: 0
A5005: -0.11775542 | B5005: 0
A5006: -0.11775542 | B5006: =$K$3 -> 0.22684741
A5007: -0.11620289 | B5007: =$K$3 -> 0.22684741
A5008: -0.11620289 | B5008: 0
A5009: -0.11465036 | B5009: 0
A5010: -0.11465036 | B5010: =$K$3 -> 0.22684741
A5011: -0.11309783 | B5011: =$K$3 -> 0.22684741
A5012: -0.11309783 | B5012: 0
A5013: -0.1115453 | B5013: 0
A5014: -0.1115453 | B5014: =$K$3 -> 0.22684741
A5015: -0.10999276 | B5015: =$K$3 -> 0.22684741
A5016: -0.10999276 | B5016: 0
A5017: -0.10844023 | B5017: 0
A5018: -0.10844023 | B5018: =$K$3 -> 0.22684741
A5019: -0.1068877 | B5019: =$K$3 -> 0.22684741
A5020: -0.1068877 | B5020: 0
A5021: -0.10533517 | B5021: 0
A5022: -0.10533517 | B5022: =$K$3 -> 0.22684741
A5023: -0.10378264 | B5023: =$K$3 -> 0.22684741
A5024: -0.10378264 | B5024: 0
A5025: -0.1022301 | B5025: 0
A5026: -0.1022301 | B5026: =$K$3 -> 0.22684741
A5027: -0.10067757 | B5027: =$K$3 -> 0.22684741
A5028: -0.10067757 | B5028: 0
A5029: -0.099125041 | B5029: 0
A5030: -0.099125041 | B5030: =$K$3 -> 0.22684741
A5031: -0.097572509 | B5031: =$K$3 -> 0.22684741
A5032: -0.097572509 | B5032: 0
A5033: -0.096019977 | B5033: 0
A5034: -0.096019977 | B5034: =$K$3 -> 0.22684741
A5035: -0.094467445 | B5035: =$K$3 -> 0.22684741
A5036: -0.094467445 | B5036: 0
A5037: -0.092914914 | B5037: 0
A5038: -0.092914914 | B5038: =$K$3 -> 0.22684741
A5039: -0.091362382 | B5039: =$K$3 -> 0.22684741
A5040: -0.091362382 | B5040: 0
A5041: -0.08980985 | B5041: 0
A5042: -0.08980985 | B5042: =$K$3 -> 0.22684741
A5043: -0.088257318 | B5043: =$K$3 -> 0.22684741
A5044: -0.088257318 | B5044: 0
A5045: -0.086704786 | B5045: 0
A5046: -0.086704786 | B5046: =$K$3 -> 0.22684741
A5047: -0.085152254 | B5047: =$K$3 -> 0.22684741
A5048: -0.085152254 | B5048: 0
A5049: -0.083599722 | B5049: 0
A5050: -0.083599722 | B5050: =$K$3 -> 0.22684741
A5051: -0.082047191 | B5051: =$K$3 -> 0.22684741
A5052: -0.082047191 | B5052: 0
A5053: -0.080494659 | B5053: 0
...

Sheet RiskRGSCI DynamicodelR39C1
Z1: 0.10678878
J2: Bin | K2: Height | Z2: 0.87569126
J3: 0.062042684 | K3: 0.49150896 | Z3: 0.48029152
J4: 0.18224591 | K4: 0.82828363
J5: 0.30244913 | K5: 1.1832623
J6: 0.42265236 | K6: 1.4563229
J7: 0.54285559 | K7: 2.2117903
J8: 0.66305881 | K8: 1.010324
J9: 0.78326204 | K9: 0.6098352
J10: 0.90346526 | K10: 0.30946861
J11: 1.0236685 | K11: 0.13653027
J12: 1.1438717 | K12: 0.054612107
J13: 1.2640749 | K13: 0.027306054
A4001: 0.0019410715 | B4001: 0
A4002: 0.0019410715 | B4002: =$K$3 -> 0.49150896
A4003: 0.1221443 | B4003: =$K$3 -> 0.49150896
A4004: 0.1221443 | B4004: 0
A4005: 0.1221443 | B4005: =$K$4 -> 0.82828363
A4006: 0.24234752 | B4006: =$K$4 -> 0.82828363
A4007: 0.24234752 | B4007: 0
A4008: 0.24234752 | B4008: =$K$5 -> 1.1832623
A4009: 0.36255075 | B4009: =$K$5 -> 1.1832623
A4010: 0.36255075 | B4010: 0
A4011: 0.36255075 | B4011: =$K$6 -> 1.4563229
A4012: 0.48275397 | B4012: =$K$6 -> 1.4563229
A4013: 0.48275397 | B4013: 0
A4014: 0.48275397 | B4014: =$K$7 -> 2.2117903
A4015: 0.6029572 | B4015: =$K$7 -> 2.2117903
A4016: 0.6029572 | B4016: 0
A4017: 0.6029572 | B4017: =$K$8 -> 1.010324
A4018: 0.72316042 | B4018: =$K$8 -> 1.010324
A4019: 0.72316042 | B4019: 0
A4020: 0.72316042 | B4020: =$K$9 -> 0.6098352
A4021: 0.84336365 | B4021: =$K$9 -> 0.6098352
A4022: 0.84336365 | B4022: 0
A4023: 0.84336365 | B4023: =$K$10 -> 0.30946861
A4024: 0.96356687 | B4024: =$K$10 -> 0.30946861
A4025: 0.96356687 | B4025: 0
A4026: 0.96356687 | B4026: =$K$11 -> 0.13653027
A4027: 1.0837701 | B4027: =$K$11 -> 0.13653027
A4028: 1.0837701 | B4028: 0
A4029: 1.0837701 | B4029: =$K$12 -> 0.054612107
A4030: 1.2039733 | B4030: =$K$12 -> 0.054612107
A4031: 1.2039733 | B4031: 0
A4032: 1.2039733 | B4032: =$K$13 -> 0.027306054
A4033: 1.3241765 | B4033: =$K$13 -> 0.027306054
A4034: 1.3241765 | B4034: 0
A5001: 0.0019410715 | B5001: 0
A5002: 0.0019410715 | B5002: =$K$3 -> 0.49150896
A5003: 0.003263307 | B5003: =$K$3 -> 0.49150896
A5004: 0.003263307 | B5004: 0
A5005: 0.0045855424 | B5005: 0
A5006: 0.0045855424 | B5006: =$K$3 -> 0.49150896
A5007: 0.0059077779 | B5007: =$K$3 -> 0.49150896
A5008: 0.0059077779 | B5008: 0
A5009: 0.0072300134 | B5009: 0
A5010: 0.0072300134 | B5010: =$K$3 -> 0.49150896
A5011: 0.0085522489 | B5011: =$K$3 -> 0.49150896
A5012: 0.0085522489 | B5012: 0
A5013: 0.0098744843 | B5013: 0
A5014: 0.0098744843 | B5014: =$K$3 -> 0.49150896
A5015: 0.01119672 | B5015: =$K$3 -> 0.49150896
A5016: 0.01119672 | B5016: 0
A5017: 0.012518955 | B5017: 0
A5018: 0.012518955 | B5018: =$K$3 -> 0.49150896
A5019: 0.013841191 | B5019: =$K$3 -> 0.49150896
A5020: 0.013841191 | B5020: 0
A5021: 0.015163426 | B5021: 0
A5022: 0.015163426 | B5022: =$K$3 -> 0.49150896
A5023: 0.016485662 | B5023: =$K$3 -> 0.49150896
A5024: 0.016485662 | B5024: 0
A5025: 0.017807897 | B5025: 0
A5026: 0.017807897 | B5026: =$K$3 -> 0.49150896
A5027: 0.019130133 | B5027: =$K$3 -> 0.49150896
A5028: 0.019130133 | B5028: 0
A5029: 0.020452368 | B5029: 0
A5030: 0.020452368 | B5030: =$K$3 -> 0.49150896
A5031: 0.021774604 | B5031: =$K$3 -> 0.49150896
A5032: 0.021774604 | B5032: 0
A5033: 0.023096839 | B5033: 0
A5034: 0.023096839 | B5034: =$K$3 -> 0.49150896
A5035: 0.024419075 | B5035: =$K$3 -> 0.49150896
A5036: 0.024419075 | B5036: 0
A5037: 0.02574131 | B5037: 0
A5038: 0.02574131 | B5038: =$K$3 -> 0.49150896
A5039: 0.027063546 | B5039: =$K$3 -> 0.49150896
A5040: 0.027063546 | B5040: 0
A5041: 0.028385781 | B5041: 0
A5042: 0.028385781 | B5042: =$K$3 -> 0.49150896
A5043: 0.029708017 | B5043: =$K$3 -> 0.49150896
A5044: 0.029708017 | B5044: 0
A5045: 0.031030252 | B5045: 0
A5046: 0.031030252 | B5046: =$K$3 -> 0.49150896
A5047: 0.032352487 | B5047: =$K$3 -> 0.49150896
A5048: 0.032352487 | B5048: 0
A5049: 0.033674723 | B5049: 0
A5050: 0.033674723 | B5050: =$K$3 -> 0.49150896
A5051: 0.034996958 | B5051: =$K$3 -> 0.49150896
A5052: 0.034996958 | B5052: 0
A5053: 0.036319194 | B5053: 0
...

Sheet RiskRGSCI DynamicodelR39C6
Z1: -5.1260891
J2: Bin | K2: Height | Z2: 40.155487
J3: -3.5989465 | K3: 22.141753 | Z3: 15.655104
J4: 2.8594399 | K4: 19.974029
J5: 9.3178264 | K5: 26.167527
J6: 15.776213 | K6: 26.941714
J7: 22.234599 | K7: 22.296591
J8: 28.692986 | K8: 16.877281
J9: 35.151372 | K9: 10.683783
J10: 41.609759 | K10: 5.7289851
J11: 48.068145 | K11: 2.6322364
J12: 54.526532 | K12: 0.92902462
J13: 60.984918 | K13: 0.46451231
A4001: -6.8281398 | B4001: 0
A4002: -6.8281398 | B4002: =$K$3 -> 22.141753
A4003: -0.36975332 | B4003: =$K$3 -> 22.141753
A4004: -0.36975332 | B4004: 0
A4005: -0.36975332 | B4005: =$K$4 -> 19.974029
A4006: 6.0886331 | B4006: =$K$4 -> 19.974029
A4007: 6.0886331 | B4007: 0
A4008: 6.0886331 | B4008: =$K$5 -> 26.167527
A4009: 12.54702 | B4009: =$K$5 -> 26.167527
A4010: 12.54702 | B4010: 0
A4011: 12.54702 | B4011: =$K$6 -> 26.941714
A4012: 19.005406 | B4012: =$K$6 -> 26.941714
A4013: 19.005406 | B4013: 0
A4014: 19.005406 | B4014: =$K$7 -> 22.296591
A4015: 25.463793 | B4015: =$K$7 -> 22.296591
A4016: 25.463793 | B4016: 0
A4017: 25.463793 | B4017: =$K$8 -> 16.877281
A4018: 31.922179 | B4018: =$K$8 -> 16.877281
A4019: 31.922179 | B4019: 0
A4020: 31.922179 | B4020: =$K$9 -> 10.683783
A4021: 38.380565 | B4021: =$K$9 -> 10.683783
A4022: 38.380565 | B4022: 0
A4023: 38.380565 | B4023: =$K$10 -> 5.7289851
A4024: 44.838952 | B4024: =$K$10 -> 5.7289851
A4025: 44.838952 | B4025: 0
A4026: 44.838952 | B4026: =$K$11 -> 2.6322364
A4027: 51.297338 | B4027: =$K$11 -> 2.6322364
A4028: 51.297338 | B4028: 0
A4029: 51.297338 | B4029: =$K$12 -> 0.92902462
A4030: 57.755725 | B4030: =$K$12 -> 0.92902462
A4031: 57.755725 | B4031: 0
A4032: 57.755725 | B4032: =$K$13 -> 0.46451231
A4033: 64.214111 | B4033: =$K$13 -> 0.46451231
A4034: 64.214111 | B4034: 0
A5001: -6.8281398 | B5001: 0
A5002: -6.8281398 | B5002: =$K$3 -> 22.141753
A5003: -6.7570975 | B5003: =$K$3 -> 22.141753
A5004: -6.7570975 | B5004: 0
A5005: -6.6860553 | B5005: 0
A5006: -6.6860553 | B5006: =$K$3 -> 22.141753
A5007: -6.615013 | B5007: =$K$3 -> 22.141753
A5008: -6.615013 | B5008: 0
A5009: -6.5439708 | B5009: 0
A5010: -6.5439708 | B5010: =$K$3 -> 22.141753
A5011: -6.4729285 | B5011: =$K$3 -> 22.141753
A5012: -6.4729285 | B5012: 0
A5013: -6.4018863 | B5013: 0
A5014: -6.4018863 | B5014: =$K$3 -> 22.141753
A5015: -6.330844 | B5015: =$K$3 -> 22.141753
A5016: -6.330844 | B5016: 0
A5017: -6.2598018 | B5017: 0
A5018: -6.2598018 | B5018: =$K$3 -> 22.141753
A5019: -6.1887595 | B5019: =$K$3 -> 22.141753
A5020: -6.1887595 | B5020: 0
A5021: -6.1177173 | B5021: 0
A5022: -6.1177173 | B5022: =$K$3 -> 22.141753
A5023: -6.046675 | B5023: =$K$3 -> 22.141753
A5024: -6.046675 | B5024: 0
A5025: -5.9756328 | B5025: 0
A5026: -5.9756328 | B5026: =$K$3 -> 22.141753
A5027: -5.9045905 | B5027: =$K$3 -> 22.141753
A5028: -5.9045905 | B5028: 0
A5029: -5.8335483 | B5029: 0
A5030: -5.8335483 | B5030: =$K$3 -> 22.141753
A5031: -5.762506 | B5031: =$K$3 -> 22.141753
A5032: -5.762506 | B5032: 0
A5033: -5.6914638 | B5033: 0
A5034: -5.6914638 | B5034: =$K$3 -> 22.141753
A5035: -5.6204215 | B5035: =$K$3 -> 22.141753
A5036: -5.6204215 | B5036: 0
A5037: -5.5493793 | B5037: 0
A5038: -5.5493793 | B5038: =$K$3 -> 22.141753
A5039: -5.478337 | B5039: =$K$3 -> 22.141753
A5040: -5.478337 | B5040: 0
A5041: -5.4072948 | B5041: 0
A5042: -5.4072948 | B5042: =$K$3 -> 22.141753
A5043: -5.3362525 | B5043: =$K$3 -> 22.141753
A5044: -5.3362525 | B5044: 0
A5045: -5.2652103 | B5045: 0
A5046: -5.2652103 | B5046: =$K$3 -> 22.141753
A5047: -5.194168 | B5047: =$K$3 -> 22.141753
A5048: -5.194168 | B5048: 0
A5049: -5.1231258 | B5049: 0
A5050: -5.1231258 | B5050: =$K$3 -> 22.141753
A5051: -5.0520835 | B5051: =$K$3 -> 22.141753
A5052: -5.0520835 | B5052: 0
A5053: -4.9810413 | B5053: 0
...

Sheet Company Data & Beta 
A1: F370 SU 2025 I-core Case Finance Raw Data for Company and Project beta
F2: These five projects comprise all of the company's business lines over the past five years.
A4: Past Security Returns (Percent) | F4: Monthly Gross Margin data for Recent Projects | N4: GM-to-Return Percentages
A5: Year | B5: Month | C5: Historic S&P 500 Mthly Return % | D5: Company Mthly Return % | E5: Historic 1 yr T-Bill % | F5: Project P | G5: Project Q | H5: Project R | I5: Project S | J5: Project T | K5: Tax Rate (see case) | L5: Debt to Equity (see case) | M5: Sum of Gross Margins | N5: P | O5: Q | P5: R | Q5: S | R5: T | S5: All
A6: 2020 | B6: Jan | C6: 0.10011 | D6: 0.4 | E6: 0.0222 | F6: 714457.65 | G6: 773731.5 | H6: 913232.49 | I6: 116227.2 | J6: 221553.95 | K6: 0.218 | L6: 0.185 | M6: =SUM(F6:J6) -> 2739202.8
B7: Feb | C7: -0.04543 | D7: -0.05 | E7: 0.0252 | F7: 879240.34 | G7: 752901.08 | H7: 1076028.6 | I7: 173700.86 | J7: 331111.05 | K7: 0.218 | L7: 0.185 | M7: =SUM(F7:J7) -> 3212981.9 | N7: =(F7-F6)/F6 -> 0.23064024 | O7: =(G7-G6)/G6 -> -0.026922019 | P7: =(H7-H6)/H6 -> 0.1782636 | Q7: =(I7-I6)/I6 -> 0.49449402 | R7: =(J7-J6)/J6 -> 0.49449402 | S7: =(M7-M6)/M6 -> 0.17296242
B8: Mar | C8: 0.06711 | D8: 0.089 | E8: 0.0282 | F8: 855569.41 | G8: 745813.39 | H8: 1061051.4 | I8: 162214.96 | J8: 309216.47 | K8: 0.218 | L8: 0.185 | M8: =SUM(F8:J8) -> 3133865.6 | N8: =(F8-F7)/F7 -> -0.026922019 | O8: =(G8-G7)/G7 -> -0.0094138389 | P8: =(H8-H7)/H7 -> -0.013918946 | Q8: =(I8-I7)/I7 -> -0.066124595 | R8: =(J8-J7)/J7 -> -0.066124595 | S8: =(M8-M7)/M7 -> -0.024623942
B9: Apr | C9: 0.08282 | D9: 0.09 | E9: 0.0312 | F9: 847515.22 | G9: 822354.34 | H9: 972641.77 | I9: 126258.94 | J9: 240676.58 | K9: 0.218 | L9: 0.185 | M9: =SUM(F9:J9) -> 3009446.9 | N9: =(F9-F8)/F8 -> -0.0094138389 | O9: =(G9-G8)/G8 -> 0.10262748 | P9: =(H9-H8)/H8 -> -0.083322675 | Q9: =(I9-I8)/I8 -> -0.22165664 | R9: =(J9-J8)/J8 -> -0.22165664 | S9: =(M9-M8)/M8 -> -0.03970138
B10: May | C10: -0.07336 | D10: -0.11 | E10: 0.0342 | F10: 934493.57 | G10: 732477.27 | H10: 1226377.7 | I10: 223556.55 | J10: 426146.69 | K10: 0.218 | L10: 0.185 | M10: =SUM(F10:J10) -> 3543051.8 | N10: =(F10-F9)/F9 -> 0.10262748 | O10: =(G10-G9)/G9 -> -0.1092924 | P10: =(H10-H9)/H9 -> 0.26087293 | Q10: =(I10-I9)/I9 -> 0.77061964 | R10: =(J10-J9)/J9 -> 0.77061964 | S10: =(M10-M9)/M9 -> 0.17730996
B11: Jun | C11: 0.26562 | D11: 0.44 | E11: 0.03 | F11: 832360.53 | G11: 748417.38 | H11: 992593.76 | I11: 157258.56 | J11: 299768.52 | K11: 0.218 | L11: 0.185 | M11: =SUM(F11:J11) -> 3030398.8 | N11: =(F11-F10)/F10 -> -0.1092924 | O11: =(G11-G10)/G10 -> 0.021761928 | P11: =(H11-H10)/H10 -> -0.19062963 | Q11: =(I11-I10)/I10 -> -0.29656025 | R11: =(J11-J10)/J10 -> -0.29656025 | S11: =(M11-M10)/M10 -> -0.1446925
B12: Jul | C12: -0.06657 | D12: -0.08 | E12: 0.0342 | F12: 850474.3 | G12: 613994.14 | H12: 1019811.6 | I12: 145252.6 | J12: 276882.57 | K12: 0.218 | L12: 0.185 | M12: =SUM(F12:J12) -> 2906415.2 | N12: =(F12-F11)/F11 -> 0.021761928 | O12: =(G12-G11)/G11 -> -0.17960999 | P12: =(H12-H11)/H11 -> 0.02742094 | Q12: =(I12-I11)/I11 -> -0.07634541 | R12: =(J12-J11)/J11 -> -0.07634541 | S12: =(M12-M11)/M11 -> -0.040913275
B13: Aug | C13: 0.13874 | D13: 0.19748 | E13: 0.0341 | F13: 697720.62 | G13: 703527.49 | H13: 890771.23 | I13: 117497.95 | J13: 223976.26 | K13: 0.218 | L13: 0.185 | M13: =SUM(F13:J13) -> 2633493.6 | N13: =(F13-F12)/F12 -> -0.17960999 | O13: =(G13-G12)/G12 -> 0.14582117 | P13: =(H13-H12)/H12 -> -0.12653354 | Q13: =(I13-I12)/I12 -> -0.19107849 | R13: =(J13-J12)/J12 -> -0.19107849 | S13: =(M13-M12)/M12 -> -0.093903191
B14: Sep | C14: -0.01728 | D14: -0.48918 | E14: 0.0348 | F14: 799463.06 | G14: 706376.37 | H14: 961304.65 | I14: 147679.37 | J14: 281508.51 | K14: 0.218 | L14: 0.185 | M14: =SUM(F14:J14) -> 2896332 | N14: =(F14-F13)/F13 -> 0.14582117 | O14: =(G14-G13)/G13 -> 0.0040494284 | P14: =(H14-H13)/H13 -> 0.079182415 | Q14: =(I14-I13)/I13 -> 0.25686761 | R14: =(J14-J13)/J13 -> 0.25686761 | S14: =(M14-M13)/M13 -> 0.09980598
B15: Oct | C15: 0.3788 | D15: 0.4 | E15: 0.0286 | F15: 802700.42 | G15: 792008.87 | H15: 998111.94 | I15: 142145.92 | J15: 270960.58 | K15: 0.218 | L15: 0.185 | M15: =SUM(F15:J15) -> 3005927.7 | N15: =(F15-F14)/F14 -> 0.0040494284 | O15: =(G15-G14)/G14 -> 0.12122786 | P15: =(H15-H14)/H14 -> 0.038288887 | Q15: =(I15-I14)/I14 -> -0.037469318 | R15: =(J15-J14)/J14 -> -0.037469318 | S15: =(M15-M14)/M14 -> 0.037839506
B16: Nov | C16: 0.10543 | D16: -0.001 | E16: 0.0248 | F16: 900010.08 | G16: 794112.16 | H16: 1216855.3 | I16: 228854.83 | J16: 436246.33 | K16: 0.218 | L16: 0.185 | M16: =SUM(F16:J16) -> 3576078.7 | N16: =(F16-F15)/F15 -> 0.12122786 | O16: =(G16-G15)/G15 -> 0.0026556405 | P16: =(H16-H15)/H15 -> 0.21915719 | Q16: =(I16-I15)/I15 -> 0.60999926 | R16: =(J16-J15)/J15 -> 0.60999926 | S16: =(M16-M15)/M15 -> 0.18967555
B17: Dec | C17: 0.03413 | D17: 0.66472 | E17: 0.0242 | F17: 902400.18 | G17: 753634.82 | H17: 1069789.9 | I17: 195561.28 | J17: 372781.7 | K17: 0.218 | L17: 0.185 | M17: =SUM(F17:J17) -> 3294167.8 | N17: =(F17-F16)/F16 -> 0.0026556405 | O17: =(G17-G16)/G16 -> -0.050971819 | P17: =(H17-H16)/H16 -> -0.12085699 | Q17: =(I17-I16)/I16 -> -0.14547889 | R17: =(J17-J16)/J16 -> -0.14547889 | S17: =(M17-M16)/M16 -> -0.078832407
A18: 2021 | B18: Jan | C18: 0.25304 | D18: 0.1 | E18: 0.0266 | F18: 856403.2 | G18: 679129.07 | H18: 1099295.6 | I18: 175156.36 | J18: 333885.54 | K18: 0.218 | L18: 0.185 | M18: =SUM(F18:J18) -> 3143869.7 | N18: =(F18-F17)/F17 -> -0.050971819 | O18: =(G18-G17)/G17 -> -0.098861873 | P18: =(H18-H17)/H17 -> 0.027580844 | Q18: =(I18-I17)/I17 -> -0.10434031 | R18: =(J18-J17)/J17 -> -0.10434031 | S18: =(M18-M17)/M17 -> -0.045625515
B19: Feb | C19: 0.14988 | D19: 0.7 | E19: 0.0277 | F19: 793394.9 | G19: 583213.39 | H19: 944888.63 | I19: 148120.95 | J19: 282350.26 | K19: 0.218 | L19: 0.185 | M19: =SUM(F19:J19) -> 2751968.1 | N19: =(F19-F18)/F18 -> -0.073573173 | O19: =(G19-G18)/G18 -> -0.14123335 | P19: =(H19-H18)/H18 -> -0.1404599 | Q19: =(I19-I18)/I18 -> -0.15435015 | R19: =(J19-J18)/J18 -> -0.15435015 | S19: =(M19-M18)/M18 -> -0.12465581
B20: Mar | C20: 0.29724 | D20: 0.22376 | E20: 0.0333 | F20: 807945.93 | G20: 678579.54 | H20: 1012788.4 | I20: 151791.12 | J20: 289346.41 | K20: 0.218 | L20: 0.185 | M20: =SUM(F20:J20) -> 2940451.4 | N20: =(F20-F19)/F19 -> 0.018340211 | O20: =(G20-G19)/G19 -> 0.16351844 | P20: =(H20-H19)/H19 -> 0.071860064 | Q20: =(I20-I19)/I19 -> 0.024778256 | R20: =(J20-J19)/J19 -> 0.024778256 | S20: =(M20-M19)/M19 -> 0.06849035
B21: Apr | C21: -0.0805 | D21: -0.03 | E21: 0.0258 | F21: 868835.62 | G21: 730536.58 | H21: 1127044.1 | I21: 219656.87 | J21: 418713.05 | K21: 0.218 | L21: 0.21 | M21: =SUM(F21:J21) -> 3364786.2 | N21: =(F21-F20)/F20 -> 0.075363572 | O21: =(G21-G20)/G20 -> 0.076567361 | P21: =(H21-H20)/H20 -> 0.11281298 | Q21: =(I21-I20)/I20 -> 0.44709954 | R21: =(J21-J20)/J20 -> 0.44709954 | S21: =(M21-M20)/M20 -> 0.14430941
B22: May | C22: -0.03644 | D22: -0.05 | E22: 0.0324 | F22: 884359.93 | G22: 626677.91 | H22: 1052702.3 | I22: 148028.52 | J22: 282174.08 | K22: 0.218 | L22: 0.21 | M22: =SUM(F22:J22) -> 2993942.8 | N22: =(F22-F21)/F21 -> 0.017867944 | O22: =(G22-G21)/G21 -> -0.14216766 | P22: =(H22-H21)/H21 -> -0.065961686 | Q22: =(I22-I21)/I21 -> -0.32609199 | R22: =(J22-J21)/J21 -> -0.32609199 | S22: =(M22-M21)/M21 -> -0.11021307
B23: Jun | C23: -0.18032 | D23: -0.3 | E23: 0.0328344 | F23: 882023.42 | G23: 814652.18 | H23: 1245132.7 | I23: 217094.53 | J23: 413828.68 | K23: 0.218 | L23: 0.21 | M23: =SUM(F23:J23) -> 3572731.5 | N23: =(F23-F22)/F22 -> -0.0026420381 | O23: =(G23-G22)/G22 -> 0.29995356 | P23: =(H23-H22)/H22 -> 0.18279657 | Q23: =(I23-I22)/I22 -> 0.46657229 | R23: =(J23-J22)/J22 -> 0.46657229 | S23: =(M23-M22)/M22 -> 0.19331991
B24: Jul | C24: 0.31828 | D24: 0.21 | E24: 0.0332688 | F24: 828770.73 | G24: 709689.71 | H24: 1074706.9 | I24: 157859.34 | J24: 300913.72 | K24: 0.218 | L24: 0.21 | M24: =SUM(F24:J24) -> 3071940.4 | N24: =(F24-F23)/F23 -> -0.060375588 | O24: =(G24-G23)/G23 -> -0.12884328 | P24: =(H24-H23)/H23 -> -0.13687361 | Q24: =(I24-I23)/I23 -> -0.27285436 | R24: =(J24-J23)/J23 -> -0.27285436 | S24: =(M24-M23)/M23 -> -0.14017037
B25: Aug | C25: 0.04817 | D25: -0.001 | E25: 0.0337032 | F25: 915338.35 | G25: 778078.86 | H25: 1100990.1 | I25: 178909.95 | J25: 341040.7 | K25: 0.218 | L25: 0.21 | M25: =SUM(F25:J25) -> 3314358 | N25: =(F25-F24)/F24 -> 0.10445303 | O25: =(G25-G24)/G24 -> 0.096364857 | P25: =(H25-H24)/H24 -> 0.024456195 | Q25: =(I25-I24)/I24 -> 0.13335043 | R25: =(J25-J24)/J24 -> 0.13335043 | S25: =(M25-M24)/M24 -> 0.078913507
B26: Sep | C26: -0.09813 | D26: -0.05 | E26: 0.0341376 | F26: 831843.38 | G26: 619786.21 | H26: 1009231.7 | I26: 180038.32 | J26: 343191.6 | K26: 0.218 | L26: 0.21 | M26: =SUM(F26:J26) -> 2984091.2 | N26: =(F26-F25)/F25 -> -0.091217596 | O26: =(G26-G25)/G25 -> -0.20344037 | P26: =(H26-H25)/H25 -> -0.083341743 | Q26: =(I26-I25)/I25 -> 0.0063068918 | R26: =(J26-J25)/J25 -> 0.0063068918 | S26: =(M26-M25)/M25 -> -0.099647287
B27: Oct | C27: 0.21238 | D27: 0.21 | E27: 0.034572 | F27: 908453.31 | G27: 672787.33 | H27: 1110952 | I27: 185893.84 | J27: 354353.48 | K27: 0.218 | L27: 0.21 | M27: =SUM(F27:J27) -> 3232440 | N27: =(F27-F26)/F26 -> 0.092096575 | O27: =(G27-G26)/G26 -> 0.085515168 | P27: =(H27-H26)/H26 -> 0.10078987 | Q27: =(I27-I26)/I26 -> 0.032523751 | R27: =(J27-J26)/J26 -> 0.032523751 | S27: =(M27-M26)/M26 -> 0.08322426
B28: Nov | C28: 0.00387 | D28: 0.002 | E28: 0.0350064 | F28: 875359.16 | G28: 627503.16 | H28: 1059187.4 | I28: 165426.27 | J28: 315337.91 | K28: 0.255 | L28: 0.21 | M28: =SUM(F28:J28) -> 3042813.9 | N28: =(F28-F27)/F27 -> -0.036429113 | O28: =(G28-G27)/G27 -> -0.0673083 | P28: =(H28-H27)/H27 -> -0.046594881 | Q28: =(I28-I27)/I27 -> -0.11010355 | R28: =(J28-J27)/J27 -> -0.11010355 | S28: =(M28-M27)/M27 -> -0.05866347
B29: Dec | C29: 0.02125 | D29: 0.35434 | E29: 0.0354408 | F29: 904506.38 | G29: 669967.41 | H29: 1080636.9 | I29: 195063.81 | J29: 371833.41 | K29: 0.255 | L29: 0.21 | M29: =SUM(F29:J29) -> 3222007.9 | N29: =(F29-F28)/F28 -> 0.033297439 | O29: =(G29-G28)/G28 -> 0.067671773 | P29: =(H29-H28)/H28 -> 0.020250926 | Q29: =(I29-I28)/I28 -> 0.17915862 | R29: =(J29-J28)/J28 -> 0.17915862 | S29: =(M29-M28)/M28 -> 0.058890897
A30: 2022 | B30: Jan | C30: 0.21495 | D30: -0.7348 | E30: 0.0358752 | F30: 876133.72 | G30: 831165.22 | H30: 1223187.5 | I30: 207803.43 | J30: 396117.86 | K30: 0.255 | L30: 0.21 | M30: =SUM(F30:J30) -> 3534407.7 | N30: =(F30-F29)/F29 -> -0.031368115 | O30: =(G30-G29)/G29 -> 0.24060544 | P30: =(H30-H29)/H29 -> 0.13191347 | Q30: =(I30-I29)/I29 -> 0.065310038 | R30: =(J30-J29)/J29 -> 0.065310038 | S30: =(M30-M29)/M29 -> 0.096958108
B31: Feb | C31: 0.18989 | D31: 0.5 | E31: 0.0363096 | F31: 790009.87 | G31: 629596.97 | H31: 959086.54 | I31: 152202.38 | J31: 290130.35 | K31: 0.255 | L31: 0.21 | M31: =SUM(F31:J31) -> 2821026.1 | N31: =(F31-F30)/F30 -> -0.098299892 | O31: =(G31-G30)/G30 -> -0.24251285 | P31: =(H31-H30)/H30 -> -0.21591205 | Q31: =(I31-I30)/I30 -> -0.26756559 | R31: =(J31-J30)/J30 -> -0.26756559 | S31: =(M31-M30)/M30 -> -0.20183907
B32: Mar | C32: -0.051856 | D32: -0.04076 | E32: 0.036744 | F32: 823031.33 | G32: 755853.09 | H32: 1124699.3 | I32: 199665.7 | J32: 380605.61 | K32: 0.255 | L32: 0.21 | M32: =SUM(F32:J32) -> 3283855.1 | N32: =(F32-F31)/F31 -> 0.041798787 | O32: =(G32-G31)/G31 -> 0.20053483 | P32: =(H32-H31)/H31 -> 0.17267765 | Q32: =(I32-I31)/I31 -> 0.31184349 | R32: =(J32-J31)/J31 -> 0.31184349 | S32: =(M32-M31)/M31 -> 0.16406405
B33: Apr | C33: 0.070768 | D33: 0.15474 | E33: 0.0371784 | F33: 893561.57 | G33: 724194.05 | H33: 1129107.3 | I33: 208458.24 | J33: 397366.06 | K33: 0.255 | L33: 0.21 | M33: =SUM(F33:J33) -> 3352687.2 | N33: =(F33-F32)/F32 -> 0.085695698 | O33: =(G33-G32)/G32 -> -0.041885178 | P33: =(H33-H32)/H32 -> 0.0039192191 | Q33: =(I33-I32)/I32 -> 0.044036264 | R33: =(J33-J32)/J32 -> 0.044036264 | S33: =(M33-M32)/M32 -> 0.020960769
B34: May | C34: 0.120628 | D34: 0.50522 | E34: 0.0376128 | F34: 904808.01 | G34: 769531.95 | H34: 1085163.8 | I34: 559854.55 | J34: 345556.61 | K34: 0.255 | L34: 0.21 | M34: =SUM(F34:J34) -> 3664915 | N34: =(F34-F33)/F33 -> 0.01258608 | O34: =(G34-G33)/G33 -> 0.062604623 | P34: =(H34-H33)/H33 -> -0.038918754 | Q34: =(I34-I33)/I33 -> 1.6856917 | R34: =(J34-J33)/J33 -> -0.13038217 | S34: =(M34-M33)/M33 -> 0.093127609
B35: Jun | C35: 0.093617 | D35: 0.86078 | E35: 0.0380472 | F35: 859555.33 | G35: 645659.74 | H35: 1084469.5 | I35: 520462.47 | J35: 264401.8 | K35: 0.255 | L35: 0.21 | M35: =SUM(F35:J35) -> 3374548.8 | N35: =(F35-F34)/F34 -> -0.050013565 | O35: =(G35-G34)/G34 -> -0.16097084 | P35: =(H35-H34)/H34 -> -0.00063988021 | Q35: =(I35-I34)/I34 -> -0.070361271 | R35: =(J35-J34)/J34 -> -0.23485244 | S35: =(M35-M34)/M34 -> -0.079228617
B36: Jul | C36: 0.118987 | D36: 0.4216 | E36: 0.0384816 | F36: 914285.79 | G36: 812001.7 | H36: 1229824.1 | I36: 572511.34 | J36: 427921.78 | K36: 0.255 | L36: 0.21 | M36: =SUM(F36:J36) -> 3956544.7 | N36: =(F36-F35)/F35 -> 0.063672986 | O36: =(G36-G35)/G35 -> 0.25763098 | P36: =(H36-H35)/H35 -> 0.13403295 | Q36: =(I36-I35)/I35 -> 0.10000505 | R36: =(J36-J35)/J35 -> 0.61845258 | S36: =(M36-M35)/M35 -> 0.17246629
B37: Aug | C37: -0.12 | D37: -0.38572 | E37: 0.0358752 | F37: 890423.77 | G37: 739180.44 | H37: 1050960.9 | I37: 535242.45 | J37: 341535.28 | K37: 0.255 | L37: 0.21 | M37: =SUM(F37:J37) -> 3557342.8 | N37: =(F37-F36)/F36 -> -0.026099084 | O37: =(G37-G36)/G36 -> -0.089681166 | P37: =(H37-H36)/H36 -> -0.14543807 | Q37: =(I37-I36)/I36 -> -0.065097222 | R37: =(J37-J36)/J36 -> -0.20187449 | S37: =(M37-M36)/M36 -> -0.1008966
B38: Sep | C38: 0.089187 | D38: 0.14072 | E38: 0.034572 | F38: 836435.04 | G38: 656897.68 | H38: 1063273.5 | I38: 439978.92 | J38: 289363.58 | K38: 0.255 | L38: 0.21 | M38: =SUM(F38:J38) -> 3285948.7 | N38: =(F38-F37)/F37 -> -0.060632625 | O38: =(G38-G37)/G37 -> -0.1113162 | P38: =(H38-H37)/H37 -> 0.011715621 | Q38: =(I38-I37)/I37 -> -0.17798202 | R38: =(J38-J37)/J37 -> -0.15275641 | S38: =(M38-M37)/M37 -> -0.07629123
B39: Oct | C39: 0.090925 | D39: 0.3759 | E39: 0.0350064 | F39: 860546.64 | G39: 643303.14 | H39: 979641.51 | I39: 447498.45 | J39: 266878.71 | K39: 0.255 | L39: 0.222 | M39: =SUM(F39:J39) -> 3197868.5 | N39: =(F39-F38)/F38 -> 0.028826635 | O39: =(G39-G38)/G38 -> -0.020695069 | P39: =(H39-H38)/H38 -> -0.078655222 | Q39: =(I39-I38)/I38 -> 0.017090679 | R39: =(J39-J38)/J38 -> -0.077704559 | S39: =(M39-M38)/M38 -> -0.026805129
B40: Nov | C40: 0.110295 | D40: 0.12 | E40: 0.0354408 | F40: 820832.5 | G40: 687936.01 | H40: 1060609.1 | I40: 546865.23 | J40: 347597.36 | K40: 0.255 | L40: 0.222 | M40: =SUM(F40:J40) -> 3463840.2 | N40: =(F40-F39)/F39 -> -0.046149906 | O40: =(G40-G39)/G39 -> 0.06938078 | P40: =(H40-H39)/H39 -> 0.082650258 | Q40: =(I40-I39)/I39 -> 0.22204943 | R40: =(J40-J39)/J39 -> 0.30245445 | S40: =(M40-M39)/M39 -> 0.083171582
B41: Dec | C41: 0.107789 | D41: 0.108 | E41: 0.0358752 | F41: 896170.29 | G41: 660663.67 | H41: 1090435.9 | I41: 508751.89 | J41: 306494.35 | K41: 0.255 | L41: 0.222 | M41: =SUM(F41:J41) -> 3462516.1 | N41: =(F41-F40)/F40 -> 0.091782174 | O41: =(G41-G40)/G40 -> -0.039643715 | P41: =(H41-H40)/H40 -> 0.028122294 | Q41: =(I41-I40)/I40 -> -0.069694201 | R41: =(J41-J40)/J40 -> -0.11824893 | S41: =(M41-M40)/M40 -> -0.00038227477
A42: 2023 | B42: Jan | C42: -0.073594 | D42: -0.02 | E42: 0.0322 | F42: 896624.47 | G42: 689376.67 | H42: 1103978.1 | I42: 514730.37 | J42: 355944.57 | K42: 0.255 | L42: 0.222 | M42: =SUM(F42:J42) -> 3560654.2 | N42: =(F42-F41)/F41 -> 0.00050680348 | O42: =(G42-G41)/G41 -> 0.043460843 | P42: =(H42-H41)/H41 -> 0.012419108 | Q42: =(I42-I41)/I41 -> 0.011751263 | R42: =(J42-J41)/J41 -> 0.16134139 | S42: =(M42-M41)/M41 -> 0.028343009
B43: Feb | C43: 0.042812 | D43: 0.96278 | E43: 0.031423 | F43: 850417.89 | G43: 609030.7 | H43: 1071642.2 | I43: 504410.75 | J43: 319129.23 | K43: 0.255 | L43: 0.222 | M43: =SUM(F43:J43) -> 3354630.8 | N43: =(F43-F42)/F42 -> -0.051533926 | O43: =(G43-G42)/G42 -> -0.11654872 | P43: =(H43-H42)/H42 -> -0.029290371 | Q43: =(I43-I42)/I42 -> -0.0200486 | R43: =(J43-J42)/J42 -> -0.10342998 | S43: =(M43-M42)/M42 -> -0.057861121
B44: Mar | C44: 0.096135 | D44: 0.1 | E44: 0.030646 | F44: 887980.23 | G44: 710286.99 | H44: 1095970 | I44: 500691.08 | J44: 368752.21 | K44: 0.22 | L44: 0.222 | M44: =SUM(F44:J44) -> 3563680.5 | N44: =(F44-F43)/F43 -> 0.044169273 | O44: =(G44-G43)/G43 -> 0.1662581 | P44: =(H44-H43)/H43 -> 0.022701424 | Q44: =(I44-I43)/I43 -> -0.0073742762 | R44: =(J44-J43)/J43 -> 0.15549493 | S44: =(M44-M43)/M43 -> 0.062316767
B45: Apr | C45: -0.033429 | D45: -0.07 | E45: 0.029869 | F45: 826233.98 | G45: 623115.5 | H45: 1058683.1 | I45: 446733.23 | J45: 302079.43 | K45: 0.22 | L45: 0.222 | M45: =SUM(F45:J45) -> 3256845.3 | N45: =(F45-F44)/F44 -> -0.069535618 | O45: =(G45-G44)/G44 -> -0.12272714 | P45: =(H45-H44)/H44 -> -0.034021811 | Q45: =(I45-I44)/I44 -> -0.10776676 | R45: =(J45-J44)/J44 -> -0.18080645 | S45: =(M45-M44)/M44 -> -0.086100664
B46: May | C46: 0.073865 | D46: 0.006 | E46: 0.029092 | F46: 842428.05 | G46: 724403.96 | H46: 1066595 | I46: 489618.43 | J46: 302802.22 | K46: 0.22 | L46: 0.222 | M46: =SUM(F46:J46) -> 3425847.6 | N46: =(F46-F45)/F45 -> 0.019599871 | O46: =(G46-G45)/G45 -> 0.16255166 | P46: =(H46-H45)/H45 -> 0.0074732782 | Q46: =(I46-I45)/I45 -> 0.09599733 | R46: =(J46-J45)/J45 -> 0.0023927055 | S46: =(M46-M45)/M45 -> 0.05189143
B47: Jun | C47: 0.066336 | D47: 0.04 | E47: 0.028315 | F47: 859009.69 | G47: 672707.09 | H47: 1051871.9 | I47: 477588.62 | J47: 330297.03 | K47: 0.22 | L47: 0.222 | M47: =SUM(F47:J47) -> 3391474.3 | N47: =(F47-F46)/F46 -> 0.019683149 | O47: =(G47-G46)/G46 -> -0.071364698 | P47: =(H47-H46)/H46 -> -0.0138038 | Q47: =(I47-I46)/I46 -> -0.024569764 | R47: =(J47-J46)/J46 -> 0.090801232 | S47: =(M47-M46)/M46 -> -0.010033514
B48: Jul | C48: 0.05476 | D48: 0.32594 | E48: 0.027538 | F48: 886466.14 | G48: 686036.9 | H48: 1038942.3 | I48: 528922.85 | J48: 361814.18 | K48: 0.22 | L48: 0.222 | M48: =SUM(F48:J48) -> 3502182.3 | N48: =(F48-F47)/F47 -> 0.031962907 | O48: =(G48-G47)/G47 -> 0.019815177 | P48: =(H48-H47)/H47 -> -0.012292022 | Q48: =(I48-I47)/I47 -> 0.10748629 | R48: =(J48-J47)/J47 -> 0.095420614 | S48: =(M48-M47)/M47 -> 0.032643031
B49: Aug | C49: 0.095707 | D49: 0.121 | E49: 0.026761 | F49: 830667.15 | G49: 596483.55 | H49: 1042715.4 | I49: 467934.05 | J49: 308302.08 | K49: 0.22 | L49: 0.222 | M49: =SUM(F49:J49) -> 3246102.2 | N49: =(F49-F48)/F48 -> -0.062945421 | O49: =(G49-G48)/G48 -> -0.13053722 | P49: =(H49-H48)/H48 -> 0.0036317331 | Q49: =(I49-I48)/I48 -> -0.11530756 | R49: =(J49-J48)/J48 -> -0.14789941 | S49: =(M49-M48)/M48 -> -0.073120145
B50: Sep | C50: 0.059998 | D50: 0.07 | E50: 0.026986 | F50: 859689.42 | G50: 666920.59 | H50: 1103085.6 | I50: 544670.49 | J50: 306780.84 | K50: 0.22 | L50: 0.222 | M50: =SUM(F50:J50) -> 3481146.9 | N50: =(F50-F49)/F49 -> 0.034938503 | O50: =(G50-G49)/G49 -> 0.11808715 | P50: =(H50-H49)/H49 -> 0.057897036 | Q50: =(I50-I49)/I49 -> 0.16398987 | R50: =(J50-J49)/J49 -> -0.0049342276 | S50: =(M50-M49)/M49 -> 0.072408272
B51: Oct | C51: 0.087203 | D51: 0.11502 | E51: 0.027211 | F51: 854306.59 | G51: 639299.19 | H51: 1055045.3 | I51: 525048.17 | J51: 343913.29 | K51: 0.22 | L51: 0.222 | M51: =SUM(F51:J51) -> 3417612.6 | N51: =(F51-F50)/F50 -> -0.0062613672 | O51: =(G51-G50)/G50 -> -0.04141633 | P51: =(H51-H50)/H50 -> -0.043550772 | Q51: =(I51-I50)/I50 -> -0.036026037 | R51: =(J51-J50)/J50 -> 0.12103899 | S51: =(M51-M50)/M50 -> -0.018250979
B52: Nov | C52: 0.046028 | D52: 0.59134 | E52: 0.027436 | F52: 835013.82 | G52: 733227.3 | H52: 1077147.9 | I52: 531819.07 | J52: 340099.02 | K52: 0.22 | L52: 0.222 | M52: =SUM(F52:J52) -> 3517307.1 | N52: =(F52-F51)/F51 -> -0.02258296 | O52: =(G52-G51)/G51 -> 0.14692356 | P52: =(H52-H51)/H51 -> 0.020949406 | Q52: =(I52-I51)/I51 -> 0.012895773 | R52: =(J52-J51)/J51 -> -0.011090781 | S52: =(M52-M51)/M51 -> 0.029170816
B53: Dec | C53: 0.089555 | D53: 0.51982 | E53: 0.028 | F53: 805632.65 | G53: 683728.43 | H53: 1102485.3 | I53: 521465.24 | J53: 363034.52 | K53: 0.22 | L53: 0.222 | M53: =SUM(F53:J53) -> 3476346.1 | N53: =(F53-F52)/F52 -> -0.035186447 | O53: =(G53-G52)/G52 -> -0.067508227 | P53: =(H53-H52)/H52 -> 0.023522677 | Q53: =(I53-I52)/I52 -> -0.019468716 | R53: =(J53-J52)/J52 -> 0.067437707 | S53: =(M53-M52)/M52 -> -0.011645551
A54: 2024 | B54: Jan | C54: 0.077962 | D54: 0.08 | E54: 0.03208 | F54: 865932.44 | G54: 743262.85 | H54: 1126627.5 | I54: 515360.97 | J54: 396295.21 | K54: 0.22 | L54: 0.222 | M54: =SUM(F54:J54) -> 3647479 | N54: =(F54-F53)/F53 -> 0.074847747 | O54: =(G54-G53)/G53 -> 0.087073196 | P54: =(H54-H53)/H53 -> 0.02189798 | Q54: =(I54-I53)/I53 -> -0.011705991 | R54: =(J54-J53)/J53 -> 0.09161855 | S54: =(M54-M53)/M53 -> 0.04922779
B55: Feb | C55: -0.06205 | D55: -0.0888 | E55: 0.03306 | F55: 911323.45 | G55: 786192.32 | H55: 1139066.5 | I55: 588244.37 | J55: 357800.69 | K55: 0.22 | L55: 0.222 | M55: =SUM(F55:J55) -> 3782627.4 | N55: =(F55-F54)/F54 -> 0.052418652 | O55: =(G55-G54)/G54 -> 0.05775814 | P55: =(H55-H54)/H54 -> 0.011040943 | Q55: =(I55-I54)/I54 -> 0.14142203 | R55: =(J55-J54)/J54 -> -0.097135968 | S55: =(M55-M54)/M54 -> 0.03705255
B56: Mar | C56: 0.043067 | D56: 0.22 | E56: 0.03404 | F56: 780375.06 | G56: 604453.19 | H56: 984045.08 | I56: 420054.46 | J56: 263891.24 | K56: 0.22 | L56: 0.222 | M56: =SUM(F56:J56) -> 3052819 | N56: =(F56-F55)/F55 -> -0.14369035 | O56: =(G56-G55)/G55 -> -0.23116371 | P56: =(H56-H55)/H55 -> -0.13609517 | Q56: =(I56-I55)/I55 -> -0.28591842 | R56: =(J56-J55)/J55 -> -0.26246302 | S56: =(M56-M55)/M55 -> -0.19293688
B57: Apr | C57: 0.088526 | D57: 0.3 | E57: 0.03502 | F57: 883707.04 | G57: 719248.45 | H57: 1047522.8 | I57: 518282.9 | J57: 296786.29 | K57: 0.22 | L57: 0.222 | M57: =SUM(F57:J57) -> 3465547.5 | N57: =(F57-F56)/F56 -> 0.13241323 | O57: =(G57-G56)/G56 -> 0.18991588 | P57: =(H57-H56)/H56 -> 0.064506942 | Q57: =(I57-I56)/I56 -> 0.2338469 | R57: =(J57-J56)/J56 -> 0.12465381 | S57: =(M57-M56)/M56 -> 0.13519585
B58: May | C58: 0.046368 | D58: 0.48178 | E58: 0.0302 | F58: 855102.86 | G58: 717856.25 | H58: 1037055.9 | I58: 469587.8 | J58: 323389.75 | K58: 0.22 | L58: 0.222 | M58: =SUM(F58:J58) -> 3402992.5 | N58: =(F58-F57)/F57 -> -0.032368401 | O58: =(G58-G57)/G57 -> -0.0019356286 | P58: =(H58-H57)/H57 -> -0.0099920839 | Q58: =(I58-I57)/I57 -> -0.093954679 | R58: =(J58-J57)/J57 -> 0.089638424 | S58: =(M58-M57)/M57 -> -0.018050529
B59: Jun | C59: -0.0334 | D59: -0.05 | E59: 0.031 | F59: 933400.57 | G59: 769838.92 | H59: 1137059.7 | I59: 575918.52 | J59: 392947.97 | K59: 0.22 | L59: 0.222 | M59: =SUM(F59:J59) -> 3809165.6 | N59: =(F59-F58)/F58 -> 0.091565252 | O59: =(G59-G58)/G58 -> 0.072413755 | P59: =(H59-H58)/H58 -> 0.096430461 | Q59: =(I59-I58)/I58 -> 0.22643418 | R59: =(J59-J58)/J58 -> 0.21509099 | S59: =(M59-M58)/M58 -> 0.11935762
B60: Jul | C60: 0.061269 | D60: 0.005 | E60: 0.033811 | F60: 801280.82 | G60: 649765.13 | H60: 1015422.6 | I60: 466078.51 | J60: 312520.17 | K60: 0.22 | L60: 0.222 | M60: =SUM(F60:J60) -> 3245067.2 | N60: =(F60-F59)/F59 -> -0.14154668 | O60: =(G60-G59)/G59 -> -0.15597261 | P60: =(H60-H59)/H59 -> -0.10697509 | Q60: =(I60-I59)/I59 -> -0.19072145 | R60: =(J60-J59)/J59 -> -0.20467798 | S60: =(M60-M59)/M59 -> -0.14808975
B61: Aug | C61: 0.081169 | D61: 0.48 | E61: 0.033408 | F61: 807675.41 | G61: 632261.79 | H61: 928081.64 | I61: 390409.4 | J61: 282987.18 | K61: 0.22 | L61: 0.222 | M61: =SUM(F61:J61) -> 3041415.4 | N61: =(F61-F60)/F60 -> 0.0079804635 | O61: =(G61-G60)/G60 -> -0.026937959 | P61: =(H61-H60)/H60 -> -0.086014395 | Q61: =(I61-I60)/I60 -> -0.16235271 | R61: =(J61-J60)/J60 -> -0.094499489 | S61: =(M61-M60)/M60 -> -0.06275735
B62: Sep | C62: 0.082464 | D62: 0.004 | E62: 0.033005 | F62: 849531.57 | G62: 708250.49 | H62: 1137229.7 | I62: 592499.16 | J62: 351338.63 | K62: 0.22 | L62: 0.222 | M62: =SUM(F62:J62) -> 3638849.6 | N62: =(F62-F61)/F61 -> 0.051822999 | O62: =(G62-G61)/G61 -> 0.1201855 | P62: =(H62-H61)/H61 -> 0.22535528 | Q62: =(I62-I61)/I61 -> 0.51763547 | R62: =(J62-J61)/J61 -> 0.24153551 | S62: =(M62-M61)/M61 -> 0.19643294
B63: Oct | C63: 0.05708 | D63: 0.08468 | E63: 0.0295 | F63: 890046.43 | G63: 729826.28 | H63: 1101356.7 | I63: 494578.66 | J63: 372554.21 | K63: 0.22 | L63: 0.222 | M63: =SUM(F63:J63) -> 3588362.3 | N63: =(F63-F62)/F62 -> 0.047690825 | O63: =(G63-G62)/G62 -> 0.030463509 | P63: =(H63-H62)/H62 -> -0.031544197 | Q63: =(I63-I62)/I62 -> -0.1652669 | R63: =(J63-J62)/J62 -> 0.06038498 | S63: =(M63-M62)/M62 -> -0.013874513
B64: Nov | C64: 0.094651 | D64: 0.12 | E64: 0.0299 | F64: 791303.91 | G64: 648425.78 | H64: 1038367.9 | I64: 487536.11 | J64: 284127.93 | K64: 0.22 | L64: 0.222 | M64: =SUM(F64:J64) -> 3249761.6 | N64: =(F64-F63)/F63 -> -0.11094086 | O64: =(G64-G63)/G63 -> -0.11153408 | P64: =(H64-H63)/H63 -> -0.057192059 | Q64: =(I64-I63)/I63 -> -0.014239484 | R64: =(J64-J63)/J63 -> -0.23735143 | S64: =(M64-M63)/M63 -> -0.09436079
B65: Dec | C65: 0.052555 | D65: 0.06 | E65: 0.0303 | F65: 833298.29 | G65: 647046.37 | H65: 1045080.1 | I65: 485741.23 | J65: 344663.27 | K65: 0.22 | L65: 0.222 | M65: =SUM(F65:J65) -> 3355829.3 | N65: =(F65-F64)/F64 -> 0.053069842 | O65: =(G65-G64)/G64 -> -0.0021273219 | P65: =(H65-H64)/H64 -> 0.0064642139 | Q65: =(I65-I64)/I64 -> -0.0036815308 | R65: =(J65-J64)/J64 -> 0.21305663 | S65: =(M65-M64)/M64 -> 0.032638596
A66: Calculations: | B66: Average | C66: =AVERAGE(C6:C65) -> 0.068484283 | D66: =AVERAGE(D6:D65) -> 0.15673933 | E66: =AVERAGE(E6:E65) -> 0.031738043 | G66: <-- historic rf rate (use in MRP calc) | I66: current rf rate | J66: semi annual coupon
A67: Calculations: | B67: Standard Deviation | C67: =_xlfn.STDEV.P(C6:C65) -> 0.10563537 | D67: =_xlfn.STDEV.P(D6:D65) -> 0.29798157 | E67: =_xlfn.STDEV.P(E6:E65) -> 0.0038267959 | F67: P | G67: Q | H67: R | I67: =RATE(10*2,J67,-955.43,1000)*2 -> 0.036356131 | J67: =(3.1%*1000)/2 -> 15.5
A68: Calculations: | B68: Beta | C68: 1 | D68: =SLOPE(D6:D65,C6:C65) -> 1.0400724 | E68: 0 | F68: =SLOPE(N7:N65,C7:C65) -> -0.1692684 | G68: =SLOPE(O7:O65,C7:C65) -> 0.084731109 | H68: =SLOPE(P7:P65,C7:C65) -> -0.20260674 | I68: S | J68: T
A69: Calculations: | B69: Avg Tax Rate | C69: Avg D/E Ratio | D69: MRP | E69: CAPM r | F69: liquidity risk prem | I69: =SLOPE(Q7:Q65,C7:C65) -> -0.6703044 | J69: =SLOPE(R7:R65,C7:C65) -> -0.7272268
A70: Calculations | B70: =AVERAGE(K6:K65) -> 0.2286 | C70: =AVERAGE(L6:L65) -> 0.20915 | D70: =C66-E66 -> 0.03674624 | E70: =I67+B81*D70 -> 0.070055062 | F70: 0.012 | I70: All: | J70: =SLOPE(S7:S65,C7:C65) -> -0.19785887
A71: Show all work, formulas, and calculations using the above data. The table can be modified for calculations
A72: Beta Calculations
A74: Stock b | F74: CAPM Summary | G74: MRP (Rm-Rf) | I74: =D70 -> 0.03674624
G75: Current Rf | I75: =I67 -> 0.036356131
A77: bL = | B77: =D68 -> 1.0400724 | G77: Project Levered Beta (Bl) | I77: =B81 -> 0.91707152
A78: bU = | B78: =B77/(1+(C70*(1-B70))) -> 0.8955809 | G78: Project Cost of Capital ( r ) | I78: =E70+F70 -> 0.082055062
A81: Project b | B81: =D86*B78 -> 0.91707152
A83: Project | D83: Relative Sensitivity (Risk Scaler)
A84: P | B84: =F68 -> -0.1692684 | C84: =$J$70 -> -0.19785887 | D84: =B84/C84 -> 0.85550073
A85: Q | B85: =G68 -> 0.084731109 | C85: =$J$70 -> -0.19785887 | D85: =B85/C85 -> -0.42824014
A86: R | B86: =H68 -> -0.20260674 | C86: =$J$70 -> -0.19785887 | D86: =B86/C86 -> 1.0239963
A87: S | B87: =I69 -> -0.6703044 | C87: =$J$70 -> -0.19785887 | D87: =B87/C87 -> 3.3877906
A88: T | B88: =J69 -> -0.7272268 | C88: =$J$70 -> -0.19785887 | D88: =B88/C88 -> 3.6754825

Sheet Cash Flow Assumptions
A1: Project Cash Flows
A2: Unit Assumptions | B2: 0 | C2: 1 | D2: 2 | E2: 3 | F2: 4 | G2: 5 | H2: 6 | I2: 7 | J2: 8 | K2: 9 | L2: 10
A3: Unit quantity | C3: 100000 | D3: =C3*1.1 -> 110000 | E3: =D3*1.1 -> 121000 | F3: =E3*1.1 -> 133100 | G3: =F3*1.1 -> 146410 | H3: =G3*1.1 -> 161051 | I3: =H3*1.1 -> 177156.1 | J3: =I3*1.1 -> 194871.71 | K3: =J3*1.1 -> 214358.88 | L3: =K3*1.1 -> 235794.77
A4: Unit Selling Price (for retail) | C4: 75 | D4: 75 | E4: 75 | F4: 75 | G4: 75 | H4: 75 | I4: 75 | J4: 75 | K4: 75 | L4: 75
A5: Net Unit Selling Price (revenue) (net channel costs and incentives) | C5: 35 | D5: 35 | E5: 35 | F5: 35 | G5: 35 | H5: 35 | I5: 35 | J5: 35 | K5: 35 | L5: 35
A6: Material Unit Variable Cost | C6: 6.19 | D6: =C6*1.015 -> 6.28285 | E6: =D6*1.015 -> 6.3770927 | F6: =E6*1.015 -> 6.4727491 | G6: =F6*1.015 -> 6.5698404 | H6: =G6*1.015 -> 6.668388 | I6: =H6*1.015 -> 6.7684138 | J6: =I6*1.015 -> 6.86994 | K6: =J6*1.015 -> 6.9729891 | L6: =K6*1.015 -> 7.0775839
A7: Overhead Unit Variable Cost | C7: =4.08 -> 4.08 | D7: =4.08 -> 4.08 | E7: =4.08 -> 4.08 | F7: =1.12 -> 1.12 | G7: =1.12 -> 1.12 | H7: =1.12 -> 1.12 | I7: =1.12 -> 1.12 | J7: =1.12 -> 1.12 | K7: =1.12 -> 1.12 | L7: =1.12 -> 1.12
A8: Unit Fixed Cost | C8: =(70000*4)/C3 -> 2.8 | D8: =(70000*4)/D3 -> 2.5454545 | E8: =(70000*4)/E3 -> 2.3140496 | F8: =((70000*4)+50000)/F3 -> 2.4793388 | G8: =((70000*4)+50000)/G3 -> 2.2539444 | H8: =((70000*4)+50000)/H3 -> 2.0490404 | I8: =((70000*4)+50000)/I3 -> 1.862764 | J8: =((70000*4)+50000)/J3 -> 1.6934218 | K8: =((70000*4)+50000)/K3 -> 1.5394744 | L8: =((70000*4)+50000)/L3 -> 1.3995221
M9: Depreciable Assets
A10: Project Assumptions
B11: 0 | C11: 1 | D11: 2 | E11: 3 | F11: 4 | G11: 5 | H11: 6 | I11: 7 | J11: 8 | K11: 9 | L11: 10 | M11: Deprec Asset Class | N11: ED | O11: Recovery Period (SL) | P11: Annual Depr | R11: MV5 | S11: BV5 | T11: NSV5
A12: Units Sold | C12: =C3 -> 100000 | D12: =D3 -> 110000 | E12: =E3 -> 121000 | F12: =F3 -> 133100 | G12: =G3 -> 146410 | H12: =H3 -> 161051 | I12: =I3 -> 177156.1 | J12: =J3 -> 194871.71 | ... L12: =L3 -> 235794.77 | M12: A | N12: 150000 | O12: 5 | P12: =N12/O12 -> 30000 | R12: =0 -> 0 | S12: =N12-(O12*P12)+U12 -> 0 | T12: =S12-(S12*'Company Data & Beta '!$B$70) -> 0
A13: Revenue | C13: =C12*C5 -> 3500000 | D13: =D12*D5 -> 3850000 | E13: =E12*E5 -> 4235000 | F13: =F12*F5 -> 4658500 | G13: =G12*G5 -> 5124350 | H13: =H12*H5 -> 5636785 | I13: =I12*I5 -> 6200463.5 | J13: =J12*J5 -> 6820509.9 | ... L13: =L12*L5 -> 8252816.9 | M13: B | N13: 110000 | O13: 5 | P13: =N13/O13 -> 22000 | R13: =0 -> 0 | S13: =N13-(O13*P13)+U13 -> 0 | T13: =S13-(S13*'Company Data & Beta '!$B$70) -> 0
A14: Synergies or Erosion impacts | C14: =C12*8*0.55 -> 440000 | D14: =D12*8*0.55 -> 484000 | E14: =E12*8*0.55 -> 532400 | F14: =F12*8*0.55 -> 585640 | G14: =G12*8*0.55 -> 644204 | H14: =H12*8*0.55 -> 708624.4 | I14: =I12*8*0.55 -> 779486.84 | J14: =J12*8*0.55 -> 857435.52 | ... L14: =L12*8*0.55 -> 1037497 | M14: C | N14: 40000 | O14: 5 | P14: =N14/O14 -> 8000 | R14: =0 -> 0 | S14: =N14-(O14*P14)+U14 -> 0 | T14: =S14-(S14*'Company Data & Beta '!$B$70) -> 0
A15: Variable Expenses | C15: =(C12*C7)+(C12*C6) -> 1027000 | D15: =(D12*D7)+(D12*D6) -> 1139913.5 | E15: =(E12*E7)+(E12*E6) -> 1265308.2 | F15: =(F12*F7)+(F12*F6) -> 1010594.9 | G15: =(G12*G7)+(G12*G6) -> 1125869.5 | H15: =(H12*H7)+(H12*H6) -> 1254327.7 | I15: =(I12*I7)+(I12*I6) -> 1397480.6 | J15: =(J12*J7)+(J12*J6) -> 1557013.3 | ... L15: =(L12*L7)+(L12*L6) -> 1932947.4 | M15: D | N15: =100000-U15 -> 100000 | O15: 5 | P15: =(70000-30000)/5 -> 8000 | R15: =0 -> 0 | S15: 30000 | T15: =S15-(S15*'Company Data & Beta '!$B$70) -> 23142
A16: Fixed Expenses | C16: =C8*C3 -> 280000 | D16: =D8*D3 -> 280000 | E16: =E8*E3 -> 280000 | F16: =F8*F3 -> 330000 | G16: =G8*G3 -> 330000 | H16: =H8*H3 -> 330000 | I16: =I8*I3 -> 330000 | J16: =J8*J3 -> 330000 | ... L16: =L8*L3 -> 330000 | M16: E | N16: =750000 -> 750000 | O16: 5 | P16: =N16/O16 -> 150000 | R16: =0 -> 0 | S16: =N16-(P16*2) -> 450000 | T16: =0 -> 0
A17: Commission Expenses | C17: =(0.01*C13) -> 35000 | D17: =(0.01*D13) -> 38500 | E17: =(0.01*E13) -> 42350 | F17: =(0.01*F13) -> 46585 | G17: =(0.01*G13) -> 51243.5 | H17: =(0.5%*H13) -> 28183.925 | I17: =(0.5%*I13) -> 31002.318 | J17: =(0.5%*J13) -> 34102.549 | K17: =(0.5%*K13) -> 37512.804 | L17: =0.5%*L13 -> 41264.085 | M17: totals | N17: =SUM(N12:N16) -> 1150000 | P17: =SUM(P12:P16) -> 218000 | R17: =SUM(R12:R15) -> 0 | S17: =SUM(S12:S16) -> 480000 | T17: =SUM(T12:T15) -> 23142
A18: Campaign Expenses | C18: =80000 -> 80000 | D18: =(13%*D13) -> 500500 | E18: =(13%*E13) -> 550550 | F18: =(13%*F13) -> 605605 | G18: =(13%*G13) -> 666165.5 | H18: =(13%*H13) -> 732782.05 | I18: =(13%*I13) -> 806060.26 | J18: =(13%*J13) -> 886666.28 | K18: =(13%*K13) -> 975332.91 | L18: =13%*L13 -> 1072866.2
A19: Depreciation Expense | C19: =SUM($P$12:$P$15) -> 68000 | D19: =SUM($P$12:$P$15) -> 68000 | E19: =SUM($P$12:$P$15) -> 68000 | F19: =SUM($P$12:$P$16) -> 218000 | G19: =SUM($P$12:$P$16) -> 218000 | H19: =SUM($P$12:$P$16) -> 218000 | I19: =SUM($P$12:$P$16) -> 218000 | J19: =SUM($P$12:$P$16) -> 218000 | K19: =SUM($P$12:$P$16) -> 218000 | L19: =SUM($P$12:$P$16) -> 218000
A20: Net working Capital | B20: 150000 | C20: =0.5*C12 -> 50000 | D20: =0.5*D12 -> 55000 | E20: =0.5*E12 -> 60500 | F20: =0.5*F12 -> 66550 | G20: =0.5*G12 -> 73205 | H20: =0.5*H12 -> 80525.5 | I20: =0.5*I12 -> 88578.05 | J20: =0.5*J12 -> 97435.855 | K20: =0.5*K12 -> 107179.44 | L20: 0 | M20: Assume any loss on salvage of machinery result in an immediate tax deduction which adds to total cash flows in the same year of disposal
A21: Capital Equipment | B21: =N12+N13+N14+N15 -> 400000 | F21: =N16 -> 750000 | G21: =N12+N13+N14+N15 -> 400000 | K21: =F21 -> 750000
A22: Net Salvage Value\ | G22: =L22 -> 23142 | L22: =T15 -> 23142
A23: Taxes | C23: =(C13-SUM(C14:C19))*'Company Data & Beta '!$B$70 -> 358902 | D23: =(D13-SUM(D14:D19))*'Company Data & Beta '!$B$70 -> 306115.17 | E23: =(E13-SUM(E14:E19))*'Company Data & Beta '!$B$70 -> 342075.16 | F23: =(F13-SUM(F14:F19))*'Company Data & Beta '!$B$70 -> 425670.37 | G23: =(G13-SUM(G14:G19))*'Company Data & Beta '!$B$70 -> 477515.1 | H23: =(H13-SUM(H14:H19))*'Company Data & Beta '!$B$70 -> 540608.59 | I23: =(I13-SUM(I14:I19))*'Company Data & Beta '!$B$70 -> 603145.89 | J23: =(J13-SUM(J14:J19))*'Company Data & Beta '!$B$70 -> 671465 | ... L23: =(L13-SUM(L14:L19))*'Company Data & Beta '!$B$70 -> 827587.38
A25: Project Decision Metrics | F25: Benchmark CAPM Returns | M25: Side Effects
M26: Year | N26: 1 | O26: 2 | P26: 3 | Q26: 4 | R26: 5 | S26: 6 | T26: 7 | U26: 8 | V26: 9 | W26: 10
A27: Project b | B27: ='Company Data & Beta '!B81 -> 0.91707152 | G27: Risk Free Rate | H27: ='Company Data & Beta '!I67 -> 0.036356131 | M27: New Units Sold | N27: =C3 -> 100000 | O27: =D3 -> 110000 | P27: =E3 -> 121000 | Q27: =F3 -> 133100 | R27: =G3 -> 146410 | S27: =H3 -> 161051 | T27: =I3 -> 177156.1 | U27: =J3 -> 194871.71 | ... W27: =L3 -> 235794.77
A28: Project IRR | B28: ='Baseline DCF NPV analysis'!B22 -> 1.803997 | G28: Equity Market Risk Premium | H28: ='Company Data & Beta '!D70 -> 0.03674624 | M28: Old Units Cannibalized | N28: =8*N27 -> 800000 | O28: =8*O27 -> 880000 | P28: =8*P27 -> 968000 | Q28: =8*Q27 -> 1064800 | R28: =8*R27 -> 1171280 | S28: =8*S27 -> 1288408 | T28: =8*T27 -> 1417248.8 | U28: =8*U27 -> 1558973.7 | ... W28: =8*W27 -> 1886358.2
A29: Project Cost of Capital | B29: ='Company Data & Beta '!I78 -> 0.082055062 | G29: Possible Liquidity Premium | H29: 0.012 | M29: Loss of Revenue | N29: =N28*0.55 -> 440000 | O29: =O28*0.55 -> 484000 | P29: =P28*0.55 -> 532400 | Q29: =Q28*0.55 -> 585640 | R29: =R28*0.55 -> 644204 | S29: =S28*0.55 -> 708624.4 | T29: =T28*0.55 -> 779486.84 | U29: =U28*0.55 -> 857435.52 | ... W29: =W28*0.55 -> 1037497
A30: Project NPV | B30: ='Baseline DCF NPV analysis'!B21 -> 10323311 | M30: New Revenue | N30: =N27*35 -> 3500000 | O30: =O27*35 -> 3850000 | P30: =P27*35 -> 4235000 | Q30: =Q27*35 -> 4658500 | R30: =R27*35 -> 5124350 | S30: =S27*35 -> 5636785 | T30: =T27*35 -> 6200463.5 | U30: =U27*35 -> 6820509.9 | ... W30: =W27*35 -> 8252816.9
F31: Treasury Debt Data (All data assume semi-annual coupon payments) | X31: average
F32: Maturity | G32: Current Price | H32: Coupon Rate | I32: Face Value | M32: Net Cash Flow pre-tax | N32: =N30-N29 -> 3060000 | O32: =O30-O29 -> 3366000 | P32: =P30-P29 -> 3702600 | Q32: =Q30-Q29 -> 4072860 | R32: =R30-R29 -> 4480146 | S32: =S30-S29 -> 4928160.6 | T32: =T30-T29 -> 5420976.7 | U32: =U30-U29 -> 5963074.3 | ... W32: =W30-W29 -> 7215319.9 | X32: =AVERAGE(N32:W32) -> 4876851.9
F33: 1 year | G33: 965.05 | H33: 0 | I33: 1000
F34: 5 years | G34: 955.16 | H34: 0.027 | I34: 1000
F35: 10 years | G35: 955.43 | H35: 0.031 | I35: 1000

Sheet Baseline DCF NPV analysis
A2: Timepoint | B2: 0 | C2: 1 | D2: 2 | E2: 3 | F2: 4 | G2: 5 | H2: 6 | I2: 7 | J2: 8 | K2: 9 | L2: 10
A3: Revenue | B3: ='Cash Flow Assumptions'!B3*'Cash Flow Assumptions'!B5 -> 0 | C3: ='Cash Flow Assumptions'!C3*'Cash Flow Assumptions'!C5 -> 3500000 | D3: ='Cash Flow Assumptions'!D3*'Cash Flow Assumptions'!D5 -> 3850000 | E3: ='Cash Flow Assumptions'!E3*'Cash Flow Assumptions'!E5 -> 4235000 | F3: ='Cash Flow Assumptions'!F3*'Cash Flow Assumptions'!F5 -> 4658500 | G3: ='Cash Flow Assumptions'!G3*'Cash Flow Assumptions'!G5 -> 5124350 | H3: ='Cash Flow Assumptions'!H3*'Cash Flow Assumptions'!H5 -> 5636785 | I3: ='Cash Flow Assumptions'!I3*'Cash Flow Assumptions'!I5 -> 6200463.5 | ... L3: ='Cash Flow Assumptions'!L3*'Cash Flow Assumptions'!L5 -> 8252816.9
A4: Side Effects | B4: ='Cash Flow Assumptions'!B14 -> 0 | C4: ='Cash Flow Assumptions'!C14 -> 440000 | D4: ='Cash Flow Assumptions'!D14 -> 484000 | E4: ='Cash Flow Assumptions'!E14 -> 532400 | F4: ='Cash Flow Assumptions'!F14 -> 585640 | G4: ='Cash Flow Assumptions'!G14 -> 644204 | H4: ='Cash Flow Assumptions'!H14 -> 708624.4 | I4: ='Cash Flow Assumptions'!I14 -> 779486.84 | ... L4: ='Cash Flow Assumptions'!L14 -> 1037497
A5: Variable Expenses | B5: ='Cash Flow Assumptions'!B15 -> 0 | C5: ='Cash Flow Assumptions'!C15 -> 1027000 | D5: ='Cash Flow Assumptions'!D15 -> 1139913.5 | E5: ='Cash Flow Assumptions'!E15 -> 1265308.2 | F5: ='Cash Flow Assumptions'!F15 -> 1010594.9 | G5: ='Cash Flow Assumptions'!G15 -> 1125869.5 | H5: ='Cash Flow Assumptions'!H15 -> 1254327.7 | I5: ='Cash Flow Assumptions'!I15 -> 1397480.6 | ... L5: ='Cash Flow Assumptions'!L15 -> 1932947.4
A6: Fixed Expenses | B6: ='Cash Flow Assumptions'!B16 -> 0 | C6: ='Cash Flow Assumptions'!C16 -> 280000 | D6: ='Cash Flow Assumptions'!D16 -> 280000 | E6: ='Cash Flow Assumptions'!E16 -> 280000 | F6: ='Cash Flow Assumptions'!F16 -> 330000 | G6: ='Cash Flow Assumptions'!G16 -> 330000 | H6: ='Cash Flow Assumptions'!H16 -> 330000 | I6: ='Cash Flow Assumptions'!I16 -> 330000 | ... L6: ='Cash Flow Assumptions'!L16 -> 330000
A7: Commision Expense | B7: ='Cash Flow Assumptions'!B17 -> 0 | C7: ='Cash Flow Assumptions'!C17 -> 35000 | D7: ='Cash Flow Assumptions'!D17 -> 38500 | E7: ='Cash Flow Assumptions'!E17 -> 42350 | F7: ='Cash Flow Assumptions'!F17 -> 46585 | G7: ='Cash Flow Assumptions'!G17 -> 51243.5 | H7: ='Cash Flow Assumptions'!H17 -> 28183.925 | I7: ='Cash Flow Assumptions'!I17 -> 31002.318 | ... L7: ='Cash Flow Assumptions'!L17 -> 41264.085
A8: Immediate Expense | B8: 160000
A9: Campaign Expense | B9: 0 | C9: ='Cash Flow Assumptions'!C18 -> 80000 | D9: ='Cash Flow Assumptions'!D18 -> 500500 | E9: ='Cash Flow Assumptions'!E18 -> 550550 | F9: ='Cash Flow Assumptions'!F18 -> 605605 | G9: ='Cash Flow Assumptions'!G18 -> 666165.5 | H9: ='Cash Flow Assumptions'!H18 -> 732782.05 | I9: ='Cash Flow Assumptions'!I18 -> 806060.26 | J9: ='Cash Flow Assumptions'!J18 -> 886666.28 | ... L9: ='Cash Flow Assumptions'!L18 -> 1072866.2
A10: Remediation Expense | B10: 0 | C10: 100000 | D10: 100000 | E10: 100000 | F10: 100000 | G10: 100000 | H10: 100000 | I10: 100000 | J10: 100000 | K10: 100000
A11: Depreciation Expense | B11: ='Cash Flow Assumptions'!B19 -> 0 | C11: ='Cash Flow Assumptions'!C19 -> 68000 | D11: ='Cash Flow Assumptions'!D19 -> 68000 | E11: ='Cash Flow Assumptions'!E19 -> 68000 | F11: ='Cash Flow Assumptions'!F19 -> 218000 | G11: ='Cash Flow Assumptions'!G19 -> 218000 | H11: ='Cash Flow Assumptions'!H19 -> 218000 | I11: ='Cash Flow Assumptions'!I19 -> 218000 | ... L11: ='Cash Flow Assumptions'!L19 -> 218000
A12: Earnings Before Interest and Taxes (PBT or EBIT) | B12: =B3-SUM(B4:B11) -> -160000 | C12: =C3-SUM(C4:C11) -> 1470000 | D12: =D3-SUM(D4:D11) -> 1239086.5 | E12: =E3-SUM(E4:E11) -> 1396391.8 | F12: =F3-SUM(F4:F11) -> 1762075.1 | G12: =G3-SUM(G4:G11) -> 1988867.5 | H12: =H3-SUM(H4:H11) -> 2264867 | I12: =I3-SUM(I4:I11) -> 2538433.5 | ... L12: =L3-SUM(L4:L11) -> 3620242.2
A13: Taxes | B13: =B12*'Company Data & Beta '!$B$70 -> -36576 | C13: =C12*'Company Data & Beta '!$B$70 -> 336042 | D13: =D12*'Company Data & Beta '!$B$70 -> 283255.17 | E13: =E12*'Company Data & Beta '!$B$70 -> 319215.16 | F13: =F12*'Company Data & Beta '!$B$70 -> 402810.37 | G13: =G12*'Company Data & Beta '!$B$70 -> 454655.1 | H13: =H12*'Company Data & Beta '!$B$70 -> 517748.59 | I13: =I12*'Company Data & Beta '!$B$70 -> 580285.89 | ... L13: =L12*'Company Data & Beta '!$B$70 -> 827587.38
A14: Normal Operating Profit After Tax (NOPAT) | B14: =B12-B13 -> -123424 | C14: =C12-C13 -> 1133958 | D14: =D12-D13 -> 955831.33 | E14: =E12-E13 -> 1077176.6 | F14: =F12-F13 -> 1359264.7 | G14: =G12-G13 -> 1534212.4 | H14: =H12-H13 -> 1747118.4 | I14: =I12-I13 -> 1958147.6 | ... L14: =L12-L13 -> 2792654.9
A16: OCF | B16: =B14+B11 -> -123424 | C16: =C14+C11 -> 1201958 | D16: =D14+D11 -> 1023831.3 | E16: =E14+E11 -> 1145176.6 | F16: =F14+F11 -> 1577264.7 | G16: =G14+G11 -> 1752212.4 | H16: =H14+H11 -> 1965118.4 | I16: =I14+I11 -> 2176147.6 | ... L16: =L14+L11 -> 3010654.9
A17: Changes in NWC | B17: =-'Cash Flow Assumptions'!B20 -> -150000 | C17: =-('Cash Flow Assumptions'!C20-'Cash Flow Assumptions'!B20) -> 100000 | D17: =-('Cash Flow Assumptions'!D20-'Cash Flow Assumptions'!C20) -> -5000 | E17: =-('Cash Flow Assumptions'!E20-'Cash Flow Assumptions'!D20) -> -5500 | F17: =-('Cash Flow Assumptions'!F20-'Cash Flow Assumptions'!E20) -> -6050 | G17: =-('Cash Flow Assumptions'!G20-'Cash Flow Assumptions'!F20) -> -6655 | H17: =-('Cash Flow Assumptions'!H20-'Cash Flow Assumptions'!G20) -> -7320.5 | I17: =-('Cash Flow Assumptions'!I20-'Cash Flow Assumptions'!H20) -> -8052.55 | J17: =-('Cash Flow Assumptions'!J20-'Cash Flow Assumptions'!I20) -> -8857.805 | ... L17: =-('Cash Flow Assumptions'!L20-'Cash Flow Assumptions'!K20) -> 107179.44
A18: Capital Expenditures | B18: =-'Cash Flow Assumptions'!B21 -> -400000 | C18: ='Cash Flow Assumptions'!C21 -> 0 | D18: ='Cash Flow Assumptions'!D21 -> 0 | E18: ='Cash Flow Assumptions'!E21 -> 0 | F18: =-'Cash Flow Assumptions'!F21 -> -750000 | G18: =-'Cash Flow Assumptions'!G21 -> -400000 | H18: ='Cash Flow Assumptions'!H21 -> 0 | I18: ='Cash Flow Assumptions'!I21 -> 0 | J18: ='Cash Flow Assumptions'!J21 -> 0 | K18: ='Cash Flow Assumptions'!K21 -> 750000 | L18: =F18 -> -750000
A19: Net Salvage Values | G19: ='Cash Flow Assumptions'!T17 -> 23142 | L19: =G19 -> 23142
A20: Total Cash Flows | B20: =SUM(B16:B19) -> -673424 | C20: =SUM(C16:C19) -> 1301958 | D20: =SUM(D16:D19) -> 1018831.3 | E20: =SUM(E16:E19) -> 1139676.6 | F20: =SUM(F16:F19) -> 821214.72 | G20: =SUM(G16:G19) -> 1368699.4 | H20: =SUM(H16:H19) -> 1957797.9 | I20: =SUM(I16:I19) -> 2168095 | ... L20: =SUM(L16:L19) -> 2390976.3
A21: NPV | B21: =NPV(B23,C20:L20)+B20 -> 10323311
A22: IRR | B22: =IRR(B20:L20) -> 1.803997
A23: Discount rate used | B23: ='Company Data & Beta '!I78 -> 0.082055062

Sheet Alternative Scenario Cash Flows
A1: Project Cash Flows
A2: Unit Assumptions | B2: 0 | C2: 1 | D2: 2 | E2: 3 | F2: 4 | G2: 5 | H2: 6 | I2: 7 | J2: 8 | K2: 9 | L2: 10
A3: Unit quantity | C3: ='Cash Flow Assumptions'!C3 -> 100000 | D3: ='Cash Flow Assumptions'!D3 -> 110000 | E3: ='Cash Flow Assumptions'!E3 -> 121000 | F3: ='Cash Flow Assumptions'!F3 -> 133100 | G3: ='Cash Flow Assumptions'!G3 -> 146410 | H3: ='Cash Flow Assumptions'!H3 -> 161051 | I3: ='Cash Flow Assumptions'!I3 -> 177156.1 | J3: ='Cash Flow Assumptions'!J3 -> 194871.71 | ... L3: ='Cash Flow Assumptions'!L3 -> 235794.77
A4: Unit Selling Price (revenue) | C4: =24 -> 24 | D4: =24 -> 24 | E4: =24 -> 24 | F4: =24 -> 24 | G4: =24 -> 24 | H4: =24 -> 24 | I4: =24 -> 24 | J4: =24 -> 24 | ... L4: =24 -> 24
A5: Material Unit Variable Cost | C5: =5.19 -> 5.19 | D5: =C5*1.015 -> 5.26785 | E5: =D5*1.015 -> 5.3468677 | F5: =E5*1.015 -> 5.4270708 | G5: =F5*1.015 -> 5.5084768 | H5: =G5*1.015 -> 5.591104 | I5: =H5*1.015 -> 5.6749705 | J5: =I5*1.015 -> 5.7600951 | K5: =J5*1.015 -> 5.8464965 | L5: =K5*1.015 -> 5.934194
A6: Overhead Unit Variable Cost | C6: ='Cash Flow Assumptions'!C7 -> 4.08 | D6: ='Cash Flow Assumptions'!D7 -> 4.08 | E6: ='Cash Flow Assumptions'!E7 -> 4.08 | F6: ='Cash Flow Assumptions'!F7 -> 1.12 | G6: ='Cash Flow Assumptions'!G7 -> 1.12 | H6: ='Cash Flow Assumptions'!H7 -> 1.12 | I6: ='Cash Flow Assumptions'!I7 -> 1.12 | J6: ='Cash Flow Assumptions'!J7 -> 1.12 | ... L6: ='Cash Flow Assumptions'!L7 -> 1.12
A7: Unit Fixed Cost | C7: ='Cash Flow Assumptions'!C8 -> 2.8 | D7: ='Cash Flow Assumptions'!D8 -> 2.5454545 | E7: ='Cash Flow Assumptions'!E8 -> 2.3140496 | F7: ='Cash Flow Assumptions'!F8 -> 2.4793388 | G7: ='Cash Flow Assumptions'!G8 -> 2.2539444 | H7: ='Cash Flow Assumptions'!H8 -> 2.0490404 | I7: ='Cash Flow Assumptions'!I8 -> 1.862764 | J7: ='Cash Flow Assumptions'!J8 -> 1.6934218 | ... L7: ='Cash Flow Assumptions'!L8 -> 1.3995221
M8: Depreciable Assets
A9: Project Assumptions
B10: 0 | C10: 1 | D10: 2 | E10: 3 | F10: 4 | G10: 5 | H10: 6 | I10: 7 | J10: 8 | K10: 9 | L10: 10 | M10: Deprec Asset Class | N10: ED | O10: Recovery Period (SL) | P10: Annual Depr | Q10: Bonus Depr | R10: MV5 | S10: BV5 | T10: NSV5
A11: Units Sold | C11: =C3 -> 100000 | D11: =D3 -> 110000 | E11: =E3 -> 121000 | F11: =F3 -> 133100 | G11: =G3 -> 146410 | H11: =H3 -> 161051 | I11: =I3 -> 177156.1 | J11: =J3 -> 194871.71 | ... L11: =L3 -> 235794.77 | M11: A | N11: ='Cash Flow Assumptions'!N12 -> 150000 | O11: 5 | P11: =N11/O11 -> 30000 | S11: 0 | T11: 0
A12: Revenue | C12: =C11*C4 -> 2400000 | D12: =D11*D4 -> 2640000 | E12: =E11*E4 -> 2904000 | F12: =F11*F4 -> 3194400 | G12: =G11*G4 -> 3513840 | H12: =H11*H4 -> 3865224 | I12: =I11*I4 -> 4251746.4 | J12: =J11*J4 -> 4676921 | ... L12: =L11*L4 -> 5659074.5 | M12: B | N12: ='Cash Flow Assumptions'!N13 -> 110000 | O12: 5 | P12: =N12/O12 -> 22000 | S12: 0 | T12: 0
A13: Synergies or Erosion impacts | C13: =N27 -> 440000 | D13: =O27 -> 484000 | E13: =P27 -> 532400 | F13: =Q27 -> 585640 | G13: =R27 -> 644204 | H13: =S27 -> 708624.4 | I13: =T27 -> 779486.84 | J13: =U27 -> 857435.52 | ... L13: =W27 -> 1037497 | M13: C | N13: ='Cash Flow Assumptions'!N14 -> 40000 | O13: 5 | P13: =N13/O13 -> 8000 | S13: 0 | T13: 0 | V13: tax rate | W13: 0.2286
A14: Variable Expenses | C14: =(C11*C5)+(C11*C6) -> 927000 | D14: =(D11*D5)+(D11*D6) -> 1028263.5 | E14: =(E11*E5)+(E11*E6) -> 1140651 | F14: =(F11*F5)+(F11*F6) -> 871415.12 | G14: =(G11*G5)+(G11*G6) -> 970475.29 | H14: =(H11*H5)+(H11*H6) -> 1080830 | I14: =(I11*I5)+(I11*I6) -> 1203770.5 | J14: =(J11*J5)+(J11*J6) -> 1340735.9 | ... L14: =(L11*L5)+(L11*L6) -> 1663342 | M14: D | N14: ='Cash Flow Assumptions'!N15 -> 100000 | O14: 5 | P14: =(N14-S14)/O14 -> 14000 | R14: 200000 | S14: 30000 | T14: =W18 -> 161138 | V14: MV5 | W14: =R14 -> 200000
A15: Fixed Expenses | C15: =C7*C11 -> 280000 | D15: =D7*D11 -> 280000 | E15: =E7*E11 -> 280000 | F15: =F7*F11 -> 330000 | G15: =G7*G11 -> 330000 | H15: =H7*H11 -> 330000 | I15: =I7*I11 -> 330000 | J15: =J7*J11 -> 330000 | ... L15: =L7*L11 -> 330000 | M15: E | N15: ='Cash Flow Assumptions'!N16 -> 750000 | O15: 5 | P15: N/A | Q15: =N15 -> 750000 | S15: 0 | T15: 0 | V15: BV5 | W15: =S14 -> 30000
A16: Commission Expenses | C16: =0.01*C12 -> 24000 | D16: =0.01*D12 -> 26400 | E16: =0.01*E12 -> 29040 | F16: =0.01*F12 -> 31944 | G16: =0.01*G12 -> 35138.4 | H16: =0.5%*H12 -> 19326.12 | I16: =0.5%*I12 -> 21258.732 | J16: =0.5%*J12 -> 23384.605 | K16: =0.5%*K12 -> 25723.066 | L16: =0.5%*L12 -> 28295.372 | M16: totals | N16: =SUM(N11:N14) -> 400000 | P16: =SUM(P11:P15) -> 74000 | R16: =SUM(R11:R14) -> 200000 | S16: =SUM(S11:S15) -> 30000 | T16: =SUM(T11:T15) -> 161138 | V16: Gain on sale of D | W16: =W14-W15 -> 170000
A17: Campaign Expenses | C17: =80000 -> 80000 | D17: =13%*D12 -> 343200 | E17: =13%*E12 -> 377520 | F17: =13%*F12 -> 415272 | G17: =13%*G12 -> 456799.2 | H17: =13%*H12 -> 502479.12 | I17: =13%*I12 -> 552727.03 | J17: =13%*J12 -> 607999.74 | K17: =13%*K12 -> 668799.71 | L17: =13%*L12 -> 735679.68 | V17: Tax on Gain | W17: =W16*W13 -> 38862
A18: Depreciation Expense | C18: =SUM($P$11:$P$14) -> 74000 | D18: =C18 -> 74000 | E18: =D18 -> 74000 | F18: =E18+Q15 -> 824000 | G18: =C18 -> 74000 | H18: =D18 -> 74000 | I18: =E18 -> 74000 | J18: =I18 -> 74000 | K18: =G18+Q15 -> 824000 | L18: =P16 -> 74000 | M18: Assume any loss on salvage of machinery result in an immediate tax deduction which adds to total cash flows in the same year of disposal | V18: NSV5 on D | W18: =W14-W17 -> 161138
A19: Net working Capital | B19: ='Cash Flow Assumptions'!B20 -> 150000 | C19: ='Cash Flow Assumptions'!C20 -> 50000 | D19: ='Cash Flow Assumptions'!D20 -> 55000 | E19: ='Cash Flow Assumptions'!E20 -> 60500 | F19: ='Cash Flow Assumptions'!F20 -> 66550 | G19: ='Cash Flow Assumptions'!G20 -> 73205 | H19: ='Cash Flow Assumptions'!H20 -> 80525.5 | I19: ='Cash Flow Assumptions'!I20 -> 88578.05 | ... L19: ='Cash Flow Assumptions'!L20 -> 0
A20: Capital Equipment | B20: =SUM(N11:N14) -> 400000 | F20: =N15 -> 750000 | G20: =B20 -> 400000 | K20: =F20 -> 750000
A21: Net Salvage Value | G21: =T16 -> 161138 | L21: =T16 -> 161138
A22: Taxes | C22: =(C12-SUM(C13:C18))*$W$13 -> 131445 | D22: =(D12-SUM(D13:D18))*$W$13 -> 92385.604 | E22: =(E12-SUM(E13:E18))*$W$13 -> 107530.93 | F22: =(F12-SUM(F13:F18))*$W$13 -> 31119.062 | G22: =(G12-SUM(G13:G18))*$W$13 -> 229336.8 | H22: =(H12-SUM(H13:H18))*$W$13 -> 262881.85 | I22: =(I12-SUM(I13:I18))*$W$13 -> 295009.06 | J22: =(J12-SUM(J13:J18))*$W$13 -> 329953.3 | ... L22: =(L12-SUM(L13:L18))*$W$13 -> 409253.52
F23: Benchmark CAPM Returns | M23: Side Effects
A24: Project Decision Metrics | M24: Year | N24: 1 | O24: 2 | P24: 3 | Q24: 4 | R24: 5 | S24: 6 | T24: 7 | U24: 8 | V24: 9 | W24: 10
G25: Risk Free Rate | H25: ='Company Data & Beta '!I67 -> 0.036356131 | M25: New Units Sold | N25: =C11 -> 100000 | O25: =D11 -> 110000 | P25: =E11 -> 121000 | Q25: =F11 -> 133100 | R25: =G11 -> 146410 | S25: =H11 -> 161051 | T25: =I11 -> 177156.1 | U25: =J11 -> 194871.71 | ... W25: =L11 -> 235794.77
A26: Project b | B26: ='Cash Flow Assumptions'!B27 -> 0.91707152 | G26: Equity Market Risk Premium | H26: ='Company Data & Beta '!I74 -> 0.03674624 | M26: Old Units Cannibalized | N26: =N25*8 -> 800000 | O26: =O25*8 -> 880000 | P26: =P25*8 -> 968000 | Q26: =Q25*8 -> 1064800 | R26: =R25*8 -> 1171280 | S26: =S25*8 -> 1288408 | T26: =T25*8 -> 1417248.8 | U26: =U25*8 -> 1558973.7 | ... W26: =W25*8 -> 1886358.2
A27: Project IRR | B27: ='Alternative Scenario DCF NPV '!B22 -> 0.66092463 | G27: Possible Liquidity Premium | H27: ='Cash Flow Assumptions'!H29 -> 0.012 | M27: Loss of Revenue | N27: =N26*0.55 -> 440000 | O27: =O26*0.55 -> 484000 | P27: =P26*0.55 -> 532400 | Q27: =Q26*0.55 -> 585640 | R27: =R26*0.55 -> 644204 | S27: =S26*0.55 -> 708624.4 | T27: =T26*0.55 -> 779486.84 | U27: =U26*0.55 -> 857435.52 | ... W27: =W26*0.55 -> 1037497
A28: Project Cost of Capital | B28: ='Alternative Scenario DCF NPV '!B23 -> 0.082055062 | M28: New Revenue | N28: =N25*24 -> 2400000 | O28: =O25*24 -> 2640000 | P28: =P25*24 -> 2904000 | Q28: =Q25*24 -> 3194400 | R28: =R25*24 -> 3513840 | S28: =S25*24 -> 3865224 | T28: =T25*24 -> 4251746.4 | U28: =U25*24 -> 4676921 | ... W28: =W25*24 -> 5659074.5
A29: Project NPV | B29: ='Alternative Scenario DCF NPV '!B21 -> 3590804.1 | F29: Treasury Debt Data (All data assume semi-annual coupon payments)
F30: Maturity | G30: Current Price | H30: Coupon Rate | I30: Face Value | M30: Net Cash Flow pre-tax | N30: =N28-N27 -> 1960000 | O30: =O28-O27 -> 2156000 | P30: =P28-P27 -> 2371600 | Q30: =Q28-Q27 -> 2608760 | R30: =R28-R27 -> 2869636 | S30: =S28-S27 -> 3156599.6 | T30: =T28-T27 -> 3472259.6 | U30: =U28-U27 -> 3819485.5 | ... W30: =W28-W27 -> 4621577.5
F31: 1 year | G31: 965.05 | H31: 0 | I31: 1000
F32: 5 years | G32: 955.16 | H32: 0.027 | I32: 1000
F33: 10 years | G33: 955.43 | H33: 0.031 | I33: 1000

Sheet Alternative Scenario DCF  NPV 
A2: Timepoint | B2: 0 | C2: 1 | D2: 2 | E2: 3 | F2: 4 | G2: 5 | H2: 6 | I2: 7 | J2: 8 | K2: 9 | L2: 10
A3: Revenue | C3: ='Alternative Scenario Cash Flows'!C12 -> 2400000 | D3: ='Alternative Scenario Cash Flows'!D12 -> 2640000 | E3: ='Alternative Scenario Cash Flows'!E12 -> 2904000 | F3: ='Alternative Scenario Cash Flows'!F12 -> 3194400 | G3: ='Alternative Scenario Cash Flows'!G12 -> 3513840 | H3: ='Alternative Scenario Cash Flows'!H12 -> 3865224 | I3: ='Alternative Scenario Cash Flows'!I12 -> 4251746.4 | J3: ='Alternative Scenario Cash Flows'!J12 -> 4676921 | ... L3: ='Alternative Scenario Cash Flows'!L12 -> 5659074.5
A4: Side Effects | C4: ='Alternative Scenario Cash Flows'!C13 -> 440000 | D4: ='Alternative Scenario Cash Flows'!D13 -> 484000 | E4: ='Alternative Scenario Cash Flows'!E13 -> 532400 | F4: ='Alternative Scenario Cash Flows'!F13 -> 585640 | G4: ='Alternative Scenario Cash Flows'!G13 -> 644204 | H4: ='Alternative Scenario Cash Flows'!H13 -> 708624.4 | I4: ='Alternative Scenario Cash Flows'!I13 -> 779486.84 | J4: ='Alternative Scenario Cash Flows'!J13 -> 857435.52 | ... L4: ='Alternative Scenario Cash Flows'!L13 -> 1037497
A5: Variable Expenses | C5: ='Alternative Scenario Cash Flows'!C14 -> 927000 | D5: ='Alternative Scenario Cash Flows'!D14 -> 1028263.5 | E5: ='Alternative Scenario Cash Flows'!E14 -> 1140651 | F5: ='Alternative Scenario Cash Flows'!F14 -> 871415.12 | G5: ='Alternative Scenario Cash Flows'!G14 -> 970475.29 | H5: ='Alternative Scenario Cash Flows'!H14 -> 1080830 | I5: ='Alternative Scenario Cash Flows'!I14 -> 1203770.5 | J5: ='Alternative Scenario Cash Flows'!J14 -> 1340735.9 | ... L5: ='Alternative Scenario Cash Flows'!L14 -> 1663342
A6: Fixed Expenses | C6: ='Alternative Scenario Cash Flows'!C15 -> 280000 | D6: ='Alternative Scenario Cash Flows'!D15 -> 280000 | E6: ='Alternative Scenario Cash Flows'!E15 -> 280000 | F6: ='Alternative Scenario Cash Flows'!F15 -> 330000 | G6: ='Alternative Scenario Cash Flows'!G15 -> 330000 | H6: ='Alternative Scenario Cash Flows'!H15 -> 330000 | I6: ='Alternative Scenario Cash Flows'!I15 -> 330000 | J6: ='Alternative Scenario Cash Flows'!J15 -> 330000 | ... L6: ='Alternative Scenario Cash Flows'!L15 -> 330000
A7: Commission Expenses | C7: ='Alternative Scenario Cash Flows'!C16 -> 24000 | D7: ='Alternative Scenario Cash Flows'!D16 -> 26400 | E7: ='Alternative Scenario Cash Flows'!E16 -> 29040 | F7: ='Alternative Scenario Cash Flows'!F16 -> 31944 | G7: ='Alternative Scenario Cash Flows'!G16 -> 35138.4 | H7: ='Alternative Scenario Cash Flows'!H16 -> 19326.12 | I7: ='Alternative Scenario Cash Flows'!I16 -> 21258.732 | J7: ='Alternative Scenario Cash Flows'!J16 -> 23384.605 | ... L7: ='Alternative Scenario Cash Flows'!L16 -> 28295.372
A8: Campaign Expenses | C8: {='Alternative Scenario Cash Flows'!C17:L17} -> 80000 | D8: 343200 | E8: 377520 | F8: 415272 | G8: 456799.2 | H8: 502479.12 | I8: 552727.03 | J8: 607999.74 | K8: 668799.71 | L8: 735679.68
A9: Remediation Expense | C9: 100000 | D9: 100000 | E9: 100000 | F9: 100000 | G9: 100000 | H9: 100000 | I9: 100000 | J9: 100000 | K9: 100000
A10: Immediate Expense | B10: 160000
A11: Depreciation Expense | C11: ='Alternative Scenario Cash Flows'!C18 -> 74000 | D11: ='Alternative Scenario Cash Flows'!D18 -> 74000 | E11: ='Alternative Scenario Cash Flows'!E18 -> 74000 | F11: ='Alternative Scenario Cash Flows'!F18 -> 824000 | G11: ='Alternative Scenario Cash Flows'!G18 -> 74000 | H11: ='Alternative Scenario Cash Flows'!H18 -> 74000 | I11: ='Alternative Scenario Cash Flows'!I18 -> 74000 | J11: ='Alternative Scenario Cash Flows'!J18 -> 74000 | ... L11: ='Alternative Scenario Cash Flows'!L18 -> 74000
A12: Earnings Before Interest and Taxes (PBT or EBIT) | B12: =B3-SUM(B4:B11) -> -160000 | C12: =C3-SUM(C4:C11) -> 475000 | D12: =D3-SUM(D4:D11) -> 304136.5 | E12: =E3-SUM(E4:E11) -> 370389 | F12: =F3-SUM(F4:F11) -> 36128.881 | G12: =G3-SUM(G4:G11) -> 903223.11 | H12: =H3-SUM(H4:H11) -> 1049964.4 | I12: =I3-SUM(I4:I11) -> 1190503.3 | ... L12: =L3-SUM(L4:L11) -> 1790260.4
A13: Taxes | B13: =22.86%*B12 -> -36576 | C13: =C12*22.86% -> 108585 | D13: =D12*22.86% -> 69525.604 | E13: =E12*22.86% -> 84670.926 | F13: =F12*22.86% -> 8259.0622 | G13: =G12*22.86% -> 206476.8 | H13: =H12*22.86% -> 240021.85 | I13: =I12*22.86% -> 272149.06 | J13: =J12*22.86% -> 307093.3 | ... L13: =L12*22.86% -> 409253.52
A14: Normal Operating Profit After Tax (NOPAT) | B14: =B12-B13 -> -123424 | C14: =C12-C13 -> 366415 | D14: =D12-D13 -> 234610.9 | E14: =E12-E13 -> 285718.08 | F14: =F12-F13 -> 27869.819 | G14: =G12-G13 -> 696746.31 | H14: =H12-H13 -> 809942.5 | I14: =I12-I13 -> 918354.26 | ... L14: =L12-L13 -> 1381006.9
A16: OCF | B16: =B14+B11 -> -123424 | C16: =C14+C11 -> 440415 | D16: =D14+D11 -> 308610.9 | E16: =E14+E11 -> 359718.08 | F16: =F14+F11 -> 851869.82 | G16: =G14+G11 -> 770746.31 | H16: =H14+H11 -> 883942.5 | I16: =I14+I11 -> 992354.26 | ... L16: =L14+L11 -> 1455006.9
A17: Changes in NWC | B17: =0-'Alternative Scenario Cash Flows'!B19 -> -150000 | C17: ='Alternative Scenario Cash Flows'!B19-'Alternative Scenario Cash Flows'!C19 -> 100000 | D17: ='Alternative Scenario Cash Flows'!C19-'Alternative Scenario Cash Flows'!D19 -> -5000 | E17: ='Alternative Scenario Cash Flows'!D19-'Alternative Scenario Cash Flows'!E19 -> -5500 | F17: ='Alternative Scenario Cash Flows'!E19-'Alternative Scenario Cash Flows'!F19 -> -6050 | G17: ='Alternative Scenario Cash Flows'!F19-'Alternative Scenario Cash Flows'!G19 -> -6655 | H17: ='Alternative Scenario Cash Flows'!G19-'Alternative Scenario Cash Flows'!H19 -> -7320.5 | I17: ='Alternative Scenario Cash Flows'!H19-'Alternative Scenario Cash Flows'!I19 -> -8052.55 | J17: ='Alternative Scenario Cash Flows'!I19-'Alternative Scenario Cash Flows'!J19 -> -8857.805 | ... L17: ='Alternative Scenario Cash Flows'!K19-'Alternative Scenario Cash Flows'!L19 -> 107179.44
A18: Capital Expenditures | B18: =-'Alternative Scenario Cash Flows'!B20 -> -400000 | F18: =-'Alternative Scenario Cash Flows'!F20 -> -750000 | G18: =B18 -> -400000 | K18: =F18 -> -750000
A19: Net Salvage Values | G19: ='Alternative Scenario Cash Flows'!G21 -> 161138 | L19: ='Alternative Scenario Cash Flows'!L21 -> 161138
A20: Total Cash Flows | B20: =SUM(B16:B19) -> -673424 | C20: =SUM(C16:C19) -> 540415 | D20: =SUM(D16:D19) -> 303610.9 | E20: =SUM(E16:E19) -> 354218.08 | F20: =SUM(F16:F19) -> 95819.819 | G20: =SUM(G16:G19) -> 525229.31 | H20: =SUM(H16:H19) -> 876622 | I20: =SUM(I16:I19) -> 984301.71 | ... L20: =SUM(L16:L19) -> 1723324.3
A21: NPV | B21: =NPV(B23,C20:L20)+B20 -> 3590804.1
A22: IRR | B22: =IRR(B20:L20) -> 0.66092463
A23: Discount rate used | B23: ='Baseline DCF NPV analysis'!B23 -> 0.082055062

Sheet RiskRGSheet4R30C2
A1: X-Delimiters | E1: Series 1
E2: 20.612421 | F2: 0
A3: -18.386969 | B3: 0 | E3: 1 | F3: 0.0031631004
A4: 68.713921 | B4: 0 | E4: 2 | F4: 0.0081336868
E5: 3 | F5: 0.013375396
E6: 4 | F6: 0.014911759
E7: 5 | F7: 0.012742776
E8: 6 | F8: 0.011206413
E9: 7 | F9: 0.0090374297
E10: 8 | F10: 0.0076818153
E11: 9 | F11: 0.0051513349
E12: 10 | F12: 0.0034342233
E13: 11 | F13: 0.0015363631
A600: -31.671734 | B600: 0
A601: -31.671734 | B601: =$F$3 -> 0.0031631004 | C601: -31.671734 | D601: 0
A602: -31.59059 | B602: =$F$3 -> 0.0031631004 | C602: -31.671734 | D602: =$F$3 -> 0.0031631004
A603: -31.59059 | B603: 0 | C603: -20.606641 | D603: =$F$3 -> 0.0031631004
A604: -31.509446 | B604: 0 | C604: -20.606641 | D604: 0
A605: -31.509446 | B605: =$F$3 -> 0.0031631004 | C605: -20.606641 | D605: =$F$4 -> 0.0081336868
A606: -31.428302 | B606: =$F$3 -> 0.0031631004 | C606: -9.5415479 | D606: =$F$4 -> 0.0081336868
A607: -31.428302 | B607: 0 | C607: -9.5415479 | D607: 0
A608: -31.347158 | B608: 0 | C608: -9.5415479 | D608: =$F$5 -> 0.013375396
A609: -31.347158 | B609: =$F$3 -> 0.0031631004 | C609: 1.523545 | D609: =$F$5 -> 0.013375396
A610: -31.266014 | B610: =$F$3 -> 0.0031631004 | C610: 1.523545 | D610: 0
A611: -31.266014 | B611: 0 | C611: 1.523545 | D611: =$F$6 -> 0.014911759
A612: -31.18487 | B612: 0 | C612: 12.588638 | D612: =$F$6 -> 0.014911759
A613: -31.18487 | B613: =$F$3 -> 0.0031631004 | C613: 12.588638 | D613: 0
A614: -31.103726 | B614: =$F$3 -> 0.0031631004 | C614: 12.588638 | D614: =$F$7 -> 0.012742776
A615: -31.103726 | B615: 0 | C615: 23.653731 | D615: =$F$7 -> 0.012742776
A616: -31.022582 | B616: 0 | C616: 23.653731 | D616: 0
A617: -31.022582 | B617: =$F$3 -> 0.0031631004 | C617: 23.653731 | D617: =$F$8 -> 0.011206413
A618: -30.941438 | B618: =$F$3 -> 0.0031631004 | C618: 34.718824 | D618: =$F$8 -> 0.011206413
A619: -30.941438 | B619: 0 | C619: 34.718824 | D619: 0
A620: -30.860294 | B620: 0 | C620: 34.718824 | D620: =$F$9 -> 0.0090374297
A621: -30.860294 | B621: =$F$3 -> 0.0031631004 | C621: 45.783917 | D621: =$F$9 -> 0.0090374297
A622: -30.77915 | B622: =$F$3 -> 0.0031631004 | C622: 45.783917 | D622: 0
A623: -30.77915 | B623: 0 | C623: 45.783917 | D623: =$F$10 -> 0.0076818153
A624: -30.698006 | B624: 0 | C624: 56.84901 | D624: =$F$10 -> 0.0076818153
A625: -30.698006 | B625: =$F$3 -> 0.0031631004 | C625: 56.84901 | D625: 0
A626: -30.616862 | B626: =$F$3 -> 0.0031631004 | C626: 56.84901 | D626: =$F$11 -> 0.0051513349
A627: -30.616862 | B627: 0 | C627: 67.914103 | D627: =$F$11 -> 0.0051513349
A628: -30.535718 | B628: 0 | C628: 67.914103 | D628: 0
A629: -30.535718 | B629: =$F$3 -> 0.0031631004 | C629: 67.914103 | D629: =$F$12 -> 0.0034342233
A630: -30.454574 | B630: =$F$3 -> 0.0031631004 | C630: 78.979196 | D630: =$F$12 -> 0.0034342233
A631: -30.454574 | B631: 0 | C631: 78.979196 | D631: 0
A632: -30.37343 | B632: 0 | C632: 78.979196 | D632: =$F$13 -> 0.0015363631
A633: -30.37343 | B633: =$F$3 -> 0.0031631004 | C633: 90.044289 | D633: =$F$13 -> 0.0015363631
A634: -30.292286 | B634: =$F$3 -> 0.0031631004 | C634: 90.044289 | D634: 0
A635: -30.292286 | B635: 0
A636: -30.211142 | B636: 0
A637: -30.211142 | B637: =$F$3 -> 0.0031631004
A638: -30.129998 | B638: =$F$3 -> 0.0031631004
A639: -30.129998 | B639: 0
A640: -30.048854 | B640: 0
A641: -30.048854 | B641: =$F$3 -> 0.0031631004
A642: -29.96771 | B642: =$F$3 -> 0.0031631004
A643: -29.96771 | B643: 0
A644: -29.886566 | B644: 0
A645: -29.886566 | B645: =$F$3 -> 0.0031631004
A646: -29.805422 | B646: =$F$3 -> 0.0031631004
A647: -29.805422 | B647: 0
A648: -29.724277 | B648: 0
A649: -29.724277 | B649: =$F$3 -> 0.0031631004
A650: -29.643133 | B650: =$F$3 -> 0.0031631004
A651: -29.643133 | B651: 0
A652: -29.561989 | B652: 0
A653: -29.561989 | B653: =$F$3 -> 0.0031631004
A654: -29.480845 | B654: =$F$3 -> 0.0031631004
A655: -29.480845 | B655: 0
A656: -29.399701 | B656: 0
A657: -29.399701 | B657: =$F$3 -> 0.0031631004
A658: -29.318557 | B658: =$F$3 -> 0.0031631004
A659: -29.318557 | B659: 0
A660: -29.237413 | B660: 0
A661: -29.237413 | B661: =$F$3 -> 0.0031631004
A662: -29.156269 | B662: =$F$3 -> 0.0031631004
A663: -29.156269 | B663: 0
A664: -29.075125 | B664: 0
A665: -29.075125 | B665: =$F$3 -> 0.0031631004
A666: -28.993981 | B666: =$F$3 -> 0.0031631004
A667: -28.993981 | B667: 0
A668: -28.912837 | B668: 0
A669: -28.912837 | B669: =$F$3 -> 0.0031631004
A670: -28.831693 | B670: =$F$3 -> 0.0031631004
A671: -28.831693 | B671: 0
A672: -28.750549 | B672: 0
A673: -28.750549 | B673: =$F$3 -> 0.0031631004
A674: -28.669405 | B674: =$F$3 -> 0.0031631004
A675: -28.669405 | B675: 0
A676: -28.588261 | B676: 0
A677: -28.588261 | B677: =$F$3 -> 0.0031631004
A678: -28.507117 | B678: =$F$3 -> 0.0031631004
A679: -28.507117 | B679: 0
A680: -28.425973 | B680: 0
A681: -28.425973 | B681: =$F$3 -> 0.0031631004
A682: -28.344829 | B682: =$F$3 -> 0.0031631004
A683: -28.344829 | B683: 0
A684: -28.263685 | B684: 0
A685: -28.263685 | B685: =$F$3 -> 0.0031631004
A686: -28.182541 | B686: =$F$3 -> 0.0031631004
...

Sheet RiskRGAd ContractR30C2
A1: X-Delimiters | E1: Series 1
E2: 28.975252 | F2: 0
A3: -11.058243 | B3: 0 | E3: 1 | F3: 0.010050579
A4: 80.14402 | B4: 0 | E4: 2 | F4: 0.013224447
E5: 3 | F5: 0.012166491
E6: 4 | F6: 0.0095216016
E7: 5 | F7: 0.0037028451
E8: 6 | F8: 0.0037028451
E9: 7 | F9: 0
E10: 8 | F10: 0.00052897786
A600: -17.190323 | B600: 0
A601: -17.190323 | B601: =$F$3 -> 0.010050579 | C601: -17.190323 | D601: 0
A602: -17.0895 | B602: =$F$3 -> 0.010050579 | C602: -17.190323 | D602: =$F$3 -> 0.010050579
A603: -17.0895 | B603: 0 | C603: 1.7140598 | D603: =$F$3 -> 0.010050579
A604: -16.988676 | B604: 0 | C604: 1.7140598 | D604: 0
A605: -16.988676 | B605: =$F$3 -> 0.010050579 | C605: 1.7140598 | D605: =$F$4 -> 0.013224447
A606: -16.887853 | B606: =$F$3 -> 0.010050579 | C606: 20.618443 | D606: =$F$4 -> 0.013224447
A607: -16.887853 | B607: 0 | C607: 20.618443 | D607: 0
A608: -16.787029 | B608: 0 | C608: 20.618443 | D608: =$F$5 -> 0.012166491
A609: -16.787029 | B609: =$F$3 -> 0.010050579 | C609: 39.522825 | D609: =$F$5 -> 0.012166491
A610: -16.686206 | B610: =$F$3 -> 0.010050579 | C610: 39.522825 | D610: 0
A611: -16.686206 | B611: 0 | C611: 39.522825 | D611: =$F$6 -> 0.0095216016
A612: -16.585383 | B612: 0 | C612: 58.427208 | D612: =$F$6 -> 0.0095216016
A613: -16.585383 | B613: =$F$3 -> 0.010050579 | C613: 58.427208 | D613: 0
A614: -16.484559 | B614: =$F$3 -> 0.010050579 | C614: 58.427208 | D614: =$F$7 -> 0.0037028451
A615: -16.484559 | B615: 0 | C615: 77.331591 | D615: =$F$7 -> 0.0037028451
A616: -16.383736 | B616: 0 | C616: 77.331591 | D616: 0
A617: -16.383736 | B617: =$F$3 -> 0.010050579 | C617: 77.331591 | D617: =$F$8 -> 0.0037028451
A618: -16.282913 | B618: =$F$3 -> 0.010050579 | C618: 96.235973 | D618: =$F$8 -> 0.0037028451
A619: -16.282913 | B619: 0 | C619: 96.235973 | D619: 0
A620: -16.182089 | B620: 0 | C620: 96.235973 | D620: =$F$9 -> 0
A621: -16.182089 | B621: =$F$3 -> 0.010050579 | C621: 115.14036 | D621: =$F$9 -> 0
A622: -16.081266 | B622: =$F$3 -> 0.010050579 | C622: 115.14036 | D622: 0
A623: -16.081266 | B623: 0 | C623: 115.14036 | D623: =$F$10 -> 0.00052897786
A624: -15.980442 | B624: 0 | C624: 134.04474 | D624: =$F$10 -> 0.00052897786
A625: -15.980442 | B625: =$F$3 -> 0.010050579 | C625: 134.04474 | D625: 0
A626: -15.879619 | B626: =$F$3 -> 0.010050579
A627: -15.879619 | B627: 0
A628: -15.778796 | B628: 0
A629: -15.778796 | B629: =$F$3 -> 0.010050579
A630: -15.677972 | B630: =$F$3 -> 0.010050579
A631: -15.677972 | B631: 0
A632: -15.577149 | B632: 0
A633: -15.577149 | B633: =$F$3 -> 0.010050579
A634: -15.476326 | B634: =$F$3 -> 0.010050579
A635: -15.476326 | B635: 0
A636: -15.375502 | B636: 0
A637: -15.375502 | B637: =$F$3 -> 0.010050579
A638: -15.274679 | B638: =$F$3 -> 0.010050579
A639: -15.274679 | B639: 0
A640: -15.173855 | B640: 0
A641: -15.173855 | B641: =$F$3 -> 0.010050579
A642: -15.073032 | B642: =$F$3 -> 0.010050579
A643: -15.073032 | B643: 0
A644: -14.972209 | B644: 0
A645: -14.972209 | B645: =$F$3 -> 0.010050579
A646: -14.871385 | B646: =$F$3 -> 0.010050579
A647: -14.871385 | B647: 0
A648: -14.770562 | B648: 0
A649: -14.770562 | B649: =$F$3 -> 0.010050579
A650: -14.669739 | B650: =$F$3 -> 0.010050579
A651: -14.669739 | B651: 0
A652: -14.568915 | B652: 0
A653: -14.568915 | B653: =$F$3 -> 0.010050579
A654: -14.468092 | B654: =$F$3 -> 0.010050579
A655: -14.468092 | B655: 0
A656: -14.367268 | B656: 0
A657: -14.367268 | B657: =$F$3 -> 0.010050579
A658: -14.266445 | B658: =$F$3 -> 0.010050579
A659: -14.266445 | B659: 0
A660: -14.165622 | B660: 0
A661: -14.165622 | B661: =$F$3 -> 0.010050579
A662: -14.064798 | B662: =$F$3 -> 0.010050579
A663: -14.064798 | B663: 0
A664: -13.963975 | B664: 0
A665: -13.963975 | B665: =$F$3 -> 0.010050579
A666: -13.863152 | B666: =$F$3 -> 0.010050579
A667: -13.863152 | B667: 0
A668: -13.762328 | B668: 0
A669: -13.762328 | B669: =$F$3 -> 0.010050579
A670: -13.661505 | B670: =$F$3 -> 0.010050579
A671: -13.661505 | B671: 0
A672: -13.560681 | B672: 0
A673: -13.560681 | B673: =$F$3 -> 0.010050579
A674: -13.459858 | B674: =$F$3 -> 0.010050579
A675: -13.459858 | B675: 0
A676: -13.359035 | B676: 0
A677: -13.359035 | B677: =$F$3 -> 0.010050579
A678: -13.258211 | B678: =$F$3 -> 0.010050579
A679: -13.258211 | B679: 0
A680: -13.157388 | B680: 0
A681: -13.157388 | B681: =$F$3 -> 0.010050579
A682: -13.056565 | B682: =$F$3 -> 0.010050579
A683: -13.056565 | B683: 0
A684: -12.955741 | B684: 0
A685: -12.955741 | B685: =$F$3 -> 0.010050579
A686: -12.854918 | B686: =$F$3 -> 0.010050579
A687: -12.854918 | B687: 0
A688: -12.754094 | B688: 0
A689: -12.754094 | B689: =$F$3 -> 0.010050579
...

Sheet RiskRGInventoryR30C2
A1: X-Delimiters | E1: Series 1
E2: 26.522972 | F2: 0
A3: -14.082334 | B3: 0 | E3: 1 | F3: 0.0060750312
A4: 77.428574 | B4: 0 | E4: 2 | F4: 0.012825066
E5: 3 | F5: 0.012825066
E6: 4 | F6: 0.011475059
E7: 5 | F7: 0.0094500485
E8: 6 | F8: 0.0074250381
E9: 7 | F9: 0.0047250243
E10: 8 | F10: 0.0027000139
A600: -24.21249 | B600: 0
A601: -24.21249 | B601: =$F$3 -> 0.0060750312 | C601: -24.21249 | D601: 0
A602: -24.133478 | B602: =$F$3 -> 0.0060750312 | C602: -24.21249 | D602: =$F$3 -> 0.0060750312
A603: -24.133478 | B603: 0 | C603: -9.3977513 | D603: =$F$3 -> 0.0060750312
A604: -24.054466 | B604: 0 | C604: -9.3977513 | D604: 0
A605: -24.054466 | B605: =$F$3 -> 0.0060750312 | C605: -9.3977513 | D605: =$F$4 -> 0.012825066
A606: -23.975454 | B606: =$F$3 -> 0.0060750312 | C606: 5.4169874 | D606: =$F$4 -> 0.012825066
A607: -23.975454 | B607: 0 | C607: 5.4169874 | D607: 0
A608: -23.896442 | B608: 0 | C608: 5.4169874 | D608: =$F$5 -> 0.012825066
A609: -23.896442 | B609: =$F$3 -> 0.0060750312 | C609: 20.231726 | D609: =$F$5 -> 0.012825066
A610: -23.81743 | B610: =$F$3 -> 0.0060750312 | C610: 20.231726 | D610: 0
A611: -23.81743 | B611: 0 | C611: 20.231726 | D611: =$F$6 -> 0.011475059
A612: -23.738418 | B612: 0 | C612: 35.046465 | D612: =$F$6 -> 0.011475059
A613: -23.738418 | B613: =$F$3 -> 0.0060750312 | C613: 35.046465 | D613: 0
A614: -23.659407 | B614: =$F$3 -> 0.0060750312 | C614: 35.046465 | D614: =$F$7 -> 0.0094500485
A615: -23.659407 | B615: 0 | C615: 49.861204 | D615: =$F$7 -> 0.0094500485
A616: -23.580395 | B616: 0 | C616: 49.861204 | D616: 0
A617: -23.580395 | B617: =$F$3 -> 0.0060750312 | C617: 49.861204 | D617: =$F$8 -> 0.0074250381
A618: -23.501383 | B618: =$F$3 -> 0.0060750312 | C618: 64.675942 | D618: =$F$8 -> 0.0074250381
A619: -23.501383 | B619: 0 | C619: 64.675942 | D619: 0
A620: -23.422371 | B620: 0 | C620: 64.675942 | D620: =$F$9 -> 0.0047250243
A621: -23.422371 | B621: =$F$3 -> 0.0060750312 | C621: 79.490681 | D621: =$F$9 -> 0.0047250243
A622: -23.343359 | B622: =$F$3 -> 0.0060750312 | C622: 79.490681 | D622: 0
A623: -23.343359 | B623: 0 | C623: 79.490681 | D623: =$F$10 -> 0.0027000139
A624: -23.264347 | B624: 0 | C624: 94.30542 | D624: =$F$10 -> 0.0027000139
A625: -23.264347 | B625: =$F$3 -> 0.0060750312 | C625: 94.30542 | D625: 0
A626: -23.185335 | B626: =$F$3 -> 0.0060750312
A627: -23.185335 | B627: 0
A628: -23.106323 | B628: 0
A629: -23.106323 | B629: =$F$3 -> 0.0060750312
A630: -23.027311 | B630: =$F$3 -> 0.0060750312
A631: -23.027311 | B631: 0
A632: -22.948299 | B632: 0
A633: -22.948299 | B633: =$F$3 -> 0.0060750312
A634: -22.869287 | B634: =$F$3 -> 0.0060750312
A635: -22.869287 | B635: 0
A636: -22.790275 | B636: 0
A637: -22.790275 | B637: =$F$3 -> 0.0060750312
A638: -22.711263 | B638: =$F$3 -> 0.0060750312
A639: -22.711263 | B639: 0
A640: -22.632251 | B640: 0
A641: -22.632251 | B641: =$F$3 -> 0.0060750312
A642: -22.553239 | B642: =$F$3 -> 0.0060750312
A643: -22.553239 | B643: 0
A644: -22.474227 | B644: 0
A645: -22.474227 | B645: =$F$3 -> 0.0060750312
A646: -22.395215 | B646: =$F$3 -> 0.0060750312
A647: -22.395215 | B647: 0
A648: -22.316204 | B648: 0
A649: -22.316204 | B649: =$F$3 -> 0.0060750312
A650: -22.237192 | B650: =$F$3 -> 0.0060750312
A651: -22.237192 | B651: 0
A652: -22.15818 | B652: 0
A653: -22.15818 | B653: =$F$3 -> 0.0060750312
A654: -22.079168 | B654: =$F$3 -> 0.0060750312
A655: -22.079168 | B655: 0
A656: -22.000156 | B656: 0
A657: -22.000156 | B657: =$F$3 -> 0.0060750312
A658: -21.921144 | B658: =$F$3 -> 0.0060750312
A659: -21.921144 | B659: 0
A660: -21.842132 | B660: 0
A661: -21.842132 | B661: =$F$3 -> 0.0060750312
A662: -21.76312 | B662: =$F$3 -> 0.0060750312
A663: -21.76312 | B663: 0
A664: -21.684108 | B664: 0
A665: -21.684108 | B665: =$F$3 -> 0.0060750312
A666: -21.605096 | B666: =$F$3 -> 0.0060750312
A667: -21.605096 | B667: 0
A668: -21.526084 | B668: 0
A669: -21.526084 | B669: =$F$3 -> 0.0060750312
A670: -21.447072 | B670: =$F$3 -> 0.0060750312
A671: -21.447072 | B671: 0
A672: -21.36806 | B672: 0
A673: -21.36806 | B673: =$F$3 -> 0.0060750312
A674: -21.289048 | B674: =$F$3 -> 0.0060750312
A675: -21.289048 | B675: 0
A676: -21.210036 | B676: 0
A677: -21.210036 | B677: =$F$3 -> 0.0060750312
A678: -21.131024 | B678: =$F$3 -> 0.0060750312
A679: -21.131024 | B679: 0
A680: -21.052012 | B680: 0
A681: -21.052012 | B681: =$F$3 -> 0.0060750312
A682: -20.973001 | B682: =$F$3 -> 0.0060750312
A683: -20.973001 | B683: 0
A684: -20.893989 | B684: 0
A685: -20.893989 | B685: =$F$3 -> 0.0060750312
A686: -20.814977 | B686: =$F$3 -> 0.0060750312
A687: -20.814977 | B687: 0
A688: -20.735965 | B688: 0
A689: -20.735965 | B689: =$F$3 -> 0.0060750312
...

Sheet RiskRGValueR30C2
A1: X-Delimiters | E1: Series 1
E2: 27.394045 | F2: 0
A3: -14.762085 | B3: 0 | E3: 1 | F3: 0.0067796249
A4: 77.918198 | B4: 0 | E4: 2 | F4: 0.012326591
E5: 3 | F5: 0.012326591
E6: 4 | F6: 0.010477602
E7: 5 | F7: 0.008012284
E8: 6 | F8: 0.0061632954
E9: 7 | F9: 0.0043143068
E10: 8 | F10: 0.0012326591
A600: -24.382936 | B600: 0
A601: -24.382936 | B601: =$F$3 -> 0.0067796249 | C601: -24.382936 | D601: 0
A602: -24.296403 | B602: =$F$3 -> 0.0067796249 | C602: -24.382936 | D602: =$F$3 -> 0.0067796249
A603: -24.296403 | B603: 0 | C603: -8.15785 | D603: =$F$3 -> 0.0067796249
A604: -24.209869 | B604: 0 | C604: -8.15785 | D604: 0
A605: -24.209869 | B605: =$F$3 -> 0.0067796249 | C605: -8.15785 | D605: =$F$4 -> 0.012326591
A606: -24.123335 | B606: =$F$3 -> 0.0067796249 | C606: 8.0672364 | D606: =$F$4 -> 0.012326591
A607: -24.123335 | B607: 0 | C607: 8.0672364 | D607: 0
A608: -24.036801 | B608: 0 | C608: 8.0672364 | D608: =$F$5 -> 0.012326591
A609: -24.036801 | B609: =$F$3 -> 0.0067796249 | C609: 24.292323 | D609: =$F$5 -> 0.012326591
A610: -23.950268 | B610: =$F$3 -> 0.0067796249 | C610: 24.292323 | D610: 0
A611: -23.950268 | B611: 0 | C611: 24.292323 | D611: =$F$6 -> 0.010477602
A612: -23.863734 | B612: 0 | C612: 40.517409 | D612: =$F$6 -> 0.010477602
A613: -23.863734 | B613: =$F$3 -> 0.0067796249 | C613: 40.517409 | D613: 0
A614: -23.7772 | B614: =$F$3 -> 0.0067796249 | C614: 40.517409 | D614: =$F$7 -> 0.008012284
A615: -23.7772 | B615: 0 | C615: 56.742496 | D615: =$F$7 -> 0.008012284
A616: -23.690666 | B616: 0 | C616: 56.742496 | D616: 0
A617: -23.690666 | B617: =$F$3 -> 0.0067796249 | C617: 56.742496 | D617: =$F$8 -> 0.0061632954
A618: -23.604132 | B618: =$F$3 -> 0.0067796249 | C618: 72.967582 | D618: =$F$8 -> 0.0061632954
A619: -23.604132 | B619: 0 | C619: 72.967582 | D619: 0
A620: -23.517599 | B620: 0 | C620: 72.967582 | D620: =$F$9 -> 0.0043143068
A621: -23.517599 | B621: =$F$3 -> 0.0067796249 | C621: 89.192669 | D621: =$F$9 -> 0.0043143068
A622: -23.431065 | B622: =$F$3 -> 0.0067796249 | C622: 89.192669 | D622: 0
A623: -23.431065 | B623: 0 | C623: 89.192669 | D623: =$F$10 -> 0.0012326591
A624: -23.344531 | B624: 0 | C624: 105.41776 | D624: =$F$10 -> 0.0012326591
A625: -23.344531 | B625: =$F$3 -> 0.0067796249 | C625: 105.41776 | D625: 0
A626: -23.257997 | B626: =$F$3 -> 0.0067796249
A627: -23.257997 | B627: 0
A628: -23.171463 | B628: 0
A629: -23.171463 | B629: =$F$3 -> 0.0067796249
A630: -23.08493 | B630: =$F$3 -> 0.0067796249
A631: -23.08493 | B631: 0
A632: -22.998396 | B632: 0
A633: -22.998396 | B633: =$F$3 -> 0.0067796249
A634: -22.911862 | B634: =$F$3 -> 0.0067796249
A635: -22.911862 | B635: 0
A636: -22.825328 | B636: 0
A637: -22.825328 | B637: =$F$3 -> 0.0067796249
A638: -22.738794 | B638: =$F$3 -> 0.0067796249
A639: -22.738794 | B639: 0
A640: -22.652261 | B640: 0
A641: -22.652261 | B641: =$F$3 -> 0.0067796249
A642: -22.565727 | B642: =$F$3 -> 0.0067796249
A643: -22.565727 | B643: 0
A644: -22.479193 | B644: 0
A645: -22.479193 | B645: =$F$3 -> 0.0067796249
A646: -22.392659 | B646: =$F$3 -> 0.0067796249
A647: -22.392659 | B647: 0
A648: -22.306125 | B648: 0
A649: -22.306125 | B649: =$F$3 -> 0.0067796249
A650: -22.219592 | B650: =$F$3 -> 0.0067796249
A651: -22.219592 | B651: 0
A652: -22.133058 | B652: 0
A653: -22.133058 | B653: =$F$3 -> 0.0067796249
A654: -22.046524 | B654: =$F$3 -> 0.0067796249
A655: -22.046524 | B655: 0
A656: -21.95999 | B656: 0
A657: -21.95999 | B657: =$F$3 -> 0.0067796249
A658: -21.873456 | B658: =$F$3 -> 0.0067796249
A659: -21.873456 | B659: 0
A660: -21.786923 | B660: 0
A661: -21.786923 | B661: =$F$3 -> 0.0067796249
A662: -21.700389 | B662: =$F$3 -> 0.0067796249
A663: -21.700389 | B663: 0
A664: -21.613855 | B664: 0
A665: -21.613855 | B665: =$F$3 -> 0.0067796249
A666: -21.527321 | B666: =$F$3 -> 0.0067796249
A667: -21.527321 | B667: 0
A668: -21.440787 | B668: 0
A669: -21.440787 | B669: =$F$3 -> 0.0067796249
A670: -21.354254 | B670: =$F$3 -> 0.0067796249
A671: -21.354254 | B671: 0
A672: -21.26772 | B672: 0
A673: -21.26772 | B673: =$F$3 -> 0.0067796249
A674: -21.181186 | B674: =$F$3 -> 0.0067796249
A675: -21.181186 | B675: 0
A676: -21.094652 | B676: 0
A677: -21.094652 | B677: =$F$3 -> 0.0067796249
A678: -21.008118 | B678: =$F$3 -> 0.0067796249
A679: -21.008118 | B679: 0
A680: -20.921585 | B680: 0
A681: -20.921585 | B681: =$F$3 -> 0.0067796249
A682: -20.835051 | B682: =$F$3 -> 0.0067796249
A683: -20.835051 | B683: 0
A684: -20.748517 | B684: 0
A685: -20.748517 | B685: =$F$3 -> 0.0067796249
A686: -20.661983 | B686: =$F$3 -> 0.0067796249
A687: -20.661983 | B687: 0
A688: -20.57545 | B688: 0
A689: -20.57545 | B689: =$F$3 -> 0.0067796249
...

Sheet RiskRGValueR32C2
A1: X-Delimiters | E1: Series 1
E2: 5.1347556 | F2: 0
A3: -23.28002 | B3: 0 | E3: 1 | F3: 0.0062003897
A4: 33.296616 | B4: 0 | E4: 2 | F4: 0.0076031928
E5: 3 | F5: 0.012933845
E6: 4 | F6: 0.018488945
E7: 5 | F7: 0.022276513
E8: 6 | F8: 0.022781522
E9: 7 | F9: 0.019555075
E10: 8 | F10: 0.014224423
E11: 9 | F11: 0.0086973792
E12: 10 | F12: 0.004545082
E13: 11 | F13: 0.0019639243
E14: 12 | F14: 0.00072945761
E15: 13 | F15: 0.00019639243
E16: 14 | F16: 8.4168186e-05
A600: -31.415237 | B600: 0
A601: -31.415237 | B601: =$F$3 -> 0.0062003897 | C601: -31.415237 | D601: 0
A602: -31.348704 | B602: =$F$3 -> 0.0062003897 | C602: -31.415237 | D602: =$F$3 -> 0.0062003897
A603: -31.348704 | B603: 0 | C603: -24.286653 | D603: =$F$3 -> 0.0062003897
A604: -31.282171 | B604: 0 | C604: -24.286653 | D604: 0
A605: -31.282171 | B605: =$F$3 -> 0.0062003897 | C605: -24.286653 | D605: =$F$4 -> 0.0076031928
A606: -31.215637 | B606: =$F$3 -> 0.0062003897 | C606: -17.158069 | D606: =$F$4 -> 0.0076031928
A607: -31.215637 | B607: 0 | C607: -17.158069 | D607: 0
A608: -31.149104 | B608: 0 | C608: -17.158069 | D608: =$F$5 -> 0.012933845
A609: -31.149104 | B609: =$F$3 -> 0.0062003897 | C609: -10.029485 | D609: =$F$5 -> 0.012933845
A610: -31.08257 | B610: =$F$3 -> 0.0062003897 | C610: -10.029485 | D610: 0
A611: -31.08257 | B611: 0 | C611: -10.029485 | D611: =$F$6 -> 0.018488945
A612: -31.016037 | B612: 0 | C612: -2.9009007 | D612: =$F$6 -> 0.018488945
A613: -31.016037 | B613: =$F$3 -> 0.0062003897 | C613: -2.9009007 | D613: 0
A614: -30.949503 | B614: =$F$3 -> 0.0062003897 | C614: -2.9009007 | D614: =$F$7 -> 0.022276513
A615: -30.949503 | B615: 0 | C615: 4.2276835 | D615: =$F$7 -> 0.022276513
A616: -30.88297 | B616: 0 | C616: 4.2276835 | D616: 0
A617: -30.88297 | B617: =$F$3 -> 0.0062003897 | C617: 4.2276835 | D617: =$F$8 -> 0.022781522
A618: -30.816436 | B618: =$F$3 -> 0.0062003897 | C618: 11.356268 | D618: =$F$8 -> 0.022781522
A619: -30.816436 | B619: 0 | C619: 11.356268 | D619: 0
A620: -30.749903 | B620: 0 | C620: 11.356268 | D620: =$F$9 -> 0.019555075
A621: -30.749903 | B621: =$F$3 -> 0.0062003897 | C621: 18.484852 | D621: =$F$9 -> 0.019555075
A622: -30.683369 | B622: =$F$3 -> 0.0062003897 | C622: 18.484852 | D622: 0
A623: -30.683369 | B623: 0 | C623: 18.484852 | D623: =$F$10 -> 0.014224423
A624: -30.616836 | B624: 0 | C624: 25.613436 | D624: =$F$10 -> 0.014224423
A625: -30.616836 | B625: =$F$3 -> 0.0062003897 | C625: 25.613436 | D625: 0
A626: -30.550303 | B626: =$F$3 -> 0.0062003897 | C626: 25.613436 | D626: =$F$11 -> 0.0086973792
A627: -30.550303 | B627: 0 | C627: 32.74202 | D627: =$F$11 -> 0.0086973792
A628: -30.483769 | B628: 0 | C628: 32.74202 | D628: 0
A629: -30.483769 | B629: =$F$3 -> 0.0062003897 | C629: 32.74202 | D629: =$F$12 -> 0.004545082
A630: -30.417236 | B630: =$F$3 -> 0.0062003897 | C630: 39.870604 | D630: =$F$12 -> 0.004545082
A631: -30.417236 | B631: 0 | C631: 39.870604 | D631: 0
A632: -30.350702 | B632: 0 | C632: 39.870604 | D632: =$F$13 -> 0.0019639243
A633: -30.350702 | B633: =$F$3 -> 0.0062003897 | C633: 46.999189 | D633: =$F$13 -> 0.0019639243
A634: -30.284169 | B634: =$F$3 -> 0.0062003897 | C634: 46.999189 | D634: 0
A635: -30.284169 | B635: 0 | C635: 46.999189 | D635: =$F$14 -> 0.00072945761
A636: -30.217635 | B636: 0 | C636: 54.127773 | D636: =$F$14 -> 0.00072945761
A637: -30.217635 | B637: =$F$3 -> 0.0062003897 | C637: 54.127773 | D637: 0
A638: -30.151102 | B638: =$F$3 -> 0.0062003897 | C638: 54.127773 | D638: =$F$15 -> 0.00019639243
A639: -30.151102 | B639: 0 | C639: 61.256357 | D639: =$F$15 -> 0.00019639243
A640: -30.084568 | B640: 0 | C640: 61.256357 | D640: 0
A641: -30.084568 | B641: =$F$3 -> 0.0062003897 | C641: 61.256357 | D641: =$F$16 -> 8.4168186e-05
A642: -30.018035 | B642: =$F$3 -> 0.0062003897 | C642: 68.384941 | D642: =$F$16 -> 8.4168186e-05
A643: -30.018035 | B643: 0 | C643: 68.384941 | D643: 0
A644: -29.951501 | B644: 0
A645: -29.951501 | B645: =$F$3 -> 0.0062003897
A646: -29.884968 | B646: =$F$3 -> 0.0062003897
A647: -29.884968 | B647: 0
A648: -29.818435 | B648: 0
A649: -29.818435 | B649: =$F$3 -> 0.0062003897
A650: -29.751901 | B650: =$F$3 -> 0.0062003897
A651: -29.751901 | B651: 0
A652: -29.685368 | B652: 0
A653: -29.685368 | B653: =$F$3 -> 0.0062003897
A654: -29.618834 | B654: =$F$3 -> 0.0062003897
A655: -29.618834 | B655: 0
A656: -29.552301 | B656: 0
A657: -29.552301 | B657: =$F$3 -> 0.0062003897
A658: -29.485767 | B658: =$F$3 -> 0.0062003897
A659: -29.485767 | B659: 0
A660: -29.419234 | B660: 0
A661: -29.419234 | B661: =$F$3 -> 0.0062003897
A662: -29.3527 | B662: =$F$3 -> 0.0062003897
A663: -29.3527 | B663: 0
A664: -29.286167 | B664: 0
A665: -29.286167 | B665: =$F$3 -> 0.0062003897
A666: -29.219633 | B666: =$F$3 -> 0.0062003897
A667: -29.219633 | B667: 0
A668: -29.1531 | B668: 0
A669: -29.1531 | B669: =$F$3 -> 0.0062003897
A670: -29.086567 | B670: =$F$3 -> 0.0062003897
A671: -29.086567 | B671: 0
A672: -29.020033 | B672: 0
A673: -29.020033 | B673: =$F$3 -> 0.0062003897
A674: -28.9535 | B674: =$F$3 -> 0.0062003897
A675: -28.9535 | B675: 0
A676: -28.886966 | B676: 0
A677: -28.886966 | B677: =$F$3 -> 0.0062003897
A678: -28.820433 | B678: =$F$3 -> 0.0062003897
A679: -28.820433 | B679: 0
A680: -28.753899 | B680: 0
A681: -28.753899 | B681: =$F$3 -> 0.0062003897
A682: -28.687366 | B682: =$F$3 -> 0.0062003897
A683: -28.687366 | B683: 0
...

Sheet RiskRGAbandonR33C2
A1: X-Delimiters | E1: Series 1
E2: 10.902644 | F2: 0
A3: -10.419797 | B3: 0 | E3: 1 | F3: 0.016937377
A4: 45.513573 | B4: 0 | E4: 2 | F4: 0.029898845
E5: 3 | F5: 0.016168702
E6: 4 | F6: 0.017361475
E7: 5 | F7: 0.014710868
E8: 6 | F8: 0.012775925
E9: 7 | F9: 0.010363873
E10: 8 | F10: 0.006626517
E11: 9 | F11: 0.0038168738
E12: 10 | F12: 0.0021734976
E13: 11 | F13: 0.0010072306
E14: 12 | F14: 0.00045060316
E15: 13 | F15: 0.00013253034
E16: 14 | F16: 0.00010602427
A600: -16.281322 | B600: 0
A601: -16.281322 | B601: =$F$3 -> 0.016937377 | C601: -16.281322 | D601: 0
A602: -16.210898 | B602: =$F$3 -> 0.016937377 | C602: -16.281322 | D602: =$F$3 -> 0.016937377
A603: -16.210898 | B603: 0 | C603: -8.7358804 | D603: =$F$3 -> 0.016937377
A604: -16.140474 | B604: 0 | C604: -8.7358804 | D604: 0
A605: -16.140474 | B605: =$F$3 -> 0.016937377 | C605: -8.7358804 | D605: =$F$4 -> 0.029898845
A606: -16.07005 | B606: =$F$3 -> 0.016937377 | C606: -1.1904384 | D606: =$F$4 -> 0.029898845
A607: -16.07005 | B607: 0 | C607: -1.1904384 | D607: 0
A608: -15.999626 | B608: 0 | C608: -1.1904384 | D608: =$F$5 -> 0.016168702
A609: -15.999626 | B609: =$F$3 -> 0.016937377 | C609: 6.3550036 | D609: =$F$5 -> 0.016168702
A610: -15.929202 | B610: =$F$3 -> 0.016937377 | C610: 6.3550036 | D610: 0
A611: -15.929202 | B611: 0 | C611: 6.3550036 | D611: =$F$6 -> 0.017361475
A612: -15.858778 | B612: 0 | C612: 13.900446 | D612: =$F$6 -> 0.017361475
A613: -15.858778 | B613: =$F$3 -> 0.016937377 | C613: 13.900446 | D613: 0
A614: -15.788354 | B614: =$F$3 -> 0.016937377 | C614: 13.900446 | D614: =$F$7 -> 0.014710868
A615: -15.788354 | B615: 0 | C615: 21.445888 | D615: =$F$7 -> 0.014710868
A616: -15.717929 | B616: 0 | C616: 21.445888 | D616: 0
A617: -15.717929 | B617: =$F$3 -> 0.016937377 | C617: 21.445888 | D617: =$F$8 -> 0.012775925
A618: -15.647505 | B618: =$F$3 -> 0.016937377 | C618: 28.99133 | D618: =$F$8 -> 0.012775925
A619: -15.647505 | B619: 0 | C619: 28.99133 | D619: 0
A620: -15.577081 | B620: 0 | C620: 28.99133 | D620: =$F$9 -> 0.010363873
A621: -15.577081 | B621: =$F$3 -> 0.016937377 | C621: 36.536772 | D621: =$F$9 -> 0.010363873
A622: -15.506657 | B622: =$F$3 -> 0.016937377 | C622: 36.536772 | D622: 0
A623: -15.506657 | B623: 0 | C623: 36.536772 | D623: =$F$10 -> 0.006626517
A624: -15.436233 | B624: 0 | C624: 44.082214 | D624: =$F$10 -> 0.006626517
A625: -15.436233 | B625: =$F$3 -> 0.016937377 | C625: 44.082214 | D625: 0
A626: -15.365809 | B626: =$F$3 -> 0.016937377 | C626: 44.082214 | D626: =$F$11 -> 0.0038168738
A627: -15.365809 | B627: 0 | C627: 51.627656 | D627: =$F$11 -> 0.0038168738
A628: -15.295385 | B628: 0 | C628: 51.627656 | D628: 0
A629: -15.295385 | B629: =$F$3 -> 0.016937377 | C629: 51.627656 | D629: =$F$12 -> 0.0021734976
A630: -15.224961 | B630: =$F$3 -> 0.016937377 | C630: 59.173098 | D630: =$F$12 -> 0.0021734976
A631: -15.224961 | B631: 0 | C631: 59.173098 | D631: 0
A632: -15.154536 | B632: 0 | C632: 59.173098 | D632: =$F$13 -> 0.0010072306
A633: -15.154536 | B633: =$F$3 -> 0.016937377 | C633: 66.71854 | D633: =$F$13 -> 0.0010072306
A634: -15.084112 | B634: =$F$3 -> 0.016937377 | C634: 66.71854 | D634: 0
A635: -15.084112 | B635: 0 | C635: 66.71854 | D635: =$F$14 -> 0.00045060316
A636: -15.013688 | B636: 0 | C636: 74.263982 | D636: =$F$14 -> 0.00045060316
A637: -15.013688 | B637: =$F$3 -> 0.016937377 | C637: 74.263982 | D637: 0
A638: -14.943264 | B638: =$F$3 -> 0.016937377 | C638: 74.263982 | D638: =$F$15 -> 0.00013253034
A639: -14.943264 | B639: 0 | C639: 81.809424 | D639: =$F$15 -> 0.00013253034
A640: -14.87284 | B640: 0 | C640: 81.809424 | D640: 0
A641: -14.87284 | B641: =$F$3 -> 0.016937377 | C641: 81.809424 | D641: =$F$16 -> 0.00010602427
A642: -14.802416 | B642: =$F$3 -> 0.016937377 | C642: 89.354866 | D642: =$F$16 -> 0.00010602427
A643: -14.802416 | B643: 0 | C643: 89.354866 | D643: 0
A644: -14.731992 | B644: 0
A645: -14.731992 | B645: =$F$3 -> 0.016937377
A646: -14.661568 | B646: =$F$3 -> 0.016937377
A647: -14.661568 | B647: 0
A648: -14.591143 | B648: 0
A649: -14.591143 | B649: =$F$3 -> 0.016937377
A650: -14.520719 | B650: =$F$3 -> 0.016937377
A651: -14.520719 | B651: 0
A652: -14.450295 | B652: 0
A653: -14.450295 | B653: =$F$3 -> 0.016937377
A654: -14.379871 | B654: =$F$3 -> 0.016937377
A655: -14.379871 | B655: 0
A656: -14.309447 | B656: 0
A657: -14.309447 | B657: =$F$3 -> 0.016937377
A658: -14.239023 | B658: =$F$3 -> 0.016937377
A659: -14.239023 | B659: 0
A660: -14.168599 | B660: 0
A661: -14.168599 | B661: =$F$3 -> 0.016937377
A662: -14.098175 | B662: =$F$3 -> 0.016937377
A663: -14.098175 | B663: 0
A664: -14.02775 | B664: 0
A665: -14.02775 | B665: =$F$3 -> 0.016937377
A666: -13.957326 | B666: =$F$3 -> 0.016937377
A667: -13.957326 | B667: 0
A668: -13.886902 | B668: 0
A669: -13.886902 | B669: =$F$3 -> 0.016937377
A670: -13.816478 | B670: =$F$3 -> 0.016937377
A671: -13.816478 | B671: 0
A672: -13.746054 | B672: 0
A673: -13.746054 | B673: =$F$3 -> 0.016937377
A674: -13.67563 | B674: =$F$3 -> 0.016937377
A675: -13.67563 | B675: 0
A676: -13.605206 | B676: 0
A677: -13.605206 | B677: =$F$3 -> 0.016937377
A678: -13.534782 | B678: =$F$3 -> 0.016937377
A679: -13.534782 | B679: 0
A680: -13.464357 | B680: 0
A681: -13.464357 | B681: =$F$3 -> 0.016937377
A682: -13.393933 | B682: =$F$3 -> 0.016937377
A683: -13.393933 | B683: 0
...

Sheet RiskRGAbandonR32C2
A1: X-Delimiters | E1: Series 1
E2: 12.397065 | F2: 0
A3: -9.3942757 | B3: 0 | E3: 1 | F3: 0.025590669
A4: 49.082291 | B4: 0 | E4: 2 | F4: 0.019357044
E5: 3 | F5: 0.016294913
E6: 4 | F6: 0.014873209
E7: 5 | F7: 0.011701716
E8: 6 | F8: 0.011045545
E9: 7 | F9: 0.0047025588
E10: 8 | F10: 0.003937026
E11: 9 | F11: 0.0012029802
E12: 10 | F12: 0.00021872367
E13: 11 | F13: 0.00043744733
A600: -15.192409 | B600: 0
A601: -15.192409 | B601: =$F$3 -> 0.025590669 | C601: -15.192409 | D601: 0
A602: -15.125353 | B602: =$F$3 -> 0.025590669 | C602: -15.192409 | D602: =$F$3 -> 0.025590669
A603: -15.125353 | B603: 0 | C603: -6.0484506 | D603: =$F$3 -> 0.025590669
A604: -15.058297 | B604: 0 | C604: -6.0484506 | D604: 0
A605: -15.058297 | B605: =$F$3 -> 0.025590669 | C605: -6.0484506 | D605: =$F$4 -> 0.019357044
A606: -14.991241 | B606: =$F$3 -> 0.025590669 | C606: 3.0955073 | D606: =$F$4 -> 0.019357044
A607: -14.991241 | B607: 0 | C607: 3.0955073 | D607: 0
A608: -14.924186 | B608: 0 | C608: 3.0955073 | D608: =$F$5 -> 0.016294913
A609: -14.924186 | B609: =$F$3 -> 0.025590669 | C609: 12.239465 | D609: =$F$5 -> 0.016294913
A610: -14.85713 | B610: =$F$3 -> 0.025590669 | C610: 12.239465 | D610: 0
A611: -14.85713 | B611: 0 | C611: 12.239465 | D611: =$F$6 -> 0.014873209
A612: -14.790074 | B612: 0 | C612: 21.383423 | D612: =$F$6 -> 0.014873209
A613: -14.790074 | B613: =$F$3 -> 0.025590669 | C613: 21.383423 | D613: 0
A614: -14.723019 | B614: =$F$3 -> 0.025590669 | C614: 21.383423 | D614: =$F$7 -> 0.011701716
A615: -14.723019 | B615: 0 | C615: 30.527381 | D615: =$F$7 -> 0.011701716
A616: -14.655963 | B616: 0 | C616: 30.527381 | D616: 0
A617: -14.655963 | B617: =$F$3 -> 0.025590669 | C617: 30.527381 | D617: =$F$8 -> 0.011045545
A618: -14.588907 | B618: =$F$3 -> 0.025590669 | C618: 39.671339 | D618: =$F$8 -> 0.011045545
A619: -14.588907 | B619: 0 | C619: 39.671339 | D619: 0
A620: -14.521852 | B620: 0 | C620: 39.671339 | D620: =$F$9 -> 0.0047025588
A621: -14.521852 | B621: =$F$3 -> 0.025590669 | C621: 48.815297 | D621: =$F$9 -> 0.0047025588
A622: -14.454796 | B622: =$F$3 -> 0.025590669 | C622: 48.815297 | D622: 0
A623: -14.454796 | B623: 0 | C623: 48.815297 | D623: =$F$10 -> 0.003937026
A624: -14.38774 | B624: 0 | C624: 57.959255 | D624: =$F$10 -> 0.003937026
A625: -14.38774 | B625: =$F$3 -> 0.025590669 | C625: 57.959255 | D625: 0
A626: -14.320685 | B626: =$F$3 -> 0.025590669 | C626: 57.959255 | D626: =$F$11 -> 0.0012029802
A627: -14.320685 | B627: 0 | C627: 67.103213 | D627: =$F$11 -> 0.0012029802
A628: -14.253629 | B628: 0 | C628: 67.103213 | D628: 0
A629: -14.253629 | B629: =$F$3 -> 0.025590669 | C629: 67.103213 | D629: =$F$12 -> 0.00021872367
A630: -14.186573 | B630: =$F$3 -> 0.025590669 | C630: 76.247171 | D630: =$F$12 -> 0.00021872367
A631: -14.186573 | B631: 0 | C631: 76.247171 | D631: 0
A632: -14.119517 | B632: 0 | C632: 76.247171 | D632: =$F$13 -> 0.00043744733
A633: -14.119517 | B633: =$F$3 -> 0.025590669 | C633: 85.391129 | D633: =$F$13 -> 0.00043744733
A634: -14.052462 | B634: =$F$3 -> 0.025590669 | C634: 85.391129 | D634: 0
A635: -14.052462 | B635: 0
A636: -13.985406 | B636: 0
A637: -13.985406 | B637: =$F$3 -> 0.025590669
A638: -13.91835 | B638: =$F$3 -> 0.025590669
A639: -13.91835 | B639: 0
A640: -13.851295 | B640: 0
A641: -13.851295 | B641: =$F$3 -> 0.025590669
A642: -13.784239 | B642: =$F$3 -> 0.025590669
A643: -13.784239 | B643: 0
A644: -13.717183 | B644: 0
A645: -13.717183 | B645: =$F$3 -> 0.025590669
A646: -13.650128 | B646: =$F$3 -> 0.025590669
A647: -13.650128 | B647: 0
A648: -13.583072 | B648: 0
A649: -13.583072 | B649: =$F$3 -> 0.025590669
A650: -13.516016 | B650: =$F$3 -> 0.025590669
A651: -13.516016 | B651: 0
A652: -13.448961 | B652: 0
A653: -13.448961 | B653: =$F$3 -> 0.025590669
A654: -13.381905 | B654: =$F$3 -> 0.025590669
A655: -13.381905 | B655: 0
A656: -13.314849 | B656: 0
A657: -13.314849 | B657: =$F$3 -> 0.025590669
A658: -13.247794 | B658: =$F$3 -> 0.025590669
A659: -13.247794 | B659: 0
A660: -13.180738 | B660: 0
A661: -13.180738 | B661: =$F$3 -> 0.025590669
A662: -13.113682 | B662: =$F$3 -> 0.025590669
A663: -13.113682 | B663: 0
A664: -13.046626 | B664: 0
A665: -13.046626 | B665: =$F$3 -> 0.025590669
A666: -12.979571 | B666: =$F$3 -> 0.025590669
A667: -12.979571 | B667: 0
A668: -12.912515 | B668: 0
A669: -12.912515 | B669: =$F$3 -> 0.025590669
A670: -12.845459 | B670: =$F$3 -> 0.025590669
A671: -12.845459 | B671: 0
A672: -12.778404 | B672: 0
A673: -12.778404 | B673: =$F$3 -> 0.025590669
A674: -12.711348 | B674: =$F$3 -> 0.025590669
A675: -12.711348 | B675: 0
A676: -12.644292 | B676: 0
A677: -12.644292 | B677: =$F$3 -> 0.025590669
A678: -12.577237 | B678: =$F$3 -> 0.025590669
A679: -12.577237 | B679: 0
A680: -12.510181 | B680: 0
A681: -12.510181 | B681: =$F$3 -> 0.025590669
A682: -12.443125 | B682: =$F$3 -> 0.025590669
A683: -12.443125 | B683: 0
A684: -12.37607 | B684: 0
A685: -12.37607 | B685: =$F$3 -> 0.025590669
A686: -12.309014 | B686: =$F$3 -> 0.025590669
...

Sheet RiskRGValueR31C2
Z1: -28.163502
J2: Bin | K2: Height | Z2: 38.1269
J3: -24.66839 | K3: 12.710675 | Z3: 5.4178383
J4: -15.148833 | K4: 13.235909
J5: -5.6292752 | K5: 14.181331
J6: 3.8902824 | K6: 19.118535
J7: 13.40984 | K7: 17.647879
J8: 22.929398 | K8: 13.55105
J9: 32.448955 | K9: 8.6138457
J10: 41.968513 | K10: 3.5715945
J11: 51.48807 | K11: 1.2605628
J12: 61.007628 | K12: 0.84037519
J13: 70.527186 | K13: 0.31514069
A4001: -29.428169 | B4001: 0
A4002: -29.428169 | B4002: =$K$3 -> 12.710675
A4003: -19.908612 | B4003: =$K$3 -> 12.710675
A4004: -19.908612 | B4004: 0
A4005: -19.908612 | B4005: =$K$4 -> 13.235909
A4006: -10.389054 | B4006: =$K$4 -> 13.235909
A4007: -10.389054 | B4007: 0
A4008: -10.389054 | B4008: =$K$5 -> 14.181331
A4009: -0.86949643 | B4009: =$K$5 -> 14.181331
A4010: -0.86949643 | B4010: 0
A4011: -0.86949643 | B4011: =$K$6 -> 19.118535
A4012: 8.6500612 | B4012: =$K$6 -> 19.118535
A4013: 8.6500612 | B4013: 0
A4014: 8.6500612 | B4014: =$K$7 -> 17.647879
A4015: 18.169619 | B4015: =$K$7 -> 17.647879
A4016: 18.169619 | B4016: 0
A4017: 18.169619 | B4017: =$K$8 -> 13.55105
A4018: 27.689176 | B4018: =$K$8 -> 13.55105
A4019: 27.689176 | B4019: 0
A4020: 27.689176 | B4020: =$K$9 -> 8.6138457
A4021: 37.208734 | B4021: =$K$9 -> 8.6138457
A4022: 37.208734 | B4022: 0
A4023: 37.208734 | B4023: =$K$10 -> 3.5715945
A4024: 46.728292 | B4024: =$K$10 -> 3.5715945
A4025: 46.728292 | B4025: 0
A4026: 46.728292 | B4026: =$K$11 -> 1.2605628
A4027: 56.247849 | B4027: =$K$11 -> 1.2605628
A4028: 56.247849 | B4028: 0
A4029: 56.247849 | B4029: =$K$12 -> 0.84037519
A4030: 65.767407 | B4030: =$K$12 -> 0.84037519
A4031: 65.767407 | B4031: 0
A4032: 65.767407 | B4032: =$K$13 -> 0.31514069
A4033: 75.286964 | B4033: =$K$13 -> 0.31514069
A4034: 75.286964 | B4034: 0
A5001: -29.428169 | B5001: 0
A5002: -29.428169 | B5002: =$K$3 -> 12.710675
A5003: -29.323454 | B5003: =$K$3 -> 12.710675
A5004: -29.323454 | B5004: 0
A5005: -29.218739 | B5005: 0
A5006: -29.218739 | B5006: =$K$3 -> 12.710675
A5007: -29.114024 | B5007: =$K$3 -> 12.710675
A5008: -29.114024 | B5008: 0
A5009: -29.009309 | B5009: 0
A5010: -29.009309 | B5010: =$K$3 -> 12.710675
A5011: -28.904594 | B5011: =$K$3 -> 12.710675
A5012: -28.904594 | B5012: 0
A5013: -28.799878 | B5013: 0
A5014: -28.799878 | B5014: =$K$3 -> 12.710675
A5015: -28.695163 | B5015: =$K$3 -> 12.710675
A5016: -28.695163 | B5016: 0
A5017: -28.590448 | B5017: 0
A5018: -28.590448 | B5018: =$K$3 -> 12.710675
A5019: -28.485733 | B5019: =$K$3 -> 12.710675
A5020: -28.485733 | B5020: 0
A5021: -28.381018 | B5021: 0
A5022: -28.381018 | B5022: =$K$3 -> 12.710675
A5023: -28.276303 | B5023: =$K$3 -> 12.710675
A5024: -28.276303 | B5024: 0
A5025: -28.171588 | B5025: 0
A5026: -28.171588 | B5026: =$K$3 -> 12.710675
A5027: -28.066873 | B5027: =$K$3 -> 12.710675
A5028: -28.066873 | B5028: 0
A5029: -27.962157 | B5029: 0
A5030: -27.962157 | B5030: =$K$3 -> 12.710675
A5031: -27.857442 | B5031: =$K$3 -> 12.710675
A5032: -27.857442 | B5032: 0
A5033: -27.752727 | B5033: 0
A5034: -27.752727 | B5034: =$K$3 -> 12.710675
A5035: -27.648012 | B5035: =$K$3 -> 12.710675
A5036: -27.648012 | B5036: 0
A5037: -27.543297 | B5037: 0
A5038: -27.543297 | B5038: =$K$3 -> 12.710675
A5039: -27.438582 | B5039: =$K$3 -> 12.710675
A5040: -27.438582 | B5040: 0
A5041: -27.333867 | B5041: 0
A5042: -27.333867 | B5042: =$K$3 -> 12.710675
A5043: -27.229151 | B5043: =$K$3 -> 12.710675
A5044: -27.229151 | B5044: 0
A5045: -27.124436 | B5045: 0
A5046: -27.124436 | B5046: =$K$3 -> 12.710675
A5047: -27.019721 | B5047: =$K$3 -> 12.710675
A5048: -27.019721 | B5048: 0
A5049: -26.915006 | B5049: 0
A5050: -26.915006 | B5050: =$K$3 -> 12.710675
A5051: -26.810291 | B5051: =$K$3 -> 12.710675
A5052: -26.810291 | B5052: 0
A5053: -26.705576 | B5053: 0
...

Sheet RiskRGAbandonR31C2
Z1: -7.1329808
J2: Bin | K2: Height | Z2: 40.747612
J3: -9.8645518 | K3: 34.216178 | Z3: 9.9840806
J4: -1.359803 | K4: 16.578973
J5: 7.1449458 | K5: 18.107531
J6: 15.649695 | K6: 17.16688
J7: 24.154443 | K7: 13.75702
J8: 32.659192 | K8: 9.6416722
J9: 41.163941 | K9: 3.9977665
J10: 49.66869 | K10: 2.1164646
J11: 58.173438 | K11: 1.1758137
J12: 66.678187 | K12: 0.58790684
J13: 75.182936 | K13: 0.23516274
A4001: -14.116926 | B4001: 0
A4002: -14.116926 | B4002: =$K$3 -> 34.216178
A4003: -5.6121774 | B4003: =$K$3 -> 34.216178
A4004: -5.6121774 | B4004: 0
A4005: -5.6121774 | B4005: =$K$4 -> 16.578973
A4006: 2.8925714 | B4006: =$K$4 -> 16.578973
A4007: 2.8925714 | B4007: 0
A4008: 2.8925714 | B4008: =$K$5 -> 18.107531
A4009: 11.39732 | B4009: =$K$5 -> 18.107531
A4010: 11.39732 | B4010: 0
A4011: 11.39732 | B4011: =$K$6 -> 17.16688
A4012: 19.902069 | B4012: =$K$6 -> 17.16688
A4013: 19.902069 | B4013: 0
A4014: 19.902069 | B4014: =$K$7 -> 13.75702
A4015: 28.406818 | B4015: =$K$7 -> 13.75702
A4016: 28.406818 | B4016: 0
A4017: 28.406818 | B4017: =$K$8 -> 9.6416722
A4018: 36.911566 | B4018: =$K$8 -> 9.6416722
A4019: 36.911566 | B4019: 0
A4020: 36.911566 | B4020: =$K$9 -> 3.9977665
A4021: 45.416315 | B4021: =$K$9 -> 3.9977665
A4022: 45.416315 | B4022: 0
A4023: 45.416315 | B4023: =$K$10 -> 2.1164646
A4024: 53.921064 | B4024: =$K$10 -> 2.1164646
A4025: 53.921064 | B4025: 0
A4026: 53.921064 | B4026: =$K$11 -> 1.1758137
A4027: 62.425813 | B4027: =$K$11 -> 1.1758137
A4028: 62.425813 | B4028: 0
A4029: 62.425813 | B4029: =$K$12 -> 0.58790684
A4030: 70.930562 | B4030: =$K$12 -> 0.58790684
A4031: 70.930562 | B4031: 0
A4032: 70.930562 | B4032: =$K$13 -> 0.23516274
A4033: 79.43531 | B4033: =$K$13 -> 0.23516274
A4034: 79.43531 | B4034: 0
A5001: -14.116926 | B5001: 0
A5002: -14.116926 | B5002: =$K$3 -> 34.216178
A5003: -14.023374 | B5003: =$K$3 -> 34.216178
A5004: -14.023374 | B5004: 0
A5005: -13.929822 | B5005: 0
A5006: -13.929822 | B5006: =$K$3 -> 34.216178
A5007: -13.836269 | B5007: =$K$3 -> 34.216178
A5008: -13.836269 | B5008: 0
A5009: -13.742717 | B5009: 0
A5010: -13.742717 | B5010: =$K$3 -> 34.216178
A5011: -13.649165 | B5011: =$K$3 -> 34.216178
A5012: -13.649165 | B5012: 0
A5013: -13.555613 | B5013: 0
A5014: -13.555613 | B5014: =$K$3 -> 34.216178
A5015: -13.462061 | B5015: =$K$3 -> 34.216178
A5016: -13.462061 | B5016: 0
A5017: -13.368508 | B5017: 0
A5018: -13.368508 | B5018: =$K$3 -> 34.216178
A5019: -13.274956 | B5019: =$K$3 -> 34.216178
A5020: -13.274956 | B5020: 0
A5021: -13.181404 | B5021: 0
A5022: -13.181404 | B5022: =$K$3 -> 34.216178
A5023: -13.087852 | B5023: =$K$3 -> 34.216178
A5024: -13.087852 | B5024: 0
A5025: -12.994299 | B5025: 0
A5026: -12.994299 | B5026: =$K$3 -> 34.216178
A5027: -12.900747 | B5027: =$K$3 -> 34.216178
A5028: -12.900747 | B5028: 0
A5029: -12.807195 | B5029: 0
A5030: -12.807195 | B5030: =$K$3 -> 34.216178
A5031: -12.713643 | B5031: =$K$3 -> 34.216178
A5032: -12.713643 | B5032: 0
A5033: -12.62009 | B5033: 0
A5034: -12.62009 | B5034: =$K$3 -> 34.216178
A5035: -12.526538 | B5035: =$K$3 -> 34.216178
A5036: -12.526538 | B5036: 0
A5037: -12.432986 | B5037: 0
A5038: -12.432986 | B5038: =$K$3 -> 34.216178
A5039: -12.339434 | B5039: =$K$3 -> 34.216178
A5040: -12.339434 | B5040: 0
A5041: -12.245881 | B5041: 0
A5042: -12.245881 | B5042: =$K$3 -> 34.216178
A5043: -12.152329 | B5043: =$K$3 -> 34.216178
A5044: -12.152329 | B5044: 0
A5045: -12.058777 | B5045: 0
A5046: -12.058777 | B5046: =$K$3 -> 34.216178
A5047: -11.965225 | B5047: =$K$3 -> 34.216178
A5048: -11.965225 | B5048: 0
A5049: -11.871673 | B5049: 0
A5050: -11.871673 | B5050: =$K$3 -> 34.216178
A5051: -11.77812 | B5051: =$K$3 -> 34.216178
A5052: -11.77812 | B5052: 0
A5053: -11.684568 | B5053: 0
...

Sheet RiskRGSheet2R11C15
A33: Del X | B33: Del Y | E33: X1 | F33: Y1
A34: -21.618247 | B34: 0.025 | E34: -46.505779 | F34: 0.00055531325
A35: 32.975775 | B35: 0.025 | E35: -42.904208 | F35: 0.00027765663
A36: -40.809123 | B36: 0.025 | E36: -39.302638 | F36: 0.0011106265
A37: 5.6787643 | B37: 0.025 | E37: -35.701067 | F37: 0.0011106265
A38: 46.487888 | B38: 0.025 | E38: -32.099496 | F38: 0.0024989096
E39: -28.497925 | F39: 0.0033318795
E40: -24.896354 | F40: 0.0055531325
E41: -21.294783 | F41: 0.0074967289
E42: -17.693213 | F42: 0.010273295
E43: -14.091642 | F43: 0.013327518
E44: -10.490071 | F44: 0.016381741
E45: -6.8885002 | F45: 0.019435964
E46: -3.2869294 | F46: 0.021657217
E47: 0.31464145 | F47: 0.023600813
E48: 3.9162123 | F48: 0.02387847
E49: 7.5177831 | F49: 0.023323157
E50: 11.119354 | F50: 0.021657217
... E63: 57.939775 | F63: 0
B2501: XFill1 | C2501: NPV STATIC | D2501: XLine1 | E2501: NPV STATIC
B2502: -46.505779 | C2502: =0 -> 0 | D2502: -46.505779 | E2502: 0
B2503: -46.505779 | C2503: =$F$34 -> 0.00055531325 | D2503: -46.505779 | E2503: 0
B2504: -46.087997 | C2504: =$F$34 -> 0.00055531325 | D2504: -46.505779 | E2504: =$F$34 -> 0.00055531325
B2505: -45.670215 | C2505: =$F$34 -> 0.00055531325 | D2505: -42.904208 | E2505: =$F$34 -> 0.00055531325
B2506: -45.252433 | C2506: =$F$34 -> 0.00055531325 | D2506: -42.904208 | E2506: 0
B2507: -44.83465 | C2507: =$F$34 -> 0.00055531325 | D2507: -42.904208 | E2507: =$F$35 -> 0.00027765663
B2508: -44.416868 | C2508: =$F$34 -> 0.00055531325 | D2508: -39.302638 | E2508: =$F$35 -> 0.00027765663
B2509: -43.999086 | C2509: =$F$34 -> 0.00055531325 | D2509: -39.302638 | E2509: 0
B2510: -43.581304 | C2510: =$F$34 -> 0.00055531325 | D2510: -39.302638 | E2510: =$F$36 -> 0.0011106265
B2511: -43.163521 | C2511: =$F$34 -> 0.00055531325 | D2511: -35.701067 | E2511: =$F$36 -> 0.0011106265
B2512: -42.904208 | C2512: =$F$34 -> 0.00055531325 | D2512: -35.701067 | E2512: 0
B2513: -42.904208 | C2513: 0 | D2513: -35.701067 | E2513: =$F$37 -> 0.0011106265
B2514: -42.904208 | C2514: =0 -> 0 | D2514: -32.099496 | E2514: =$F$37 -> 0.0011106265
B2515: -42.904208 | C2515: =$F$35 -> 0.00027765663 | D2515: -32.099496 | E2515: 0
B2516: -42.486426 | C2516: =$F$35 -> 0.00027765663 | D2516: -32.099496 | E2516: =$F$38 -> 0.0024989096
B2517: -42.068644 | C2517: =$F$35 -> 0.00027765663 | D2517: -28.497925 | E2517: =$F$38 -> 0.0024989096
B2518: -41.650862 | C2518: =$F$35 -> 0.00027765663 | D2518: -28.497925 | E2518: 0
B2519: -41.233079 | C2519: =$F$35 -> 0.00027765663 | D2519: -28.497925 | E2519: =$F$39 -> 0.0033318795
B2520: -40.815297 | C2520: =$F$35 -> 0.00027765663 | D2520: -24.896354 | E2520: =$F$39 -> 0.0033318795
B2521: -40.397515 | C2521: =$F$35 -> 0.00027765663 | D2521: -24.896354 | E2521: 0
B2522: -39.979733 | C2522: =$F$35 -> 0.00027765663 | D2522: -24.896354 | E2522: =$F$40 -> 0.0055531325
B2523: -39.561951 | C2523: =$F$35 -> 0.00027765663 | D2523: -21.294783 | E2523: =$F$40 -> 0.0055531325
B2524: -39.302638 | C2524: =$F$35 -> 0.00027765663 | D2524: -21.294783 | E2524: 0
B2525: -39.302638 | C2525: 0 | D2525: -21.294783 | E2525: =$F$41 -> 0.0074967289
B2526: -39.302638 | C2526: =0 -> 0 | D2526: -17.693213 | E2526: =$F$41 -> 0.0074967289
B2527: -39.302638 | C2527: =$F$36 -> 0.0011106265 | D2527: -17.693213 | E2527: 0
B2528: -38.884855 | C2528: =$F$36 -> 0.0011106265 | D2528: -17.693213 | E2528: =$F$42 -> 0.010273295
B2529: -38.467073 | C2529: =$F$36 -> 0.0011106265 | D2529: -14.091642 | E2529: =$F$42 -> 0.010273295
B2530: -38.049291 | C2530: =$F$36 -> 0.0011106265 | D2530: -14.091642 | E2530: 0
B2531: -37.631509 | C2531: =$F$36 -> 0.0011106265 | D2531: -14.091642 | E2531: =$F$43 -> 0.013327518
B2532: -37.213726 | C2532: =$F$36 -> 0.0011106265 | D2532: -10.490071 | E2532: =$F$43 -> 0.013327518
B2533: -36.795944 | C2533: =$F$36 -> 0.0011106265 | D2533: -10.490071 | E2533: 0
B2534: -36.378162 | C2534: =$F$36 -> 0.0011106265 | D2534: -10.490071 | E2534: =$F$44 -> 0.016381741
B2535: -35.96038 | C2535: =$F$36 -> 0.0011106265 | D2535: -6.8885002 | E2535: =$F$44 -> 0.016381741
B2536: -35.701067 | C2536: =$F$36 -> 0.0011106265 | D2536: -6.8885002 | E2536: 0
B2537: -35.701067 | C2537: 0 | D2537: -6.8885002 | E2537: =$F$45 -> 0.019435964
B2538: -35.701067 | C2538: =0 -> 0 | D2538: -3.2869294 | E2538: =$F$45 -> 0.019435964
B2539: -35.701067 | C2539: =$F$37 -> 0.0011106265 | D2539: -3.2869294 | E2539: 0
B2540: -35.283285 | C2540: =$F$37 -> 0.0011106265 | D2540: -3.2869294 | E2540: =$F$46 -> 0.021657217
B2541: -34.865502 | C2541: =$F$37 -> 0.0011106265 | D2541: 0.31464145 | E2541: =$F$46 -> 0.021657217
B2542: -34.44772 | C2542: =$F$37 -> 0.0011106265 | D2542: 0.31464145 | E2542: 0
B2543: -34.029938 | C2543: =$F$37 -> 0.0011106265 | D2543: 0.31464145 | E2543: =$F$47 -> 0.023600813
B2544: -33.612156 | C2544: =$F$37 -> 0.0011106265 | D2544: 3.9162123 | E2544: =$F$47 -> 0.023600813
B2545: -33.194373 | C2545: =$F$37 -> 0.0011106265 | D2545: 3.9162123 | E2545: 0
B2546: -32.776591 | C2546: =$F$37 -> 0.0011106265 | D2546: 3.9162123 | E2546: =$F$48 -> 0.02387847
B2547: -32.358809 | C2547: =$F$37 -> 0.0011106265 | D2547: 7.5177831 | E2547: =$F$48 -> 0.02387847
B2548: -32.099496 | C2548: =$F$37 -> 0.0011106265 | D2548: 7.5177831 | E2548: 0
B2549: -32.099496 | C2549: 0 | D2549: 7.5177831 | E2549: =$F$49 -> 0.023323157
B2550: -32.099496 | C2550: =0 -> 0 | D2550: 11.119354 | E2550: =$F$49 -> 0.023323157
B2551: -32.099496 | C2551: =$F$38 -> 0.0024989096 | D2551: 11.119354 | E2551: 0
B2552: -31.681714 | C2552: =$F$38 -> 0.0024989096 | D2552: 11.119354 | E2552: =$F$50 -> 0.021657217
B2553: -31.263931 | C2553: =$F$38 -> 0.0024989096 | D2553: 14.720925 | E2553: =$F$50 -> 0.021657217
B2554: -30.846149 | C2554: =$F$38 -> 0.0024989096 | D2554: 14.720925 | E2554: 0
B2555: -30.428367 | C2555: =$F$38 -> 0.0024989096 | D2555: 14.720925 | E2555: =$F$51 -> 0.019435964
B2556: -30.010585 | C2556: =$F$38 -> 0.0024989096 | D2556: 18.322496 | E2556: =$F$51 -> 0.019435964
B2557: -29.592803 | C2557: =$F$38 -> 0.0024989096 | D2557: 18.322496 | E2557: 0
B2558: -29.17502 | C2558: =$F$38 -> 0.0024989096 | D2558: 18.322496 | E2558: =$F$52 -> 0.016659398
B2559: -28.757238 | C2559: =$F$38 -> 0.0024989096 | D2559: 21.924066 | E2559: =$F$52 -> 0.016659398
B2560: -28.497925 | C2560: =$F$38 -> 0.0024989096 | D2560: 21.924066 | E2560: 0
B2561: -28.497925 | C2561: 0 | D2561: 21.924066 | E2561: =$F$53 -> 0.013605175
B2562: -28.497925 | C2562: =0 -> 0 | D2562: 25.525637 | E2562: =$F$53 -> 0.013605175
B2563: -28.497925 | C2563: =$F$39 -> 0.0033318795 | D2563: 25.525637 | E2563: 0
B2564: -28.080143 | C2564: =$F$39 -> 0.0033318795 | D2564: 25.525637 | E2564: =$F$54 -> 0.010273295
B2565: -27.662361 | C2565: =$F$39 -> 0.0033318795 | D2565: 29.127208 | E2565: =$F$54 -> 0.010273295
B2566: -27.244578 | C2566: =$F$39 -> 0.0033318795 | D2566: 29.127208 | E2566: 0
B2567: -26.826796 | C2567: =$F$39 -> 0.0033318795 | D2567: 29.127208 | E2567: =$F$55 -> 0.0074967289
B2568: -26.409014 | C2568: =$F$39 -> 0.0033318795 | D2568: 32.728779 | E2568: =$F$55 -> 0.0074967289
B2569: -25.991232 | C2569: =$F$39 -> 0.0033318795 | D2569: 32.728779 | E2569: 0
B2570: -25.57345 | C2570: =$F$39 -> 0.0033318795 | D2570: 32.728779 | E2570: =$F$56 -> 0.0055531325
B2571: -25.155667 | C2571: =$F$39 -> 0.0033318795 | D2571: 36.33035 | E2571: =$F$56 -> 0.0055531325
B2572: -24.896354 | C2572: =$F$39 -> 0.0033318795 | D2572: 36.33035 | E2572: 0
B2573: -24.896354 | C2573: 0 | D2573: 36.33035 | E2573: =$F$57 -> 0.0036095361
B2574: -24.896354 | C2574: =0 -> 0 | D2574: 39.93192 | E2574: =$F$57 -> 0.0036095361
B2575: -24.896354 | C2575: =$F$40 -> 0.0055531325 | D2575: 39.93192 | E2575: 0
B2576: -24.478572 | C2576: =$F$40 -> 0.0055531325 | D2576: 39.93192 | E2576: =$F$58 -> 0.002221253
B2577: -24.06079 | C2577: =$F$40 -> 0.0055531325 | D2577: 43.533491 | E2577: =$F$58 -> 0.002221253
B2578: -23.643008 | C2578: =$F$40 -> 0.0055531325 | D2578: 43.533491 | E2578: 0
B2579: -23.225225 | C2579: =$F$40 -> 0.0055531325 | D2579: 43.533491 | E2579: =$F$59 -> 0.0016659398
B2580: -22.807443 | C2580: =$F$40 -> 0.0055531325 | D2580: 47.135062 | E2580: =$F$59 -> 0.0016659398
B2581: -22.389661 | C2581: =$F$40 -> 0.0055531325 | D2581: 47.135062 | E2581: 0
...

Sheet RiskRGSheet2R29C15
A33: Del X | B33: Del Y | E33: X1 | F33: Y1
A34: -6.6528839 | B34: 0.07 | E34: -8.7413225 | F34: 0.040260721
A35: 32.975775 | B35: 0.07 | E35: -6.0836453 | F35: 0.068857121
A36: -8.3264419 | B36: 0.07 | E36: -3.4259681 | F36: 0.0214473
A37: 13.161446 | B37: 0.07 | E37: -0.76829093 | F37: 0.022576105
A38: 51.487888 | B38: 0.07 | E38: 1.8893863 | F38: 0.02370491
E39: 4.5470635 | F39: 0.024081179
E40: 7.2047407 | F40: 0.02370491
E41: 9.8624179 | F41: 0.022576105
E42: 12.520095 | F42: 0.0214473
E43: 15.177772 | F43: 0.019565958
E44: 17.835449 | F44: 0.017308347
E45: 20.493127 | F45: 0.015050737
E46: 23.150804 | F46: 0.012416858
E47: 25.808481 | F47: 0.010911784
E48: 28.466158 | F48: 0.0082779052
E49: 31.123835 | F49: 0.0067728316
E50: 33.781513 | F50: 0.0048914895
... E63: 68.331316 | F63: 0
B2501: XFill1 | C2501: NPV dynamic | D2501: XLine1 | E2501: NPV dynamic
B2502: -8.7413225 | C2502: =0 -> 0 | D2502: -8.7413225 | E2502: 0
B2503: -8.7413225 | C2503: =$F$34 -> 0.040260721 | D2503: -8.7413225 | E2503: 0
B2504: -8.433032 | C2504: =$F$34 -> 0.040260721 | D2504: -8.7413225 | E2504: =$F$34 -> 0.040260721
B2505: -8.1247414 | C2505: =$F$34 -> 0.040260721 | D2505: -6.0836453 | E2505: =$F$34 -> 0.040260721
B2506: -7.8164509 | C2506: =$F$34 -> 0.040260721 | D2506: -6.0836453 | E2506: 0
B2507: -7.5081603 | C2507: =$F$34 -> 0.040260721 | D2507: -6.0836453 | E2507: =$F$35 -> 0.068857121
B2508: -7.1998698 | C2508: =$F$34 -> 0.040260721 | D2508: -3.4259681 | E2508: =$F$35 -> 0.068857121
B2509: -6.8915792 | C2509: =$F$34 -> 0.040260721 | D2509: -3.4259681 | E2509: 0
B2510: -6.5832886 | C2510: =$F$34 -> 0.040260721 | D2510: -3.4259681 | E2510: =$F$36 -> 0.0214473
B2511: -6.2749981 | C2511: =$F$34 -> 0.040260721 | D2511: -0.76829093 | E2511: =$F$36 -> 0.0214473
B2512: -6.0836453 | C2512: =$F$34 -> 0.040260721 | D2512: -0.76829093 | E2512: 0
B2513: -6.0836453 | C2513: 0 | D2513: -0.76829093 | E2513: =$F$37 -> 0.022576105
B2514: -6.0836453 | C2514: =0 -> 0 | D2514: 1.8893863 | E2514: =$F$37 -> 0.022576105
B2515: -6.0836453 | C2515: =$F$35 -> 0.068857121 | D2515: 1.8893863 | E2515: 0
B2516: -5.7753548 | C2516: =$F$35 -> 0.068857121 | D2516: 1.8893863 | E2516: =$F$38 -> 0.02370491
B2517: -5.4670642 | C2517: =$F$35 -> 0.068857121 | D2517: 4.5470635 | E2517: =$F$38 -> 0.02370491
B2518: -5.1587737 | C2518: =$F$35 -> 0.068857121 | D2518: 4.5470635 | E2518: 0
B2519: -4.8504831 | C2519: =$F$35 -> 0.068857121 | D2519: 4.5470635 | E2519: =$F$39 -> 0.024081179
B2520: -4.5421926 | C2520: =$F$35 -> 0.068857121 | D2520: 7.2047407 | E2520: =$F$39 -> 0.024081179
B2521: -4.233902 | C2521: =$F$35 -> 0.068857121 | D2521: 7.2047407 | E2521: 0
B2522: -3.9256114 | C2522: =$F$35 -> 0.068857121 | D2522: 7.2047407 | E2522: =$F$40 -> 0.02370491
B2523: -3.6173209 | C2523: =$F$35 -> 0.068857121 | D2523: 9.8624179 | E2523: =$F$40 -> 0.02370491
B2524: -3.4259681 | C2524: =$F$35 -> 0.068857121 | D2524: 9.8624179 | E2524: 0
B2525: -3.4259681 | C2525: 0 | D2525: 9.8624179 | E2525: =$F$41 -> 0.022576105
B2526: -3.4259681 | C2526: =0 -> 0 | D2526: 12.520095 | E2526: =$F$41 -> 0.022576105
B2527: -3.4259681 | C2527: =$F$36 -> 0.0214473 | D2527: 12.520095 | E2527: 0
B2528: -3.1176776 | C2528: =$F$36 -> 0.0214473 | D2528: 12.520095 | E2528: =$F$42 -> 0.0214473
B2529: -2.809387 | C2529: =$F$36 -> 0.0214473 | D2529: 15.177772 | E2529: =$F$42 -> 0.0214473
B2530: -2.5010965 | C2530: =$F$36 -> 0.0214473 | D2530: 15.177772 | E2530: 0
B2531: -2.1928059 | C2531: =$F$36 -> 0.0214473 | D2531: 15.177772 | E2531: =$F$43 -> 0.019565958
B2532: -1.8845154 | C2532: =$F$36 -> 0.0214473 | D2532: 17.835449 | E2532: =$F$43 -> 0.019565958
B2533: -1.5762248 | C2533: =$F$36 -> 0.0214473 | D2533: 17.835449 | E2533: 0
B2534: -1.2679342 | C2534: =$F$36 -> 0.0214473 | D2534: 17.835449 | E2534: =$F$44 -> 0.017308347
B2535: -0.95964369 | C2535: =$F$36 -> 0.0214473 | D2535: 20.493127 | E2535: =$F$44 -> 0.017308347
B2536: -0.76829093 | C2536: =$F$36 -> 0.0214473 | D2536: 20.493127 | E2536: 0
B2537: -0.76829093 | C2537: 0 | D2537: 20.493127 | E2537: =$F$45 -> 0.015050737
B2538: -0.76829093 | C2538: =0 -> 0 | D2538: 23.150804 | E2538: =$F$45 -> 0.015050737
B2539: -0.76829093 | C2539: =$F$37 -> 0.022576105 | D2539: 23.150804 | E2539: 0
B2540: -0.46000037 | C2540: =$F$37 -> 0.022576105 | D2540: 23.150804 | E2540: =$F$46 -> 0.012416858
B2541: -0.15170982 | C2541: =$F$37 -> 0.022576105 | D2541: 25.808481 | E2541: =$F$46 -> 0.012416858
B2542: 0.15658074 | C2542: =$F$37 -> 0.022576105 | D2542: 25.808481 | E2542: 0
B2543: 0.46487129 | C2543: =$F$37 -> 0.022576105 | D2543: 25.808481 | E2543: =$F$47 -> 0.010911784
B2544: 0.77316185 | C2544: =$F$37 -> 0.022576105 | D2544: 28.466158 | E2544: =$F$47 -> 0.010911784
B2545: 1.0814524 | C2545: =$F$37 -> 0.022576105 | D2545: 28.466158 | E2545: 0
B2546: 1.389743 | C2546: =$F$37 -> 0.022576105 | D2546: 28.466158 | E2546: =$F$48 -> 0.0082779052
B2547: 1.6980335 | C2547: =$F$37 -> 0.022576105 | D2547: 31.123835 | E2547: =$F$48 -> 0.0082779052
B2548: 1.8893863 | C2548: =$F$37 -> 0.022576105 | D2548: 31.123835 | E2548: 0
B2549: 1.8893863 | C2549: 0 | D2549: 31.123835 | E2549: =$F$49 -> 0.0067728316
B2550: 1.8893863 | C2550: =0 -> 0 | D2550: 33.781513 | E2550: =$F$49 -> 0.0067728316
B2551: 1.8893863 | C2551: =$F$38 -> 0.02370491 | D2551: 33.781513 | E2551: 0
B2552: 2.1976768 | C2552: =$F$38 -> 0.02370491 | D2552: 33.781513 | E2552: =$F$50 -> 0.0048914895
B2553: 2.5059674 | C2553: =$F$38 -> 0.02370491 | D2553: 36.43919 | E2553: =$F$50 -> 0.0048914895
B2554: 2.8142579 | C2554: =$F$38 -> 0.02370491 | D2554: 36.43919 | E2554: 0
B2555: 3.1225485 | C2555: =$F$38 -> 0.02370491 | D2555: 36.43919 | E2555: =$F$51 -> 0.0041389526
B2556: 3.430839 | C2556: =$F$38 -> 0.02370491 | D2556: 39.096867 | E2556: =$F$51 -> 0.0041389526
B2557: 3.7391296 | C2557: =$F$38 -> 0.02370491 | D2557: 39.096867 | E2557: 0
B2558: 4.0474202 | C2558: =$F$38 -> 0.02370491 | D2558: 39.096867 | E2558: =$F$52 -> 0.0022576105
B2559: 4.3557107 | C2559: =$F$38 -> 0.02370491 | D2559: 41.754544 | E2559: =$F$52 -> 0.0022576105
B2560: 4.5470635 | C2560: =$F$38 -> 0.02370491 | D2560: 41.754544 | E2560: 0
B2561: 4.5470635 | C2561: 0 | D2561: 41.754544 | E2561: =$F$53 -> 0.0022576105
B2562: 4.5470635 | C2562: =0 -> 0 | D2562: 44.412221 | E2562: =$F$53 -> 0.0022576105
B2563: 4.5470635 | C2563: =$F$39 -> 0.024081179 | D2563: 44.412221 | E2563: 0
B2564: 4.855354 | C2564: =$F$39 -> 0.024081179 | D2564: 44.412221 | E2564: =$F$54 -> 0.0015050737
B2565: 5.1636446 | C2565: =$F$39 -> 0.024081179 | D2565: 47.069899 | E2565: =$F$54 -> 0.0015050737
B2566: 5.4719351 | C2566: =$F$39 -> 0.024081179 | D2566: 47.069899 | E2566: 0
B2567: 5.7802257 | C2567: =$F$39 -> 0.024081179 | D2567: 47.069899 | E2567: =$F$55 -> 0.00075253684
B2568: 6.0885162 | C2568: =$F$39 -> 0.024081179 | D2568: 49.727576 | E2568: =$F$55 -> 0.00075253684
B2569: 6.3968068 | C2569: =$F$39 -> 0.024081179 | D2569: 49.727576 | E2569: 0
B2570: 6.7050974 | C2570: =$F$39 -> 0.024081179 | D2570: 49.727576 | E2570: =$F$56 -> 0.00075253684
B2571: 7.0133879 | C2571: =$F$39 -> 0.024081179 | D2571: 52.385253 | E2571: =$F$56 -> 0.00075253684
B2572: 7.2047407 | C2572: =$F$39 -> 0.024081179 | D2572: 52.385253 | E2572: 0
B2573: 7.2047407 | C2573: 0 | D2573: 52.385253 | E2573: =$F$57 -> 0.00037626842
B2574: 7.2047407 | C2574: =0 -> 0 | D2574: 55.04293 | E2574: =$F$57 -> 0.00037626842
B2575: 7.2047407 | C2575: =$F$40 -> 0.02370491 | D2575: 55.04293 | E2575: 0
B2576: 7.5130312 | C2576: =$F$40 -> 0.02370491 | D2576: 55.04293 | E2576: =$F$58 -> 0
B2577: 7.8213218 | C2577: =$F$40 -> 0.02370491 | D2577: 57.700607 | E2577: =$F$58 -> 0
B2578: 8.1296123 | C2578: =$F$40 -> 0.02370491 | D2578: 57.700607 | E2578: 0
B2579: 8.4379029 | C2579: =$F$40 -> 0.02370491 | D2579: 57.700607 | E2579: =$F$59 -> 0
B2580: 8.7461934 | C2580: =$F$40 -> 0.02370491 | D2580: 60.358285 | E2580: =$F$59 -> 0
B2581: 9.054484 | C2581: =$F$40 -> 0.02370491 | D2581: 60.358285 | E2581: 0
...

Sheet RiskRGDynamic ModelR12C15
A33: Del X | B33: Del Y | E33: X1 | F33: Y1
A34: -20.191458 | B34: 0.025 | E34: -53.42095 | F34: 0.00024084441
A35: 35.034651 | B35: 0.025 | E35: -49.268891 | F35: 0
A36: -40.095729 | B36: 0.025 | E36: -45.116833 | F36: 0.00024084441
A37: 7.4215965 | B37: 0.025 | E37: -40.964775 | F37: 0.00048168883
A38: 57.517325 | B38: 0.025 | E38: -36.812717 | F38: 0.00096337765
E39: -32.660659 | F39: 0.0019267553
E40: -28.508601 | F40: 0.0031309774
E41: -24.356543 | F41: 0.0048168883
E42: -20.204485 | F42: 0.0072253324
E43: -16.052426 | F43: 0.010597154
E44: -11.900368 | F44: 0.013728132
E45: -7.7483101 | F45: 0.017340798
E46: -3.596252 | F46: 0.020712619
E47: 0.55580611 | F47: 0.022639375
E48: 4.7078642 | F48: 0.023843597
E49: 8.8599224 | F49: 0.023361908
E50: 13.01198 | F50: 0.021194308
... E63: 66.988736 | F63: 0
B2501: XFill1 | C2501: NPV STATIC | D2501: XLine1 | E2501: NPV STATIC
B2502: -53.42095 | C2502: =0 -> 0 | D2502: -53.42095 | E2502: 0
B2503: -53.42095 | C2503: =$F$34 -> 0.00024084441 | D2503: -53.42095 | E2503: 0
B2504: -52.939311 | C2504: =$F$34 -> 0.00024084441 | D2504: -53.42095 | E2504: =$F$34 -> 0.00024084441
B2505: -52.457672 | C2505: =$F$34 -> 0.00024084441 | D2505: -49.268891 | E2505: =$F$34 -> 0.00024084441
B2506: -51.976033 | C2506: =$F$34 -> 0.00024084441 | D2506: -49.268891 | E2506: 0
B2507: -51.494395 | C2507: =$F$34 -> 0.00024084441 | D2507: -49.268891 | E2507: =$F$35 -> 0
B2508: -51.012756 | C2508: =$F$34 -> 0.00024084441 | D2508: -45.116833 | E2508: =$F$35 -> 0
B2509: -50.531117 | C2509: =$F$34 -> 0.00024084441 | D2509: -45.116833 | E2509: 0
B2510: -50.049478 | C2510: =$F$34 -> 0.00024084441 | D2510: -45.116833 | E2510: =$F$36 -> 0.00024084441
B2511: -49.56784 | C2511: =$F$34 -> 0.00024084441 | D2511: -40.964775 | E2511: =$F$36 -> 0.00024084441
B2512: -49.268891 | C2512: =$F$34 -> 0.00024084441 | D2512: -40.964775 | E2512: 0
B2513: -49.268891 | C2513: 0 | D2513: -40.964775 | E2513: =$F$37 -> 0.00048168883
B2514: -49.268891 | C2514: =0 -> 0 | D2514: -36.812717 | E2514: =$F$37 -> 0.00048168883
B2515: -49.268891 | C2515: =$F$35 -> 0 | D2515: -36.812717 | E2515: 0
B2516: -48.787253 | C2516: =$F$35 -> 0 | D2516: -36.812717 | E2516: =$F$38 -> 0.00096337765
B2517: -48.305614 | C2517: =$F$35 -> 0 | D2517: -32.660659 | E2517: =$F$38 -> 0.00096337765
B2518: -47.823975 | C2518: =$F$35 -> 0 | D2518: -32.660659 | E2518: 0
B2519: -47.342336 | C2519: =$F$35 -> 0 | D2519: -32.660659 | E2519: =$F$39 -> 0.0019267553
B2520: -46.860698 | C2520: =$F$35 -> 0 | D2520: -28.508601 | E2520: =$F$39 -> 0.0019267553
B2521: -46.379059 | C2521: =$F$35 -> 0 | D2521: -28.508601 | E2521: 0
B2522: -45.89742 | C2522: =$F$35 -> 0 | D2522: -28.508601 | E2522: =$F$40 -> 0.0031309774
B2523: -45.415781 | C2523: =$F$35 -> 0 | D2523: -24.356543 | E2523: =$F$40 -> 0.0031309774
B2524: -45.116833 | C2524: =$F$35 -> 0 | D2524: -24.356543 | E2524: 0
B2525: -45.116833 | C2525: 0 | D2525: -24.356543 | E2525: =$F$41 -> 0.0048168883
B2526: -45.116833 | C2526: =0 -> 0 | D2526: -20.204485 | E2526: =$F$41 -> 0.0048168883
B2527: -45.116833 | C2527: =$F$36 -> 0.00024084441 | D2527: -20.204485 | E2527: 0
B2528: -44.635195 | C2528: =$F$36 -> 0.00024084441 | D2528: -20.204485 | E2528: =$F$42 -> 0.0072253324
B2529: -44.153556 | C2529: =$F$36 -> 0.00024084441 | D2529: -16.052426 | E2529: =$F$42 -> 0.0072253324
B2530: -43.671917 | C2530: =$F$36 -> 0.00024084441 | D2530: -16.052426 | E2530: 0
B2531: -43.190278 | C2531: =$F$36 -> 0.00024084441 | D2531: -16.052426 | E2531: =$F$43 -> 0.010597154
B2532: -42.70864 | C2532: =$F$36 -> 0.00024084441 | D2532: -11.900368 | E2532: =$F$43 -> 0.010597154
B2533: -42.227001 | C2533: =$F$36 -> 0.00024084441 | D2533: -11.900368 | E2533: 0
B2534: -41.745362 | C2534: =$F$36 -> 0.00024084441 | D2534: -11.900368 | E2534: =$F$44 -> 0.013728132
B2535: -41.263723 | C2535: =$F$36 -> 0.00024084441 | D2535: -7.7483101 | E2535: =$F$44 -> 0.013728132
B2536: -40.964775 | C2536: =$F$36 -> 0.00024084441 | D2536: -7.7483101 | E2536: 0
B2537: -40.964775 | C2537: 0 | D2537: -7.7483101 | E2537: =$F$45 -> 0.017340798
B2538: -40.964775 | C2538: =0 -> 0 | D2538: -3.596252 | E2538: =$F$45 -> 0.017340798
B2539: -40.964775 | C2539: =$F$37 -> 0.00048168883 | D2539: -3.596252 | E2539: 0
B2540: -40.483136 | C2540: =$F$37 -> 0.00048168883 | D2540: -3.596252 | E2540: =$F$46 -> 0.020712619
B2541: -40.001498 | C2541: =$F$37 -> 0.00048168883 | D2541: 0.55580611 | E2541: =$F$46 -> 0.020712619
B2542: -39.519859 | C2542: =$F$37 -> 0.00048168883 | D2542: 0.55580611 | E2542: 0
B2543: -39.03822 | C2543: =$F$37 -> 0.00048168883 | D2543: 0.55580611 | E2543: =$F$47 -> 0.022639375
B2544: -38.556581 | C2544: =$F$37 -> 0.00048168883 | D2544: 4.7078642 | E2544: =$F$47 -> 0.022639375
B2545: -38.074943 | C2545: =$F$37 -> 0.00048168883 | D2545: 4.7078642 | E2545: 0
B2546: -37.593304 | C2546: =$F$37 -> 0.00048168883 | D2546: 4.7078642 | E2546: =$F$48 -> 0.023843597
B2547: -37.111665 | C2547: =$F$37 -> 0.00048168883 | D2547: 8.8599224 | E2547: =$F$48 -> 0.023843597
B2548: -36.812717 | C2548: =$F$37 -> 0.00048168883 | D2548: 8.8599224 | E2548: 0
B2549: -36.812717 | C2549: 0 | D2549: 8.8599224 | E2549: =$F$49 -> 0.023361908
B2550: -36.812717 | C2550: =0 -> 0 | D2550: 13.01198 | E2550: =$F$49 -> 0.023361908
B2551: -36.812717 | C2551: =$F$38 -> 0.00096337765 | D2551: 13.01198 | E2551: 0
B2552: -36.331078 | C2552: =$F$38 -> 0.00096337765 | D2552: 13.01198 | E2552: =$F$50 -> 0.021194308
B2553: -35.84944 | C2553: =$F$38 -> 0.00096337765 | D2553: 17.164039 | E2553: =$F$50 -> 0.021194308
B2554: -35.367801 | C2554: =$F$38 -> 0.00096337765 | D2554: 17.164039 | E2554: 0
B2555: -34.886162 | C2555: =$F$38 -> 0.00096337765 | D2555: 17.164039 | E2555: =$F$51 -> 0.018785864
B2556: -34.404523 | C2556: =$F$38 -> 0.00096337765 | D2556: 21.316097 | E2556: =$F$51 -> 0.018785864
B2557: -33.922885 | C2557: =$F$38 -> 0.00096337765 | D2557: 21.316097 | E2557: 0
B2558: -33.441246 | C2558: =$F$38 -> 0.00096337765 | D2558: 21.316097 | E2558: =$F$52 -> 0.015173198
B2559: -32.959607 | C2559: =$F$38 -> 0.00096337765 | D2559: 25.468155 | E2559: =$F$52 -> 0.015173198
B2560: -32.660659 | C2560: =$F$38 -> 0.00096337765 | D2560: 25.468155 | E2560: 0
